Workbook

Sheet old
A1: 4 | B1: 2 | C1: 3 | D1: 4 | E1: 5 | F1: 6 | G1: 7 | H1: 8 | I1: 9 | J1: 10 | K1: 11 | L1: 12 | M1: 13 | N1: 14 | O1: 15 | P1: 16 | Q1: 17 | R1: 18 | S1: 19 | T1: 20 | U1: 21 | V1: 22 | W1: 23 | X1: 24 | Y1: 25 | Z1: 26 | AA1: 27 | AB1: 28 | AC1: 29 | AD1: 30 | AE1: 31 | AF1: 32 | AG1: 33 | AH1: 34 | AI1: 35 | AJ1: 36 | AK1: 37 | AL1: 38 | AM1: 39 | AN1: 40 | AO1: 41 | AP1: 42 | AQ1: 43 | AR1: 44 | AS1: 45 | AT1: 46 | AU1: 47 | AV1: 48 | AW1: 49
A2: inn | B2: id | C2: name | D2: inn | E2: ogrn | F2: name_light | G2: date_register | H2: working_years | I2: napka | J2: founder | K2: director | L2: adress | M2: capital | N2: agent | O2: raiting_get_a | P2: cess | Q2: raiting_get_c | R2: income2020 | S2: income2021 | T2: income2022 | U2: income2023 | V2: income2024 | W2: cost2020 | X2: cost2021 | Y2: cost2022 | Z2: cost2023 | AA2: cost2024 | AB2: profit2020 | AC2: profit2021 | AD2: profit2022 | AE2: profit2023 | AF2: profit2024 | AG2: invest2020 | AH2: invest2021 | AI2: invest2022 | AJ2: invest2023 | AK2: invest2024 | AL2: receivable2020 | AM2: receivable2021 | AN2: receivable2022 | AO2: receivable2023 | AP2: receivable2024 | AQ2: loan | AR2: grow_income_2019_2023 | AS2: risk_fssp | AT2: site | AU2: logo | AV2: temp_grow_2019_2023 | AW2: description
A3: 7735174895 | B3: 24 | C3: Общество с ограниченной ответственностью Профессиональная коллекторская организация «Гольфстрим-Р» | D3: 7735174895 | E3: 1187746489204 | F3: ООО ПКО «Гольфстрим-Р» | G3: 43238 | H3: 6 | I3: Нет | J3: Топкаев Роберт Анатольевич, Сирота Георгий Витальевич, Литвак Игорь Маркович | K3: Побожая Ирина Валерьевна | L3: 125009, Москва г, пер Большой Кисловский, д. 4, стр. 3, этаж 1, помещ. 22 | M3: 10010 | R3: 122430 | S3: 432052 | T3: 793479 | U3: 829409 | W3: 85562 | X3: 332275 | Y3: 614066 | Z3: 699868 | AB3: 85562 | AC3: 8256 | AD3: 11659 | AE3: -40805 | AG3: 0 | AH3: 447519 | AI3: 516670 | AJ3: 416339 | AL3: 241035 | AM3: 57166 | AN3: 88319 | AO3: 76206 | AS3: 0 | AT3: golfstream0r.ru | AU3: image344 | AW3: ООО ПКО «Гольфстрим-Р» зарегистрировано по адресу: 125009, Москва г, пер Большой Кисловский, д. 4, стр. 3, этаж 1, помещ. 22. Генеральным директором является Побожая Ирина Валерьевна.
A4: 5407980426 | B4: 231 | C4: Общество с ограниченной ответственностью «ИнтИнвест» | D4: 5407980426 | E4: 1215400000254 | F4: ООО «ИнтИнвест» | G4: 44209 | H4: 4 | I4: Нет | J4: Перехожев Алексей Александрович | K4: Перехожев Алексей Александрович | L4: Новосибирская обл., г.о. город Новосибирск, г. Новосибирск, ул. Фабричная, д. 4, ОФИС 412, 630007 | M4: 26.665 | R4: 0 | S4: 64318 | T4: 90885 | U4: 4384 | W4: 0 | X4: 44387 | Y4: 73283 | Z4: 34379 | AB4: 0 | AC4: 3719 | AD4: 545 | AE4: -32934 | AG4: 0 | AH4: 90871 | AI4: 34191 | AJ4: 4080 | AL4: 0 | AM4: 71255 | AN4: 55608 | AO4: 1076 | AS4: Высокий | AT4: intcollect.ru | AU4: image1001 | AW4: ООО «ИнтИнвест» зарегистрировано по адресу: Новосибирская обл., г.о. город Новосибирск, г. Новосибирск, ул. Фабричная, д. 4, ОФИС 412, 630007. Генеральным директором является Перехожев Алексей Александрович. ФССП присвоил Высокий уровень риска для данного ПКО.
A5: 9723118667 | B5: 390 | C5: Общество с ограниченной ответственностью «Инфорс-Право» | D5: 9723118667 | E5: 1217700289377 | F5: ООО «Инфорс-Право» | G5: 44365 | H5: 3 | I5: Нет | J5: Варлыгин Евгений Валерьевич | K5: Варлыгин Евгений Валерьевич | L5: 109341, Москва г, ул Люблинская, 151, Этаж 2 Помещ. 201 | M5: 10 | R5: 0 | S5: 0 | T5: 2400 | U5: 4800 | W5: 0 | X5: 133 | Y5: 48 | Z5: 82 | AB5: 0 | AC5: -2399 | AD5: -1413 | AE5: 1361 | AG5: 0 | AH5: 0 | AI5: 0 | AJ5: 0 | AL5: 0 | AM5: 21 | AN5: 673 | AO5: 1875 | AS5: Низкий | AT5: enfpv.ru | AU5: image1001 | AW5: ООО «Инфорс-Право» зарегистрировано по адресу: 109341, Москва г, ул Люблинская, 151, Этаж 2 Помещ. 201. Генеральным директором является Варлыгин Евгений Валерьевич. ФССП присвоил Низкий уровень риска для данного ПКО.
A6: 7813484544 | B6: 405 | C6: Общество с ограниченной ответственностью «Профессиональная коллекторская организация «Юридическая безопасность бизнеса» | D6: 7813484544 | E6: 1107847355000 | F6: ООО «ПКО «ЮББ» | G6: 40473 | H6: 14 | I6: Нет | J6: Лаврова Ольга Игоревна | K6: Семёнов Максим Валерьевич | L6: 197110, Город Санкт-Петербург, пр-кт Левашовский, дом 12, литер А, комната 356 | M6: 9000 | R6: 82350 | S6: 4288 | T6: 2354 | U6: 3988 | W6: 77443 | X6: 737 | Y6: 956 | Z6: 57 | AB6: 77443 | AC6: 1265 | AD6: 63 | AE6: 7 | AG6: 35252 | AH6: 30718 | AI6: 29280 | AJ6: 26237 | AL6: 163 | AM6: 125 | AN6: 102 | AO6: 119 | AS6: Низкий | AT6: ubbltd.ru | AU6: image221 | AW6: ООО «ПКО «ЮББ» зарегистрировано по адресу: 197110, Город Санкт-Петербург, пр-кт Левашовский, дом 12, литер А, комната 356. Генеральным директором является Семёнов Максим Валерьевич. ФССП присвоил Низкий уровень риска для данного ПКО.
A7: 6686116656 | B7: 421 | C7: Общество с ограниченной ответственностью «РЕГОЛА» | D7: 6686116656 | E7: 1196658043900 | F7: ООО «РЕГОЛА» | G7: 43637 | H7: 5 | I7: Нет | J7: Прокопьев Александр Валерьевич | K7: Прокопьев Александр Валерьевич | L7: 620057, Свердловская обл, г Екатеринбург, ул Фрезеровщиков, 78, 71 | M7: 20 | R7: 26382 | S7: 59707 | T7: 2311 | U7: 2810 | W7: 337 | X7: 7122 | Y7: 1565 | Z7: 2441 | AB7: 337 | AC7: 52523 | AD7: 694 | AE7: 341 | AG7: 0 | AH7: 0 | AI7: 0 | AJ7: 0 | AL7: 25339 | AM7: 82920 | AN7: 82441 | AO7: 83054 | AS7: Низкий | AT7: regolaek.ru | AU7: image1001 | AW7: ООО «РЕГОЛА» зарегистрировано по адресу: 620057, Свердловская обл, г Екатеринбург, ул Фрезеровщиков, 78, 71. Генеральным директором является Прокопьев Александр Валерьевич. ФССП присвоил Низкий уровень риска для данного ПКО.
A8: 7722466428 | B8: 425 | C8: Общество с ограниченной ответственностью «Кредо Финанс» | D8: 7722466428 | E8: 1187746783355 | F8: ООО «Кредо Финанс» | G8: 43341 | H8: 6 | I8: Нет | J8: Федюков Владимир Константинович | K8: Федюков Владимир Константинович | L8: 123290, Москва г, Ермакова Роща ул, дом 7Б, строение 6, офис 3/9 | M8: 250 | R8: 1761 | S8: 2955 | T8: 3220 | U8: 2381 | W8: 1482 | X8: 1770 | Y8: 2948 | Z8: 1712 | AB8: 1482 | AC8: 1071 | AD8: 182 | AE8: 622 | AG8: 0 | AH8: 0 | AI8: 0 | AJ8: 0 | AL8: 18460 | AM8: 16323 | AN8: 16636 | AO8: 20075 | AS8: Высокий | AT8: crfinance.ru | AU8: image1001 | AW8: ООО «Кредо Финанс» зарегистрировано по адресу: 123290, Москва г, Ермакова Роща ул, дом 7Б, строение 6, офис 3/9. Генеральным директором является Федюков Владимир Константинович. ФССП присвоил Высокий уровень риска для данного ПКО.
A9: 3702724465 | B9: 456 | C9: Общество с ограниченной ответственностью «Компания региональный Долговой Центр» | D9: 3702724465 | E9: 1143702006931 | F9: ООО «КРДЦ» | G9: 45603 | H9: 0 | I9: Нет | L9: 153013, Ивановская обл, г Иваново, ул Панина, 16а Дом | M9: 10 | R9: 9778 | S9: 2960 | T9: 146 | U9: 371 | W9: 9338 | X9: 4083 | Y9: 645 | Z9: 11824 | AB9: 9338 | AC9: -1174 | AD9: -503 | AE9: -11461 | AG9: 33 | AH9: 0 | AI9: 0 | AJ9: 0 | AL9: 12392 | AM9: 11766 | AN9: 11392 | AO9: 234 | AS9: Низкий | AT9: regiondolg.ru | AU9: image274 | AW9: ООО «КРДЦ» зарегистрировано по адресу: 153013, Ивановская обл, г Иваново, ул Панина, 16а Дом
A10: 3443147600 | B10: 459 | C10: Общество с ограниченной ответственностью «ПРОФЕССИОНАЛЬНАЯ КОЛЛЕКТОРСКАЯ ОРГАНИЗАЦИЯ «АРРИАРС» | D10: 3443147600 | E10: 1213400010042 | F10: ООО «ПКО «АРРИАРС» | G10: 44483 | H10: 3 | I10: Нет | J10: Казаков Олег Олегович, Сабиров Салават Рифович | K10: Чередник Вадим Викторович | L10: Волгоградская обл, историческая, д. № 181 | M10: 10 | R10: 0 | S10: 0 | T10: 13467 | U10: 269 | W10: 0 | X10: 0 | Y10: 11890 | Z10: 79 | AB10: 0 | AC10: 0 | AD10: 761 | AE10: 174 | AG10: 0 | AH10: 0 | AI10: 0 | AJ10: 0 | AL10: 0 | AM10: 587 | AN10: 9341 | AO10: 14822 | AS10: Низкий | AT10: arriars.ru | AU10: image1001 | AW10: ООО «ПКО «АРРИАРС» зарегистрировано по адресу: Волгоградская обл, историческая, д. № 181. Генеральным директором является Чередник Вадим Викторович. ФССП присвоил Низкий уровень риска для данного ПКО.
A11: 7810450515 | B11: 467 | C11: Общество с ограниченной ответственностью «Группа компаний «Юрфининвест» | D11: 7810450515 | E11: 1137847308642 | F11: ООО «ГК «Юрфининвест» | G11: 45666 | H11: 0 | I11: Нет | L11: 115088, Москва г, 2-Я Машиностроения ул, дом 17, строение 1, этаж 2, помещение I, комната 63, офис 60 | M11: 10 | R11: 829 | S11: 18783 | T11: 11100 | U11: 12 | W11: 1114 | X11: 1673 | Y11: 17057 | Z11: 80 | AB11: 1114 | AC11: 16556 | AD11: -5957 | AE11: -69 | AG11: 0 | AH11: 0 | AI11: 0 | AJ11: 0 | AL11: 16854 | AM11: 28285 | AN11: 20661 | AO11: 20670 | AS11: 0 | AT11: gk0ufi.ru | AU11: image1001 | AW11: ООО «ГК «Юрфининвест» зарегистрировано по адресу: 115088, Москва г, 2-Я Машиностроения ул, дом 17, строение 1, этаж 2, помещение I, комната 63, офис 60
A12: 4027143645 | B12: 470 | C12: Общество с ограниченной ответственностью Профессиональная коллекторская организация «РУСФИНАЛЬЯНС» | D12: 4027143645 | E12: 1204000005263 | F12: ООО ПКО «РУСФИНАЛЬЯНС» | G12: 44028 | H12: 4 | I12: Нет | J12: Зигель Сильвио | K12: Карасев Владимир Николаевич | L12: 248002, Калужская область, г. Калуга, ул. Болдина, здание 71, офис 213 | M12: 20 | R12: 50 | S12: 10116 | T12: 29 | U12: 4 | W12: 61 | X12: 10577 | Y12: 1091 | Z12: 113 | AB12: 61 | AC12: -468 | AD12: -1065 | AE12: -109 | AG12: 0 | AH12: 0 | AI12: 0 | AJ12: 0 | AL12: 310 | AM12: 17017 | AN12: 20062 | AO12: 20046 | AS12: Низкий | AT12: rus0finalyans.ru | AU12: image323 | AW12: ООО ПКО «РУСФИНАЛЬЯНС» зарегистрировано по адресу: 248002, Калужская область, г. Калуга, ул. Болдина, здание 71, офис 213. Генеральным директором является Карасев Владимир Николаевич. ФССП присвоил Низкий уровень риска для данного ПКО.
A13: 7736602060 | B13: 474 | C13: Общество с ограниченной ответственностью «Центр ЮСБ-М» | D13: 7736602060 | E13: 1097746188924 | F13: ООО «Центр ЮСБ-М» | G13: 45365 | H13: 1 | I13: Нет | L13: 117335, Москва г, Вавилова ул, дом 79, корпус 1, офис 4 | M13: 100 | R13: 77858 | S13: 94870 | T13: 121679 | U13: 64790 | W13: 1579 | X13: 40194 | Y13: 55682 | Z13: 32250 | AB13: 1579 | AC13: 50381 | AD13: 60627 | AE13: 30850 | AG13: 37035 | AH13: 38095 | AI13: 46000 | AJ13: 43500 | AL13: 8413 | AM13: 10720 | AN13: 8275 | AO13: 122 | AS13: Низкий | AT13: usb0m.ru | AU13: image1001 | AW13: ООО «Центр ЮСБ-М» зарегистрировано по адресу: 117335, Москва г, Вавилова ул, дом 79, корпус 1, офис 4
A14: 7717777530 | B14: 477 | C14: Общество с ограниченной ответственностью «Прайм Коллекшен» | D14: 7717777530 | E14: 1147746200062 | F14: ООО «Прайм Коллекшен» | G14: 45485 | H14: 0 | I14: Нет | L14: Москва г, ш.Дмитровское, д.100, стр.2ПОМ.4506, кв.05, 127247 | M14: 12.5 | R14: 17644 | S14: 16208 | T14: 15525 | U14: 0 | W14: 9894 | X14: 8607 | Y14: 6073 | Z14: 0 | AB14: 9894 | AC14: 7070 | AD14: 9018 | AE14: 0 | AG14: 0 | AH14: 0 | AI14: 0 | AJ14: 0 | AL14: 11129 | AM14: 18509 | AN14: 26030 | AO14: 0 | AS14: 0 | AT14: primecollection.ru | AU14: image1001 | AW14: ООО «Прайм Коллекшен» зарегистрировано по адресу: Москва г, ш.Дмитровское, д.100, стр.2ПОМ.4506, кв.05, 127247
A15: 5038126322 | B15: 481 | C15: Общество с ограниченной ответственностью «Профессиональное коллекторское бюро» | D15: 5038126322 | E15: 1175050002357 | F15: ООО «Профессиональное Коллекторское Бюро» | G15: 42809 | H15: 8 | I15: Нет | J15: Ганелин Владислав Дмитриевич, Штрафов | K15: Ганелин Владислав Дмитриевич | L15: 143404, Московская обл, г.о. Красногорск, г Красногорск, ул Парковая, д. 1, кв. эт/пом цоколь/5 | M15: 11710 | R15: 266 | S15: 0 | T15: 0 | U15: 0 | W15: 11 | X15: 0 | Y15: 0 | Z15: 0 | AB15: 11 | AC15: 0 | AD15: 0 | AE15: 0 | AG15: 44001 | AH15: 0 | AI15: 0 | AJ15: 0 | AL15: 74180 | AM15: 0 | AN15: 0 | AO15: 0 | AS15: Низкий | AT15: prof0coll.ru | AU15: image1001 | AW15: ООО «Профессиональное Коллекторское Бюро» зарегистрировано по адресу: 143404, Московская обл, г.о. Красногорск, г Красногорск, ул Парковая, д. 1, кв. эт/пом цоколь/5. Генеральным директором является Ганелин Владислав Дмитриевич. ФССП присвоил Низкий уровень риска для данного ПКО.
A16: 2130218594 | B16: 486 | C16: Акционерное общество «Профессиональная коллекторская организация «Инвест Групп» | D16: 2130218594 | E16: 1202100003665 | F16: АО «Профессиональная коллекторская организация «Инвест Групп» | G16: 45425 | H16: 0 | I16: Нет | L16: 198206, Город Санкт-Петербург, вн.тер. г. Муниципальный Округ Сосновая Поляна, ш Петергофское, дом 73, литера Т, помещение 1-Н, офис 17/4 РАБОЧЕЕ МЕСТО 3 | M16: 10 | R16: 0 | S16: 0 | T16: 0 | U16: 0 | W16: 0 | X16: 0 | Y16: 0 | Z16: 71 | AB16: 0 | AC16: 0 | AD16: 0 | AE16: -73 | AG16: 0 | AH16: 9000 | AI16: 9000 | AJ16: 10979 | AL16: 0 | AM16: 0 | AN16: 0 | AO16: 1442 | AS16: Низкий | AT16: invest0gr.ru.com | AU16: image1001 | AW16: АО «Профессиональная коллекторская организация «Инвест Групп» зарегистрировано по адресу: 198206, Город Санкт-Петербург, вн.тер. г. Муниципальный Округ Сосновая Поляна, ш Петергофское, дом 73, литера Т, помещение 1-Н, офис 17/4 РАБОЧЕЕ МЕСТО 3
A17: 7813286084 | B17: 490 | C17: Общество с ограниченной ответственностью «Центр АвтоФинансовых технологий» | D17: 7813286084 | E17: 1177847277255 | F17: ООО «ЦАФТ» | G17: 45378 | H17: 1 | I17: Нет | L17: 196084, Санкт-Петербург г, ул Черниговская, д. 8, литера А, помещ. 29Н, 81Н | M17: 10000 | R17: 3626480 | S17: 4020218 | T17: 8094908 | U17: 41399 | W17: 2862766 | X17: 3342565 | Y17: 7932887 | Z17: 54536 | AB17: 2862766 | AC17: 23848 | AD17: -13354 | AE17: -12005 | AG17: 5159588 | AH17: 7739045 | AI17: 12388 | AJ17: 5221 | AL17: 63069 | AM17: 125557 | AN17: 10150 | AO17: 248 | AS17: Низкий | AT17: caftauto.ru | AU17: image1001 | AW17: ООО «ЦАФТ» зарегистрировано по адресу: 196084, Санкт-Петербург г, ул Черниговская, д. 8, литера А, помещ. 29Н, 81Н
A18: 4101167155 | B18: 510 | C18: Общество с ограниченной ответственностью Профессиональная коллекторская организация «Правовой консалтинг» | D18: 4101167155 | E18: 1144101035924 | F18: ООО ПКО «Правовой консалтинг» | G18: 42001 | H18: 10 | I18: Нет | J18: Ван Чунвэнь | K18: Ломов Иван Викторович | L18: 683002, г.Петропавловск-Камчатский, ул.Виталия Кручины, д.6, кв.36 | M18: 10 | R18: 0 | S18: 0 | T18: 0 | U18: 0 | W18: 0 | X18: 0 | Y18: 0 | Z18: 0 | AB18: 0 | AC18: 0 | AD18: 0 | AE18: 0 | AG18: 0 | AH18: 0 | AI18: 0 | AJ18: 0 | AL18: 0 | AM18: 0 | AN18: 0 | AO18: 0 | AS18: Низкий | AT18: consult41.ru | AU18: image1001 | AW18: ООО ПКО «Правовой консалтинг» зарегистрировано по адресу: 683002, г.Петропавловск-Камчатский, ул.Виталия Кручины, д.6, кв.36. Генеральным директором является Ломов Иван Викторович. ФССП присвоил Низкий уровень риска для данного ПКО.
A19: 9705066046 | B19: 535 | C19: Общество с ограниченной ответственностью «КВЕСТОР» | D19: 9705066046 | E19: 1167746430125 | F19: ООО «КВЕСТОР» | G19: 45409 | H19: 0 | I19: Нет | J19: Филатов Данил Анатольевич | K19: Глаголев Роман Анатольевич | L19: 125252, Москва г, вн.тер.г. муниципальный округ Хорошевский, ул Авиаконструктора Микояна, д. 12, помещ. Б | M19: 8010 | R19: 33695 | S19: 504039 | T19: 201666 | U19: 155398 | W19: 28028 | X19: 341851 | Y19: 187346 | Z19: 381784 | AB19: 28028 | AC19: 128361 | AD19: 2886 | AE19: -226643 | AG19: 0 | AH19: 10 | AI19: 10 | AJ19: 10 | AL19: 259754 | AM19: 375742 | AN19: 349627 | AO19: 92330 | AT19: info@kvestor.org | AW19: ООО «КВЕСТОР» зарегистрировано по адресу: 125252, Москва г, вн.тер.г. муниципальный округ Хорошевский, ул Авиаконструктора Микояна, д. 12, помещ. Б. Генеральным директором является Глаголев Роман Анатольевич.
A20: 3123458484 | B20: 540 | C20: Общество с ограниченной ответственностью «Коллекшн Консалт» | D20: 3123458484 | E20: 1193123020452 | F20: ООО «Коллекшн Консалт» | G20: 45642 | H20: 0 | I20: Нет | L20: г. Белгород, Народный б-р, д. 79, оф. 514, 308009 | M20: 10000 | R20: 41661 | S20: 209582 | T20: 225436 | U20: 273097 | W20: 25604 | X20: 73014 | Y20: 86775 | Z20: 327372 | AB20: 25604 | AC20: 96551 | AD20: 103277 | AE20: -93270 | AG20: 79789 | AH20: 149637 | AI20: 237909 | AJ20: 28531 | AL20: 1772 | AM20: 1066 | AN20: 1341 | AO20: 19433 | AT20: 0 | AW20: ООО «Коллекшн Консалт» зарегистрировано по адресу: г. Белгород, Народный б-р, д. 79, оф. 514, 308009
A21: 9704047900 | B21: 543 | C21: Акционерное общество «Технологии Бизнеса» | D21: 9704047900 | E21: 1217700057200 | F21: АО «Технологии Бизнеса» | G21: 45611 | H21: 0 | I21: Нет | L21: 119121, город Москва, вн.тер. г. Муниципальный Округ Хамовники, пер 2-Й Вражский, дом 1, корпус 1, помещение 1/1 | M21: 100 | R21: 0 | S21: 147758 | T21: 237367 | U21: 233367 | W21: 0 | X21: 89592 | Y21: 80711 | Z21: 96178 | AB21: 0 | AC21: 38966 | AD21: 26628 | AE21: 15952 | AG21: 0 | AH21: 23796 | AI21: 28911 | AJ21: 8099 | AL21: 0 | AM21: 17036 | AN21: 26891 | AO21: 20096 | AT21: info@ao-tb.ru | AW21: АО «Технологии Бизнеса» зарегистрировано по адресу: 119121, город Москва, вн.тер. г. Муниципальный Округ Хамовники, пер 2-Й Вражский, дом 1, корпус 1, помещение 1/1
A22: 2723115222 | B22: 0 | C22: Непубличное акционерное общество Профессиональная коллекторская организация «Первое клиентское бюро» | D22: 2723115222 | E22: 1092723000446 | F22: НАО ПКО «ПКБ» | G22: 39847 | H22: 16 | I22: Да | K22: Клековкин Николай Игоревич | L22: Москва г, км Киевское шоссе 22-й (п Московский), 6, 1 | M22: 194.3 | R22: 9519863 | S22: 7778417 | T22: 9298765 | U22: 12765053 | V22: 17486370 | W22: 4961407 | X22: 1886740 | Y22: 2913013 | Z22: 3028498 | AA22: 7354522 | AB22: 4961407 | AC22: 3327903 | AD22: 3667985 | AE22: 6746377 | AF22: 7017168 | AG22: 7094613 | AH22: 11961665 | AI22: 13692288 | AJ22: 23483962 | AK22: 21143934 | AL22: 410024 | AM22: 679296 | AN22: 874521 | AO22: 589736 | AP22: 522393 | AQ22: 12919181 | AR22: 1.84 | AS22: Низкий | AT22: pkbonline.ru | AU22: image060 | AV22: 2.98 | AW22: НАО ПКО «ПКБ» зарегистрировано по адресу: Москва г, км Киевское шоссе 22-й (п Московский), 6, 1. Генеральным директором является Клековкин Николай Игоревич. Рост доходов компании за 5 лет: 183,68%. Рост финансовых активов компании за 5 лет: 298,03%. Объем заемных средств компании на конец 2024 года: 12919181 тыс. руб. ФССП присвоил Низкий уровень риска для данного ПКО.
A23: 7713793524 | B23: 1 | C23: Общество с ограниченной ответственностью Профессиональная коллекторская организация «Феникс» | D23: 7713793524 | E23: 1147746920144 | F23: ООО ПКО «Феникс» | G23: 41863 | H23: 10 | I23: Нет | J23: Акционерное Общество, "ТБАНК", Международная Компания Публичное Акционерное Общество, "Т-ТЕХНОЛОГИИ" | K23: Феклисов Иван Владимирович | L23: 127287, Москва г, Хуторская 2-Я ул, дом 38А, строение 26 | M23: 33250 | R23: 7746710 | S23: 9815218 | T23: 10699598 | U23: 12291051 | V23: 12835953 | W23: 2407105 | X23: 3230796 | Y23: 3606574 | Z23: 2415999 | AA23: 1895600 | AB23: 2407105 | AC23: 5237831 | AD23: 5366147 | AE23: 7366870 | AF23: 8229971 | AG23: 9528726 | AH23: 8257159 | AI23: 11084910 | AJ23: 11562703 | AK23: 21154197 | AL23: 249470 | AM23: 63808 | AN23: 68805 | AO23: 61492 | AP23: 276242 | AQ23: 2378544 | AR23: 1.66 | AS23: Высокий | AT23: phoenix0ca.ru | AU23: image002 | AV23: 2.22 | AW23: ООО ПКО «Феникс» зарегистрировано по адресу: 127287, Москва г, Хуторская 2-Я ул, дом 38А, строение 26. Генеральным директором является Феклисов Иван Владимирович. Рост доходов компании за 5 лет: 165,7%. Рост финансовых активов компании за 5 лет: 222%. Объем заемных средств компании на конец 2024 года: 2378544 тыс. руб. ФССП присвоил Высокий уровень риска для данного ПКО.
A24: 7730233723 | B24: 4 | C24: Общество с ограниченной ответственностью профессиональная коллекторская организация «АйДи Коллект» | D24: 7730233723 | E24: 1177746355225 | F24: ООО ПКО «АйДи Коллект» | G24: 42832 | H24: 8 | I24: Да | J24: Васильев Александр Александрович, Общество С Ограниченной Ответственностью, "ОНЛАЙН МИКРОФИНАНС", Общество С Ограниченной Ответственностью, "ФИНТЕХ ГРУПП" | K24: Васильев Александр Александрович | L24: 121096, Москва г, ул. Василисы Кожиной, дом 1, офис Д13 | M24: 101265.82 | R24: 694023 | S24: 2342953 | T24: 4647772 | U24: 8331391 | V24: 12362455 | W24: 247799 | X24: 530090 | Y24: 1630652 | Z24: 2436827 | AA24: 4073731 | AB24: 247799 | AC24: 1119448 | AD24: 1329942 | AE24: 2975359 | AF24: 3863869 | AG24: 970210 | AH24: 4311265 | AI24: 7794949 | AJ24: 13782767 | AK24: 16179682 | AL24: 20331 | AM24: 31369 | AN24: 466385 | AO24: 289827 | AP24: 114237 | AQ24: 13646924 | AR24: 17.81 | AS24: Низкий | AT24: idcollect.ru | AU24: image043 | AV24: 16.68 | AW24: ООО ПКО «АйДи Коллект» зарегистрировано по адресу: 121096, Москва г, ул. Василисы Кожиной, дом 1, офис Д13. Генеральным директором является Васильев Александр Александрович. Рост доходов компании за 5 лет: 1781,3%. Рост финансовых активов компании за 5 лет: 1667,65%. Объем заемных средств компании на конец 2024 года: 13646924 тыс. руб. ФССП присвоил Низкий уровень риска для данного ПКО.
A25: 7714704125 | B25: 2 | C25: Общество с ограниченной ответственностью Профессиональная коллекторская организация «ЭОС» | D25: 7714704125 | E25: 1077758117117 | F25: ООО ПКО «ЭОС» | G25: 39282 | H25: 17 | I25: Да | J25: Завьялова Елена Михайловна, Компания С Ограниченной Ответственностью Эос Холдинг Гмбх, Компания С Ограниченной Ответственностью Эос Интернациональ Бетайлигунгс-фервальтунгсгезелльшафт Мбх | K25: Дмитраков Антон Александрович | L25: 117105, Москва г, вн.тер. г. муниципальный округ Нагорный, ш Варшавское, д. 26, этаж 2, ч. нежил. помещ. 8 | M25: 6450 | R25: 6360674 | S25: 9143168 | T25: 10606574 | U25: 11043025 | V25: 9784245 | W25: 1778110 | X25: 2163516 | Y25: 4978419 | Z25: 3027672 | AA25: 3020218 | AB25: 1778110 | AC25: 4582547 | AD25: 2928525 | AE25: 5120363 | AF25: 4762878 | AG25: 5308242 | AH25: 9409339 | AI25: 11291057 | AJ25: 12229815 | AK25: 11134188 | AL25: 76857 | AM25: 143059 | AN25: 80269 | AO25: 335476 | AP25: 169474 | AQ25: 5081951 | AR25: 1.54 | AS25: Низкий | AT25: oooeos.ru | AU25: image017 | AV25: 2.1 | AW25: ООО ПКО «ЭОС» зарегистрировано по адресу: 117105, Москва г, вн.тер. г. муниципальный округ Нагорный, ш Варшавское, д. 26, этаж 2, ч. нежил. помещ. 8. Генеральным директором является Дмитраков Антон Александрович. Рост доходов компании за 5 лет: 153,8%. Рост финансовых активов компании за 5 лет: 209,75%. Объем заемных средств компании на конец 2024 года: 5081951 тыс. руб. ФССП присвоил Низкий уровень риска для данного ПКО.
A26: 7706450420 | B26: 3 | C26: Общество с ограниченной ответственностью «Профессиональная коллекторская организация «Национальная Фабрика Ипотеки» | D26: 7706450420 | E26: 1177746942020 | F26: ООО «ПКО «Национальная Фабрика Ипотеки» | G26: 42984 | H26: 7 | I26: Нет | J26: "МОСКОВСКИЙ КРЕДИТНЫЙ БАНК", (публичное Акционерное Общество) | K26: Исеев Руслан Маратович | L26: 107140, Москва г, ул Красносельская Верхн., 11А, 1, 2/2/45 | M26: 315000 | R26: 8878559 | S26: 12637330 | T26: 12562020 | U26: 8536698 | V26: 8753853 | W26: 7464337 | X26: 11095638 | Y26: 10423574 | Z26: 6517008 | AA26: 6476527 | AB26: 7464337 | AC26: 230250 | AD26: 151795 | AE26: 137313 | AF26: -776176 | AG26: 6273480 | AH26: 8206211 | AI26: 10015293 | AJ26: 12684814 | AK26: 13806928 | AL26: 164797 | AM26: 187427 | AN26: 322258 | AO26: 439587 | AP26: 563914 | AQ26: 14942793 | AR26: 0.99 | AS26: Низкий | AT26: ipoteka24.ru | AU26: image142 | AV26: 2.2 | AW26: ООО «ПКО «Национальная Фабрика Ипотеки» зарегистрировано по адресу: 107140, Москва г, ул Красносельская Верхн., 11А, 1, 2/2/45. Генеральным директором является Исеев Руслан Маратович. Рост доходов компании за 5 лет: 98,6%. Рост финансовых активов компании за 5 лет: 220,08%. Объем заемных средств компании на конец 2024 года: 14942793 тыс. руб. ФССП присвоил Низкий уровень риска для данного ПКО.
A27: 5407973997 | B27: 8 | C27: Общество с ограниченной ответственностью Профессиональная коллекторская организация «Право онлайн» | D27: 5407973997 | E27: 1195476020343 | F27: ООО ПКО «Право онлайн» | G27: 43538 | H27: 6 | I27: Нет | J27: Волков Павел Александрович, Кравцова Наталья Николаевна, Евстифеева Юлия Евгеньевна, Кобяков Владислав Юрьевич, Елисеев Алексей Андреевич, Трахачёв Сергей Валерьевич | K27: Телятникова Елена Васильевна | L27: 630005, Новосибирская область, Новосибирск, Фрунзе, д. 88, этаж 2, офис 21 | M27: 62.035 | R27: 215252 | S27: 1025945 | T27: 2361430 | U27: 4627147 | V27: 7129755 | W27: 49016 | X27: 637310 | Y27: 1438435 | Z27: 2640709 | AA27: 4214695 | AB27: 49016 | AC27: 296990 | AD27: 684861 | AE27: 1273402 | AF27: 1879565 | AG27: 0 | AH27: 962059 | AI27: 2260288 | AJ27: 3547923 | AK27: 5850603 | AL27: 305122 | AM27: 116045 | AN27: 121243 | AO27: 273368 | AP27: 104605 | AQ27: 4008607 | AR27: 33.12 | AS27: Низкий | AT27: pvonline.ru | AU27: image057 | AV27: 6.08 | AW27: ООО ПКО «Право онлайн» зарегистрировано по адресу: 630005, Новосибирская область, Новосибирск, Фрунзе, д. 88, этаж 2, офис 21. Генеральным директором является Телятникова Елена Васильевна. Рост доходов компании за 5 лет: 3312,3%. Рост финансовых активов компании за 5 лет: 608,13%. Объем заемных средств компании на конец 2024 года: 4008607 тыс. руб. ФССП присвоил Низкий уровень риска для данного ПКО.
A28: 7841430420 | B28: 7 | C28: Общество с ограниченной ответственностью Профессиональная коллекторская организация «Филберт» | D28: 7841430420 | E28: 1107847250961 | F28: ООО ПКО «Филберт» | G28: 40394 | H28: 14 | I28: Да | K28: Иванов Андрей Борисович | L28: 198095, Санкт-Петербург г, Маршала Говорова ул, дом № 35, корпус 5, лит. Ж | M28: 10 | R28: 1770329 | S28: 4335154 | T28: 3848709 | U28: 4799034 | V28: 6148318 | W28: 348390 | X28: 1949395 | Y28: 621948 | Z28: 874797 | AA28: 1394961 | AB28: 348390 | AC28: 1315749 | AD28: 1802945 | AE28: 2218456 | AF28: 2568638 | AG28: 2620651 | AH28: 3839953 | AI28: 4999692 | AJ28: 7168661 | AK28: 9102226 | AL28: 50639 | AM28: 113684 | AN28: 55850 | AO28: 173771 | AP28: 69730 | AQ28: 2536194 | AR28: 3.47 | AS28: Значительный | AT28: filbert.su; Filbert.pro | AU28: image004 | AV28: 3.47 | AW28: ООО ПКО «Филберт» зарегистрировано по адресу: 198095, Санкт-Петербург г, Маршала Говорова ул, дом № 35, корпус 5, лит. Ж. Генеральным директором является Иванов Андрей Борисович. Рост доходов компании за 5 лет: 347,3%. Рост финансовых активов компании за 5 лет: 347,33%. Объем заемных средств компании на конец 2024 года: 2536194 тыс. руб. ФССП присвоил Значительный уровень риска для данного ПКО.
A29: 7707782563 | B29: 6 | C29: Общество с ограниченной ответственностью Профессиональная коллекторская организация «Региональная Служба Взыскания» | D29: 7707782563 | E29: 1127746618768 | F29: ООО ПКО «РСВ» | G29: 41131 | H29: 12 | I29: Да | J29: Общество С Ограниченной Ответственностью Профессиональная Коллекторская Организация, "СТОЛИЧНАЯ СЕРВИСНАЯ КОМПАНИЯ", Свеа Экономи Сайпрус Лимитед | K29: Медведева Ольга Владимировна | L29: 127055, Москва, Бутырский Вал, дом № 68/70, стр. 1, этаж 2, помещение I, комната №4 | M29: 10 | R29: 1034499 | S29: 3183461 | T29: 6096482 | U29: 5276121 | V29: 5864105 | W29: 450337 | X29: 674239 | Y29: 2086771 | Z29: 1622048 | AA29: 2473779 | AB29: 450337 | AC29: 1489776 | AD29: 2273861 | AE29: 2145981 | AF29: 3204091 | AG29: 1192462 | AH29: 4460750 | AI29: 4571756 | AJ29: 4530378 | AK29: 4794166 | AL29: 42936 | AM29: 204656 | AN29: 303021 | AO29: 569379 | AP29: 770038 | AQ29: 3181681 | AR29: 5.67 | AS29: Высокий | AT29: rsvcollection.ru | AU29: image020 | AV29: 4.02 | AW29: ООО ПКО «РСВ» зарегистрировано по адресу: 127055, Москва, Бутырский Вал, дом № 68/70, стр. 1, этаж 2, помещение I, комната №4. Генеральным директором является Медведева Ольга Владимировна. Рост доходов компании за 5 лет: 566,9%. Рост финансовых активов компании за 5 лет: 402,04%. Объем заемных средств компании на конец 2024 года: 3181681 тыс. руб. ФССП присвоил Высокий уровень риска для данного ПКО.
A30: 7730592401 | B30: 9 | C30: Акционерное общество Профессиональная коллекторская организация «Центр Долгового Управления» | D30: 7730592401 | E30: 5087746390353 | F30: АО ПКО «ЦДУ» | G30: 39763 | H30: 16 | I30: Нет | K30: Ямпольская Елена Александровна | L30: 117420, Москва г, ул Намёткина, 15, Эт 1 Пом I Ком 01-06 | M30: 3000 | R30: 662863 | S30: 1518917 | T30: 2355062 | U30: 3768972 | V30: 4706406 | W30: 187289 | X30: 590555 | Y30: 1392888 | Z30: 1955803 | AA30: 3014575 | AB30: 187289 | AC30: 774816 | AD30: 770441 | AE30: 1453064 | AF30: 1384779 | AG30: 260194 | AH30: 728282 | AI30: 1362348 | AJ30: 2486555 | AK30: 3311833 | AL30: 18583 | AM30: 66897 | AN30: 33544 | AO30: 65828 | AP30: 60950 | AQ30: 0 | AR30: 7.1 | AS30: Низкий | AT30: gkcdu.ru | AU30: image031 | AV30: 12.73 | AW30: АО ПКО «ЦДУ» зарегистрировано по адресу: 117420, Москва г, ул Намёткина, 15, Эт 1 Пом I Ком 01-06. Генеральным директором является Ямпольская Елена Александровна. Рост доходов компании за 5 лет: 710%. Рост финансовых активов компании за 5 лет: 1272,83%. ФССП присвоил Низкий уровень риска для данного ПКО.
A31: 3801084488 | B31: 10 | C31: Общество с ограниченной ответственностью Профессиональная коллекторская организация Траст» | D31: 3801084488 | E31: 1063801051203 | F31: ООО «ПКО Траст» | G31: 38945 | H31: 18 | I31: Да | J31: Долюк Андрей Николаевич, Самбудагва Ксения Павловна | K31: Долюк Андрей Николаевич | L31: 665801, Иркутская обл, г.о. Ангарское, г Ангарск, кв-л 252, стр. 19, д.офис 202 | M31: 20 | R31: 1314917 | S31: 2158767 | T31: 2677762 | U31: 3241552 | V31: 3666014 | W31: 200114 | X31: 397768 | Y31: 650661 | Z31: 1199595 | AA31: 1582938 | AB31: 200114 | AC31: 1060974 | AD31: 1244435 | AE31: 1194514 | AF31: 1296597 | AG31: 1544620 | AH31: 2163179 | AI31: 2962323 | AJ31: 4648416 | AK31: 5416881 | AL31: 58178 | AM31: 60606 | AN31: 80407 | AO31: 252788 | AP31: 177879 | AQ31: 463656 | AR31: 2.79 | AS31: Низкий | AT31: catrust.ru | AU31: image019 | AV31: 3.51 | AW31: ООО «ПКО Траст» зарегистрировано по адресу: 665801, Иркутская обл, г.о. Ангарское, г Ангарск, кв-л 252, стр. 19, д.офис 202. Генеральным директором является Долюк Андрей Николаевич. Рост доходов компании за 5 лет: 278,8%. Рост финансовых активов компании за 5 лет: 350,69%. Объем заемных средств компании на конец 2024 года: 463656 тыс. руб. ФССП присвоил Низкий уровень риска для данного ПКО.
A32: 7805646537 | B32: 14 | C32: Общество с ограниченной ответственностью профессиональная коллекторская организация «ДОЛГОВОЕ АГЕНТСТВО «ФЕМИДА» | D32: 7805646537 | E32: 1147847101577 | F32: ООО ПКО «ДА «ФЕМИДА» | G32: 41719 | H32: 11 | I32: Нет | J32: Общество С Ограниченной Ответственностью, "ДЗП-РАЗВИТИЕ" | K32: Карташова Ольга Владимировна | L32: 197374, Город Санкт-Петербург, ул. Мебельная, дом 12, корпус 1, литер А, помещение 55-Н, офис 420 | M32: 10 | R32: 133082 | S32: 154344 | T32: 474695 | U32: 2104307 | V32: 3049049 | W32: 175483 | X32: 57865 | Y32: 92399 | Z32: 840418 | AA32: 1267589 | AB32: 175483 | AC32: 3147 | AD32: 35182 | AE32: 520556 | AF32: 835826 | AG32: 206760 | AH32: 426247 | AI32: 910217 | AJ32: 1578595 | AK32: 1713500 | AL32: 37055 | AM32: 33373 | AN32: 7705 | AO32: 56903 | AP32: 85223 | AQ32: 137577 | AR32: 22.91 | AS32: Низкий | AT32: dafemida.ru | AU32: image175 | AV32: 8.29 | AW32: ООО ПКО «ДА «ФЕМИДА» зарегистрировано по адресу: 197374, Город Санкт-Петербург, ул. Мебельная, дом 12, корпус 1, литер А, помещение 55-Н, офис 420. Генеральным директором является Карташова Ольга Владимировна. Рост доходов компании за 5 лет: 2291,1%. Рост финансовых активов компании за 5 лет: 828,74%. Объем заемных средств компании на конец 2024 года: 137577 тыс. руб. ФССП присвоил Низкий уровень риска для данного ПКО.
A33: 7726626680 | B33: 13 | C33: Общество с ограниченной ответственностью «Профессиональная коллекторская организация «М.Б.А. Финансы» | D33: 7726626680 | E33: 1097746177693 | F33: ООО «ПКО «М.Б.А. Финансы» | G33: 39903 | H33: 16 | I33: Да | J33: Товарищество С Ограниченной Ответственностью, "КОЛЛЕКТОРСКОЕ АГЕНТСТВО ", М.б.а. Финансы" | K33: Вахата Федор | L33: 115280, Москва г, ул Мастеркова, 4, Эт 15 Пом I Ком 35 | M33: 200000 | R33: 1179086 | S33: 1453942 | T33: 2075137 | U33: 2301202 | V33: 2977193 | W33: -799983 | X33: -832060 | Y33: -1266296 | Z33: -1053945 | AA33: 1292887 | AB33: -799983 | AC33: 197045 | AD33: 263131 | AE33: 484044 | AF33: 749259 | AG33: 1151591 | AH33: 1391909 | AI33: 1557802 | AJ33: 1814461 | AK33: 2496513 | AL33: 175659 | AM33: 111498 | AN33: 150323 | AO33: 176690 | AP33: 212366 | AQ33: 365873 | AR33: 2.53 | AS33: Значительный | AT33: mbafin.ru | AU33: image044 | AV33: 2.17 | AW33: ООО «ПКО «М.Б.А. Финансы» зарегистрировано по адресу: 115280, Москва г, ул Мастеркова, 4, Эт 15 Пом I Ком 35. Генеральным директором является Вахата Федор. Рост доходов компании за 5 лет: 252,5%. Рост финансовых активов компании за 5 лет: 216,79%. Объем заемных средств компании на конец 2024 года: 365873 тыс. руб. ФССП присвоил Значительный уровень риска для данного ПКО.
A34: 7727844641 | B34: 16 | C34: Общество с ограниченной ответственностью Профессиональная коллекторская организация «ЦДУ Инвест» | D34: 7727844641 | E34: 5147746158632 | F34: ООО ПКО «ЦДУ Инвест» | G34: 41912 | H34: 10 | I34: Нет | J34: Креммель Александр Владимирович, Акционерное Общество Профессиональная Коллекторская Организация, "ЦЕНТР ДОЛГОВОГО УПРАВЛЕНИЯ" | K34: Смирнов Алексей Васильевич | L34: 117420, Москва г, ул Намёткина, 15, Эт/Пом/Ком 1/I/12 | M34: 3000 | R34: 111554 | S34: 374078 | T34: 754914 | U34: 1539322 | V34: 2413732 | W34: 40336 | X34: 120744 | Y34: 430376 | Z34: 632820 | AA34: 1427145 | AB34: 40336 | AC34: 200013 | AD34: 254498 | AE34: 705293 | AF34: 768428 | AG34: 41 | AH34: 277842 | AI34: 569806 | AJ34: 1193258 | AK34: 1762672 | AL34: 186115 | AM34: 67848 | AN34: 39920 | AO34: 26529 | AP34: 26529 | AQ34: 234000 | AR34: 21.64 | AS34: 0 | AT34: cdu0invest.ru | AU34: image308 | AV34: 42992 | AW34: ООО ПКО «ЦДУ Инвест» зарегистрировано по адресу: 117420, Москва г, ул Намёткина, 15, Эт/Пом/Ком 1/I/12. Генеральным директором является Смирнов Алексей Васильевич. Рост доходов компании за 5 лет: 2163,7%. Рост финансовых активов компании за 5 лет: 4299200%. Объем заемных средств компании на конец 2024 года: 234000 тыс. руб.
A35: 7841019595 | B35: 18 | C35: Общество с ограниченной ответственностью «Профессиональная коллекторская организация «Агентство Судебного Взыскания» | D35: 7841019595 | E35: 1157847071073 | F35: ООО «ПКО «АСВ» | G35: 42067 | H35: 10 | I35: Да | J35: Общество С Ограниченной Ответственностью, "АСВ.УПРАВЛЕНИЕ" | K35: Богомолов Максим Владимирович | L35: 194044, город Санкт-Петербург, вн.тер. г. Муниципальный Округ Сампсониевское, пр-кт Большой Сампсониевский, дом 28, корпус 2, литера Д, офис 642 | M35: 115.656 | R35: 483240 | S35: 784084 | T35: 1221840 | U35: 1469015 | V35: 2330001 | W35: 189104 | X35: 234597 | Y35: 514545 | Z35: 527752 | AA35: 833951 | AB35: 189104 | AC35: 39262 | AD35: 52476 | AE35: 65942 | AF35: 210834 | AG35: 178384 | AH35: 310830 | AI35: 535756 | AJ35: 1475570 | AK35: 1857986 | AL35: 71461 | AM35: 73708 | AN35: 61021 | AO35: 113400 | AP35: 231762 | AQ35: 2217172 | AR35: 4.82 | AS35: Низкий | AT35: legalcollection.ru | AU35: image204 | AV35: 10.42 | AW35: ООО «ПКО «АСВ» зарегистрировано по адресу: 194044, город Санкт-Петербург, вн.тер. г. Муниципальный Округ Сампсониевское, пр-кт Большой Сампсониевский, дом 28, корпус 2, литера Д, офис 642. Генеральным директором является Богомолов Максим Владимирович. Рост доходов компании за 5 лет: 482,2%. Рост финансовых активов компании за 5 лет: 1041,57%. Объем заемных средств компании на конец 2024 года: 2217172 тыс. руб. ФССП присвоил Низкий уровень риска для данного ПКО.
A36: 7736659589 | B36: 12 | C36: Общество с ограниченной ответственностью Профессиональная коллекторская организация «АктивБизнесКонсалт» | D36: 7736659589 | E36: 1137746390572 | F36: ООО ПКО «АБК» | G36: 41393 | H36: 11 | I36: Да | K36: Колосков Максим Викторович | L36: 117997, Москва г, ул Вавилова, 19 | M36: 16000 | R36: 1455949 | S36: 1701012 | T36: 2030719 | U36: 2352629 | V36: 2316584 | W36: 638929 | X36: 785795 | Y36: 943905 | Z36: 855231 | AA36: 969389 | AB36: 638929 | AC36: 439314 | AD36: 554003 | AE36: 803768 | AF36: 458487 | AG36: 497523 | AH36: 393123 | AI36: 821006 | AJ36: 2319520 | AK36: 3171955 | AL36: 102538 | AM36: 148122 | AN36: 135076 | AO36: 123795 | AP36: 164532 | AQ36: 2350687 | AR36: 1.59 | AS36: Низкий | AT36: activebc.ru | AU36: image041 | AV36: 6.38 | AW36: ООО ПКО «АБК» зарегистрировано по адресу: 117997, Москва г, ул Вавилова, 19. Генеральным директором является Колосков Максим Викторович. Рост доходов компании за 5 лет: 159,1%. Рост финансовых активов компании за 5 лет: 637,55%. Объем заемных средств компании на конец 2024 года: 2350687 тыс. руб. ФССП присвоил Низкий уровень риска для данного ПКО.
A37: 5407973637 | B37: 36 | C37: Общество с ограниченной ответственностью Профессиональная коллекторская организация «Защита Онлайн» | D37: 5407973637 | E37: 1195476015085 | F37: ООО ПКО «Защита Онлайн» | G37: 43521 | H37: 6 | I37: Да | J37: Волков Павел Александрович, Шин Егор Борисович, Евстифеева Юлия Евгеньевна, Елисеев Алексей Андреевич, Кобяков Владислав Юрьевич, Непомнящая Софья Алибековна, Сазонов Иван Викторович, Евтягина Ольга Владимировна, Зоткин Валерий Александрович, Загребельный Денис Александрович, Коуров Тимофей Анатольевич, Шарапов Константин Александрович, Трахачёв Сергей Валерьевич | K37: Загребельный Денис Александрович | L37: 630005, Новосибирская обл, г Новосибирск, ул Фрунзе, д. 88, этаж 3, офис 31 | M37: 150 | R37: 122897 | S37: 21903 | T37: 16511 | U37: 522072 | V37: 1885826 | W37: 3853 | X37: 5411 | Y37: 14851 | Z37: 294040 | AA37: 1053672 | AB37: 3853 | AC37: 14072 | AD37: 29 | AE37: 117762 | AF37: 500453 | AG37: 0 | AH37: 0 | AI37: 0 | AJ37: 1305806 | AK37: 2387910 | AL37: 126639 | AM37: 37595 | AN37: 107807 | AO37: 23530 | AP37: 50562 | AQ37: 1677758 | AR37: 15.35 | AS37: Низкий | AT37: https://zonline.ru/ | AU37: image234 | AV37: 1.83 | AW37: ООО ПКО «Защита Онлайн» зарегистрировано по адресу: 630005, Новосибирская обл, г Новосибирск, ул Фрунзе, д. 88, этаж 3, офис 31. Генеральным директором является Загребельный Денис Александрович. Рост доходов компании за 5 лет: 1534,5%. Рост финансовых активов компании за 5 лет: 182,87%. Объем заемных средств компании на конец 2024 года: 1677758 тыс. руб. ФССП присвоил Низкий уровень риска для данного ПКО.
A38: 6315626402 | B38: 11 | C38: Общество с ограниченной ответственностью Профессиональная коллекторская организация «Сентинел Кредит Менеджмент» | D38: 6315626402 | E38: 1096315004720 | F38: ООО ПКО «СКМ» | G38: 40024 | H38: 15 | I38: Да | K38: Дуда Игорь Викторович | L38: 121151, Москва, Тараса Шевченко, 23А | M38: 216547 | R38: 972350 | S38: 1937261 | T38: 1781010 | U38: 2696180 | V38: 1611463 | W38: 697366 | X38: 707941 | Y38: 661037 | Z38: 852713 | AA38: 411601 | AB38: 29174 | AC38: 813058 | AD38: 547425 | AE38: 1130465 | AF38: 569404 | AG38: 623346 | AH38: 997343 | AI38: 1002540 | AJ38: 830364 | AK38: 1175885 | AL38: 93343 | AM38: 165191 | AN38: 196659 | AO38: 176870 | AP38: 176870 | AQ38: 837000 | AR38: 1.66 | AS38: Значительный | AT38: sentinelcredit.ru | AU38: image024 | AV38: 1.89 | AW38: ООО ПКО «СКМ» зарегистрировано по адресу: 121151, Москва, Тараса Шевченко, 23А. Генеральным директором является Дуда Игорь Викторович. Рост доходов компании за 5 лет: 165,7%. Рост финансовых активов компании за 5 лет: 188,64%. Объем заемных средств компании на конец 2024 года: 837000 тыс. руб. ФССП присвоил Значительный уровень риска для данного ПКО.
A39: 1657199916 | B39: 19 | C39: Общество с ограниченной ответственностью Профессиональная коллекторская организация «Фабула» | D39: 1657199916 | E39: 1151690071741 | F39: ООО ПКО «Фабула» | G39: 42256 | H39: 9 | I39: Нет | J39: Общество С Ограниченной Ответственностью, "ЛЕГАЛАЙТ" | K39: Диянов Радик Рашидович | L39: 420044, Татарстан Респ, Казань г, Ямашева пр-кт, дом № 36Д, офис 15 | M39: 15000 | R39: 432196 | S39: 688012 | T39: 902262 | U39: 1373573 | V39: 1584330 | W39: 96637 | X39: 165381 | Y39: 295097 | Z39: 562133 | AA39: 676507 | AB39: 96637 | AC39: 316576 | AD39: 378643 | AE39: 498600 | AF39: 577188 | AG39: 184152 | AH39: 497285 | AI39: 678648 | AJ39: 1031369 | AK39: 1319603 | AL39: 137587 | AM39: 119788 | AN39: 179893 | AO39: 207466 | AP39: 345144 | AQ39: 0 | AR39: 3.67 | AS39: Низкий | AT39: kafabula.ru | AU39: image036 | AV39: 7.17 | AW39: ООО ПКО «Фабула» зарегистрировано по адресу: 420044, Татарстан Респ, Казань г, Ямашева пр-кт, дом № 36Д, офис 15. Генеральным директором является Диянов Радик Рашидович. Рост доходов компании за 5 лет: 366,6%. Рост финансовых активов компании за 5 лет: 716,58%. ФССП присвоил Низкий уровень риска для данного ПКО.
A40: 6672302726 | B40: 5 | C40: Общество с ограниченной ответственностью «Профессиональная коллекторская организация «ФинТраст» | D40: 6672302726 | E40: 1096672015648 | F40: ООО «ПКО «ФинТраст» | G40: 40070 | H40: 15 | I40: Нет | J40: Шалимов Константин Викторович | K40: Шалимов Константин Викторович | L40: 620026, Свердловская обл, г Екатеринбург, ул Куйбышева, 95, 405 | M40: 10 | R40: 3566972 | S40: 4673205 | T40: 3611889 | U40: 6243476 | V40: 1394242 | W40: 3390488 | X40: 4521453 | Y40: 2810324 | Z40: 5403598 | AA40: 493549 | AB40: 3390488 | AC40: 5951 | AD40: 12656 | AE40: 17407 | AF40: -86162 | AG40: 6827666 | AH40: 10091197 | AI40: 10480485 | AJ40: 8517263 | AK40: 8583581 | AL40: 886 | AM40: 585819 | AN40: 4047773 | AO40: 1415320 | AP40: 1415320 | AQ40: 10012498 | AR40: 0.39 | AS40: 0 | AT40: cafintrust.ru | AU40: image350 | AV40: 1.26 | AW40: ООО «ПКО «ФинТраст» зарегистрировано по адресу: 620026, Свердловская обл, г Екатеринбург, ул Куйбышева, 95, 405. Генеральным директором является Шалимов Константин Викторович. Рост доходов компании за 5 лет: 39,1%. Рост финансовых активов компании за 5 лет: 125,72%. Объем заемных средств компании на конец 2024 года: 10012498 тыс. руб.
A41: 7806253521 | B41: 17 | C41: Общество с ограниченной ответственностью «Профессиональная коллекторская организация Юнона» | D41: 7806253521 | E41: 1167847404053 | F41: ООО «ПКО Юнона» | G41: 42660 | H41: 8 | I41: Да | J41: Семенов Виктор Минаевич | K41: Ларионова Надежда Анатольевна | L41: 195027, Город Санкт-Петербург, ул Магнитогорская, д. 23, к. 1, литера А, офис 332 | M41: 10 | R41: 665067 | S41: 956323 | T41: 679100 | U41: 1501180 | V41: 1370904 | W41: 600578 | X41: 865586 | Y41: 552546 | Z41: 1491220 | AA41: 1359256 | AB41: 600578 | AC41: 1378 | AD41: 1371 | AE41: 3709 | AF41: 2490 | AG41: 408951 | AH41: 975466 | AI41: 1642208 | AJ41: 1877581 | AK41: 2152864 | AL41: 1158012 | AM41: 1346422 | AN41: 1075026 | AO41: 1190465 | AP41: 1190465 | AQ41: 79648 | AR41: 2.06 | AS41: Низкий | AT41: iunona.su | AU41: image1001 | AV41: 5.26 | AW41: ООО «ПКО Юнона» зарегистрировано по адресу: 195027, Город Санкт-Петербург, ул Магнитогорская, д. 23, к. 1, литера А, офис 332. Генеральным директором является Ларионова Надежда Анатольевна. Рост доходов компании за 5 лет: 206,1%. Рост финансовых активов компании за 5 лет: 526,44%. Объем заемных средств компании на конец 2024 года: 79648 тыс. руб. ФССП присвоил Низкий уровень риска для данного ПКО.
A42: 5611067262 | B42: 22 | C42: Общество с ограниченной ответственности Профессиональная коллекторская организация «Вернём» | D42: 5611067262 | E42: 1135658002149 | F42: ООО ПКО «Вернём» | G42: 41302 | H42: 12 | I42: Нет | J42: Луцык Андрей Григорьевич, Жалнина Дарья Александровна, Стержанов Алексей Евгеньевич | K42: Ивановский Павел Владимирович | L42: 650992, Кемеровская область - Кузбасс, г.о. Кемеровский, г Кемерово, ул 50 лет Октября, д. 11, ком. 818 | M42: 30 | R42: 259551 | S42: 325575 | T42: 711964 | U42: 1097668 | V42: 1336834 | W42: 46469 | X42: 91478 | Y42: 276832 | Z42: 378927 | AA42: 494821 | AB42: 46469 | AC42: -29905 | AD42: 13 | AE42: 44568 | AF42: 75050 | AG42: 651687 | AH42: 1033420 | AI42: 1190136 | AJ42: 1265840 | AK42: 1324574 | AL42: 17428 | AM42: 35069 | AN42: 80875 | AO42: 320772 | AP42: 372691 | AQ42: 1586580 | AR42: 5.15 | AS42: 0 | AT42: вернём.рф | AU42: image240 | AV42: 2.03 | AW42: ООО ПКО «Вернём» зарегистрировано по адресу: 650992, Кемеровская область - Кузбасс, г.о. Кемеровский, г Кемерово, ул 50 лет Октября, д. 11, ком. 818. Генеральным директором является Ивановский Павел Владимирович. Рост доходов компании за 5 лет: 515,1%. Рост финансовых активов компании за 5 лет: 203,25%. Объем заемных средств компании на конец 2024 года: 1586580 тыс. руб.
A43: 1659180290 | B43: 31 | C43: Общество с ограниченной ответственностью «Профессиональная коллекторская организация «Редут» | D43: 1659180290 | E43: 1171690027585 | F43: ООО «ПКО «Редут» | G43: 42817 | H43: 8 | I43: Нет | J43: Садыкова Алина Азатовна | K43: Гаттаров Ринат Саматович | L43: 420021, Татарстан Респ, Казань г, Братьев Петряевых ул, дом № 5, помещение 407 | M43: 10501 | R43: 624986 | S43: 617489 | T43: 545602 | U43: 634272 | V43: 1261165 | W43: 407873 | X43: 569400 | Y43: 435014 | Z43: 448767 | AA43: 914213 | AB43: 407873 | AC43: -96268 | AD43: 1932 | AE43: 21054 | AF43: 108629 | AG43: 40834 | AH43: 80144 | AI43: 15635 | AJ43: 10935 | AK43: 46799 | AL43: 18533 | AM43: 28478 | AN43: 39028 | AO43: 3801 | AP43: 16702 | AQ43: 7456 | AR43: 2.02 | AS43: Низкий | AT43: redut16.ru | AU43: image233 | AV43: 1.15 | AW43: ООО «ПКО «Редут» зарегистрировано по адресу: 420021, Татарстан Респ, Казань г, Братьев Петряевых ул, дом № 5, помещение 407. Генеральным директором является Гаттаров Ринат Саматович. Рост доходов компании за 5 лет: 201,8%. Рост финансовых активов компании за 5 лет: 114,61%. Объем заемных средств компании на конец 2024 года: 7456 тыс. руб. ФССП присвоил Низкий уровень риска для данного ПКО.
A44: 6164139228 | B44: 37 | C44: Общество с ограниченной ответственностью «Профессиональная коллекторская организация СОЛ» | D44: 6164139228 | E44: 1226100025029 | F44: ООО «ПКО СОЛ» | G44: 44825 | H44: 2 | I44: Нет | J44: Ванян Лариса Кареновна | K44: Ванян Лариса Кареновна | L44: 344082, Ростовская обл, г Ростов-на-Дону, пер Халтуринский, 4, 25 | M44: 10000 | R44: 0 | S44: 0 | T44: 1870 | U44: 471460 | V44: 1258567 | W44: 0 | X44: 0 | Y44: -158 | Z44: 353920 | AA44: 1162053 | AB44: 0 | AC44: 0 | AD44: 1611 | AE44: 11298 | AF44: -5590 | AG44: 0 | AH44: 0 | AI44: 0 | AJ44: 127879 | AK44: 387009 | AL44: 0 | AM44: 0 | AN44: 14 | AO44: 118905 | AP44: 280200 | AQ44: 181610 | AR44: 673.03 | AS44: Низкий | AT44: ka0sol.ru | AU44: image432 | AV44: 3.03 | AW44: ООО «ПКО СОЛ» зарегистрировано по адресу: 344082, Ростовская обл, г Ростов-на-Дону, пер Халтуринский, 4, 25. Генеральным директором является Ванян Лариса Кареновна. Рост доходов компании за 5 лет: 67303%. Рост финансовых активов компании за 5 лет: 302,64%. Объем заемных средств компании на конец 2024 года: 181610 тыс. руб. ФССП присвоил Низкий уровень риска для данного ПКО.
A45: 3702239395 | B45: 25 | C45: Общество с ограниченной ответственностью «Профессиональная коллекторская организация ВПК-Капитал» | D45: 3702239395 | E45: 1203700004375 | F45: ООО «ПКО ВПК-Капитал» | G45: 43892 | H45: 5 | I45: Нет | J45: Вахатова Мария Михайловна, Юркив Евгения Анатольевна, Кадышев Роман Иванович | K45: Кадышев Роман Иванович | L45: 153012, Ивановская обл, г Иваново, ул Марии Рябининой, 5, 2 | M45: 10500 | R45: 32723 | S45: 172216 | T45: 404532 | U45: 781162 | V45: 1249961 | W45: 8277 | X45: 70749 | Y45: 172971 | Z45: 287250 | AA45: 675418 | AB45: 8277 | AC45: 92331 | AD45: 185242 | AE45: 368694 | AF45: 407064 | AG45: 31049 | AH45: 141586 | AI45: 432771 | AJ45: 707496 | AK45: 854703 | AL45: 343 | AM45: 585 | AN45: 1142 | AO45: 2915 | AP45: 7173 | AQ45: 205768 | AR45: 38.2 | AS45: Низкий | AT45: vpk0capital.ru | AU45: image311 | AV45: 27.53 | AW45: ООО «ПКО ВПК-Капитал» зарегистрировано по адресу: 153012, Ивановская обл, г Иваново, ул Марии Рябининой, 5, 2. Генеральным директором является Кадышев Роман Иванович. Рост доходов компании за 5 лет: 3819,8%. Рост финансовых активов компании за 5 лет: 2752,76%. Объем заемных средств компании на конец 2024 года: 205768 тыс. руб. ФССП присвоил Низкий уровень риска для данного ПКО.
A46: 5902160058 | B46: 54 | C46: Общество с ограниченной ответственностью «Профессиональная коллекторская организация «Камелот» | D46: 5902160058 | E46: 1075902008445 | F46: ООО «ПКО «Камелот» | G46: 39283 | H46: 17 | I46: Нет | J46: Харисов Артем Фанусович, Лизунов Сергей Евгеньевич | K46: Лизунов Сергей Евгеньевич | L46: 614015, Пермский край, г. Пермь, ул. Монастырская, дом 14, квартира 200 | M46: 10 | R46: 235373 | S46: 297168 | T46: 581761 | U46: 283795 | V46: 1204007 | W46: 14701 | X46: 26943 | Y46: 27548 | Z46: 49569 | AA46: 2397060 | AB46: 14701 | AC46: 269327 | AD46: 553265 | AE46: 232192 | AF46: -1197547 | AG46: 0 | AH46: 0 | AI46: 0 | AJ46: 0 | AK46: 0 | AL46: 258453 | AM46: 540280 | AN46: 1091383 | AO46: 1324970 | AP46: 125893 | AQ46: 5659 | AR46: 5.12 | AS46: 0 | AT46: kamelotperm.ru | AU46: image005 | AW46: ООО «ПКО «Камелот» зарегистрировано по адресу: 614015, Пермский край, г. Пермь, ул. Монастырская, дом 14, квартира 200. Генеральным директором является Лизунов Сергей Евгеньевич. Рост доходов компании за 5 лет: 511,5%. Объем заемных средств компании на конец 2024 года: 5659 тыс. руб.
A47: 3801109213 | B47: 20 | C47: Общество с ограниченной ответственностью «Профессиональная коллекторская организация Управляющая компания Траст» | D47: 3801109213 | E47: 1103801002909 | F47: ООО «ПКО Управляющая компания Траст» | G47: 40373 | H47: 14 | I47: Нет | J47: Долюк Андрей Николаевич, Самбудагва Ксения Павловна | K47: Долюк Андрей Николаевич | L47: 665801, Иркутская обл, г.о. Ангарское, г Ангарск, кв-л 252, стр. 19, д.офис 207 | M47: 40 | R47: 620347 | S47: 813876 | T47: 1140510 | U47: 1252507 | V47: 1151012 | W47: 70820 | X47: 121894 | Y47: 199679 | Z47: 289867 | AA47: 239551 | AB47: 70820 | AC47: 500980 | AD47: 678397 | AE47: 679210 | AF47: 649462 | AG47: 633564 | AH47: 783654 | AI47: 955607 | AJ47: 1423161 | AK47: 1918391 | AL47: 28851 | AM47: 41828 | AN47: 44679 | AO47: 34209 | AP47: 44170 | AQ47: 37031 | AR47: 1.86 | AS47: Низкий | AT47: trust0uk.ru | AU47: image300 | AV47: 3.03 | AW47: ООО «ПКО Управляющая компания Траст» зарегистрировано по адресу: 665801, Иркутская обл, г.о. Ангарское, г Ангарск, кв-л 252, стр. 19, д.офис 207. Генеральным директором является Долюк Андрей Николаевич. Рост доходов компании за 5 лет: 185,5%. Рост финансовых активов компании за 5 лет: 302,79%. Объем заемных средств компании на конец 2024 года: 37031 тыс. руб. ФССП присвоил Низкий уровень риска для данного ПКО.
A48: 5407977286 | B48: 39 | C48: Общество с ограниченной ответственностью Профессиональная коллекторская организация «Интел коллект» | D48: 5407977286 | E48: 1205400001399 | F48: ООО ПКО «Интел коллект» | G48: 43846 | H48: 5 | I48: Нет | J48: Микрофинансовая Компания, "ЛАЙМ-ЗАЙМ", (общество С Ограниченной Ответственностью) | K48: Полетаев Тимофей Олегович | L48: 630102, Новосибирская обл, г Новосибирск, ул Восход, д. 20, офис 14 | M48: 11 | R48: 606 | S48: 17881 | T48: 252365 | U48: 404847 | V48: 1032325 | W48: 31 | X48: 14010 | Y48: 109258 | Z48: 226642 | AA48: 413636 | AB48: 31 | AC48: 2559 | AD48: 121216 | AE48: 140116 | AF48: 247149 | AG48: 3846 | AH48: 0 | AI48: 0 | AJ48: 0 | AK48: 1156303 | AL48: 159 | AM48: 23449 | AN48: 164943 | AO48: 677140 | AP48: 15567 | AQ48: 414784 | AR48: 1703.51 | AS48: Низкий | AT48: intelcollect.ru | AU48: image310 | AV48: 300.65 | AW48: ООО ПКО «Интел коллект» зарегистрировано по адресу: 630102, Новосибирская обл, г Новосибирск, ул Восход, д. 20, офис 14. Генеральным директором является Полетаев Тимофей Олегович. Рост доходов компании за 5 лет: 170350,7%. Рост финансовых активов компании за 5 лет: 30065,08%. Объем заемных средств компании на конец 2024 года: 414784 тыс. руб. ФССП присвоил Низкий уровень риска для данного ПКО.
A49: 1655364579 | B49: 122 | C49: Общество с ограниченной ответственностью «Профессиональная коллекторская организация «Киберколлект» | D49: 1655364579 | E49: 1161690117852 | F49: ООО «ПКО «Киберколлект» | G49: 42544 | H49: 8 | I49: Нет | J49: Бабушкин Валерий Евгеньевич | K49: Казак Екатерина Николаевна | L49: 420043, Республика Татарстан (Татарстан), г Казань, ул Вишневского, д. 22, помещ. 9 | M49: 28232 | R49: 0 | S49: 110 | T49: 101498 | U49: 341533 | V49: 1032276 | W49: 246 | X49: 251 | Y49: 13583 | Z49: 129032 | AA49: 270763 | AB49: 246 | AC49: -6917 | AD49: -19996 | AE49: 131724 | AF49: 9535 | AG49: 38 | AH49: 0 | AI49: 179866 | AJ49: 840710 | AK49: 1619251 | AL49: 73 | AM49: 159269 | AN49: 451912 | AO49: 461271 | AP49: 252095 | AQ49: 1704387 | AR49: 9384.33 | AS49: Значительный | AT49: cybercollect.ru | AU49: image364 | AV49: 42611.87 | AW49: ООО «ПКО «Киберколлект» зарегистрировано по адресу: 420043, Республика Татарстан (Татарстан), г Казань, ул Вишневского, д. 22, помещ. 9. Генеральным директором является Казак Екатерина Николаевна. Рост доходов компании за 5 лет: 938432,7%. Рост финансовых активов компании за 5 лет: 4261186,84%. Объем заемных средств компании на конец 2024 года: 1704387 тыс. руб. ФССП присвоил Значительный уровень риска для данного ПКО.
A50: 7707790885 | B50: 28 | C50: Общество с ограниченной ответственностью Профессиональная коллекторская организация «Кредитэкспресс Финанс» | D50: 7707790885 | E50: 1127747190152 | F50: ООО ПКО «КЭФ» | G50: 41241 | H50: 12 | I50: Да | J50: Частное Общество С Ограниченной Ответственностью, "КРЕДИТ ЭКСПРЕСС ГРУПП Б.В.", Свеа Инкассо Актиболаг | K50: Семендуев Виктор Александрович | L50: 127055, Москва г, вн.тер.г. муниципальный округ Тверской, ул Бутырский Вал, д. 68/70, стр. 1, помещ. 1, комната 44 | M50: 10 | R50: 474215 | S50: 390849 | T50: 502071 | U50: 713679 | V50: 888275 | W50: 12768 | X50: 17664 | Y50: 22897 | Z50: 20296 | AA50: 12655 | AB50: 12768 | AC50: 35508 | AD50: -149088 | AE50: 106226 | AF50: 173720 | AG50: 0 | AH50: 0 | AI50: 0 | AJ50: 0 | AK50: 0 | AL50: 71864 | AM50: 58175 | AN50: 87560 | AO50: 94184 | AP50: 121904 | AQ50: 0 | AR50: 1.87 | AS50: 0 | AT50: creditexpress.ru | AU50: image289 | AW50: ООО ПКО «КЭФ» зарегистрировано по адресу: 127055, Москва г, вн.тер.г. муниципальный округ Тверской, ул Бутырский Вал, д. 68/70, стр. 1, помещ. 1, комната 44. Генеральным директором является Семендуев Виктор Александрович. Рост доходов компании за 5 лет: 187,3%.
A51: 7203492939 | B51: 94 | C51: Общество с ограниченной ответственностью «Профессиональная коллекторская организация «Аскалон» | D51: 7203492939 | E51: 1197232028388 | F51: ООО «ПКО «Аскалон» | G51: 43784 | H51: 5 | I51: Нет | J51: Аксенов Алексей Александрович | K51: Аксенов Алексей Александрович | L51: 628403, Ханты-Мансийский Автономный округ - Югра, г.о. Сургут, г Сургут, ул 30 лет Победы, зд. 44А, офис 8/1 | M51: 10.204 | R51: 11558 | S51: 248629 | T51: 246916 | U51: 163057 | V51: 871130 | W51: 1463 | X51: 237527 | Y51: 231614 | Z51: 166991 | AA51: 772065 | AB51: 1463 | AC51: 8301 | AD51: 9832 | AE51: -14228 | AF51: 6799 | AG51: 1 | AH51: 313 | AI51: 301 | AJ51: 300 | AK51: 300 | AL51: 6745 | AM51: 1006 | AN51: 3370 | AO51: 280455 | AP51: 598217 | AQ51: 576284 | AR51: 75.37 | AS51: Низкий | AT51: dolgi72.ru | AU51: image025 | AV51: 300 | AW51: ООО «ПКО «Аскалон» зарегистрировано по адресу: 628403, Ханты-Мансийский Автономный округ - Югра, г.о. Сургут, г Сургут, ул 30 лет Победы, зд. 44А, офис 8/1. Генеральным директором является Аксенов Алексей Александрович. Рост доходов компании за 5 лет: 7537%. Рост финансовых активов компании за 5 лет: 30000%. Объем заемных средств компании на конец 2024 года: 576284 тыс. руб. ФССП присвоил Низкий уровень риска для данного ПКО.
A52: 7727551797 | B52: 27 | C52: Общество с ограниченной ответственностью Профессиональная коллекторская организация НСВ | D52: 7727551797 | E52: 1057748047675 | F52: ООО ПКО НСВ | G52: 38595 | H52: 19 | I52: Да | J52: Общество С Ограниченной Ответственностью, "АВТОМАТИЗИРОВАННЫЕ ГОЛОСОВЫЕ СИСТЕМЫ", Непубличное Акционерное Общество Профессиональная Коллекторская Организация, "ПЕРВОЕ КЛИЕНТСКОЕ БЮРО" | K52: Виноградов Артур Алексеевич | L52: 108811, Москва г, км Киевское шоссе 22-й (п Московский), 6, 1 | M52: 67600 | R52: 763278 | S52: 794354 | T52: 791529 | U52: 752563 | V52: 751828 | W52: 509133 | X52: 582015 | Y52: 521744 | Z52: 426648 | AA52: 465905 | AB52: 509133 | AC52: -32283 | AD52: 47374 | AE52: 33519 | AF52: 35693 | AG52: 316508 | AH52: 350772 | AI52: 537837 | AJ52: 6380 | AK52: 12115 | AL52: 124537 | AM52: 106926 | AN52: 103491 | AO52: 155738 | AP52: 88079 | AQ52: 0 | AR52: 0.99 | AS52: Низкий | AT52: nrservice.ru | AU52: image200 | AV52: 0.04 | AW52: ООО ПКО НСВ зарегистрировано по адресу: 108811, Москва г, км Киевское шоссе 22-й (п Московский), 6, 1. Генеральным директором является Виноградов Артур Алексеевич. Рост доходов компании за 5 лет: 98,5%. Рост финансовых активов компании за 5 лет: 3,83%. ФССП присвоил Низкий уровень риска для данного ПКО.
A53: 2225130330 | B53: 34 | C53: Общество с ограниченной ответственностью Профессиональная коллекторская организация «Бюро судебного взыскания» | D53: 2225130330 | E53: 1122225006056 | F53: ООО ПКО «БСВ» | G53: 45691 | H53: 0 | I53: Да | J53: Корнилов Станислав Юрьевич | K53: Лукьянов Денис Владимирович | L53: г. Новосибирск, ул. Добролюбова, д. 10/2, 630009 | M53: 20 | R53: 144144 | S53: 230065 | T53: 320820 | U53: 558677 | V53: 642678 | W53: 21683 | X53: 41419 | Y53: 98997 | Z53: 342571 | AA53: 385166 | AB53: 21683 | AC53: 132354 | AD53: 70958 | AE53: -68269 | AF53: -11710 | AG53: 53836 | AH53: 48312 | AI53: 145178 | AJ53: 113541 | AK53: 125535 | AL53: 24420 | AM53: 125403 | AN53: 141779 | AO53: 49726 | AP53: 74119 | AQ53: 76417 | AR53: 4.46 | AS53: Низкий | AT53: bsv0nsk.ru | AU53: image153 | AV53: 2.33 | AW53: ООО ПКО «БСВ» зарегистрировано по адресу: г. Новосибирск, ул. Добролюбова, д. 10/2, 630009. Генеральным директором является Лукьянов Денис Владимирович. Рост доходов компании за 5 лет: 445,9%. Рост финансовых активов компании за 5 лет: 233,18%. Объем заемных средств компании на конец 2024 года: 76417 тыс. руб. ФССП присвоил Низкий уровень риска для данного ПКО.
A54: 7704527702 | B54: 29 | C54: Акционерное общество Профессиональная коллекторская организация «Финансовое Агентство по Сбору Платежей» | D54: 7704527702 | E54: 1047796582305 | F54: АО ПКО «ФАСП» | G54: 38208 | H54: 20 | I54: Да | K54: Давымока Сергей Вячеславович | L54: 121151, Москва г, наб Тараса Шевченко, 23А, пом. 1Н/5 | M54: 773.6 | R54: 862236 | S54: 648052 | T54: 578020 | U54: 686798 | V54: 633524 | W54: 627678 | X54: 316547 | Y54: 326949 | Z54: 526060 | AA54: 424217 | AB54: 627678 | AC54: 182119 | AD54: 110667 | AE54: 30277 | AF54: 139039 | AG54: 96823 | AH54: 100966 | AI54: 66399 | AJ54: 539 | AK54: 33682 | AL54: 78141 | AM54: 138344 | AN54: 79740 | AO54: 62352 | AP54: 121055 | AQ54: 0 | AR54: 0.74 | AS54: Низкий | AT54: fasp.ru | AU54: image157 | AV54: 0.35 | AW54: АО ПКО «ФАСП» зарегистрировано по адресу: 121151, Москва г, наб Тараса Шевченко, 23А, пом. 1Н/5. Генеральным директором является Давымока Сергей Вячеславович. Рост доходов компании за 5 лет: 73,5%. Рост финансовых активов компании за 5 лет: 34,79%. ФССП присвоил Низкий уровень риска для данного ПКО.
A55: 7720498833 | B55: 30 | C55: Общество с ограниченной ответственностью «Профессиональная коллекторская организация «Коллект Солюшенс» | D55: 7720498833 | E55: 1207700116513 | F55: ООО «ПКО «Коллект Солюшенс» | G55: 43903 | H55: 5 | I55: Да | J55: Бояров Андрей Владимирович | K55: Бояров Андрей Владимирович | L55: 111558, Город Москва, пр-кт Свободный, д. 21/2, помещ. 1/1 | M55: 10 | R55: 100 | S55: 181528 | T55: 401275 | U55: 641298 | V55: 633064 | W55: 1359 | X55: 68830 | Y55: 201961 | Z55: 405877 | AA55: 424272 | AB55: 1359 | AC55: 78403 | AD55: 118705 | AE55: 28465 | AF55: 30399 | AG55: 43093 | AH55: 186199 | AI55: 481857 | AJ55: 926352 | AK55: 887718 | AL55: 4299 | AM55: 18241 | AN55: 90229 | AO55: 184509 | AP55: 184509 | AQ55: 985557 | AR55: 6330.64 | AS55: Низкий | AT55: scollect.ru | AU55: image062 | AV55: 20.6 | AW55: ООО «ПКО «Коллект Солюшенс» зарегистрировано по адресу: 111558, Город Москва, пр-кт Свободный, д. 21/2, помещ. 1/1. Генеральным директором является Бояров Андрей Владимирович. Рост доходов компании за 5 лет: 633064%. Рост финансовых активов компании за 5 лет: 2060,01%. Объем заемных средств компании на конец 2024 года: 985557 тыс. руб. ФССП присвоил Низкий уровень риска для данного ПКО.
A56: 6168114626 | B56: 546 | C56: Общество с ограниченной ответственностью «Профессиональная коллекторская организация «ЮРИДИЧЕСКАЯ СЛУЖБА ВЗЫСКАНИЯ» | D56: 6168114626 | E56: 1216100018750 | F56: ООО ПКО «ЮСВ» | G56: 44382 | H56: 3 | I56: Нет | J56: Общество С Ограниченной Ответственностью, "ФИНБРИДЖ" | K56: Спасенная Алена Олеговна | L56: 344091, Ростовская обл, г Ростов-на-Дону, ул Малиновского, 3, 25 | M56: 10000 | R56: 0 | S56: 17357 | T56: 84780 | U56: 141693 | V56: 625885 | W56: 0 | X56: 6230 | Y56: 68610 | Z56: 89958 | AA56: 369240 | AB56: 0 | AC56: 10516 | AD56: 7660 | AE56: 19432 | AF56: 25136 | AG56: 0 | AH56: 16343 | AI56: 149363 | AJ56: 515934 | AK56: 1376077 | AL56: 0 | AM56: 230 | AN56: 796 | AO56: 18713 | AP56: 15739 | AQ56: 940402 | AR56: 36.06 | AT56: inf@usv-ka.ru | AV56: 84.2 | AW56: ООО ПКО «ЮСВ» зарегистрировано по адресу: 344091, Ростовская обл, г Ростов-на-Дону, ул Малиновского, 3, 25. Генеральным директором является Спасенная Алена Олеговна. Рост доходов компании за 5 лет: 3606%. Рост финансовых активов компании за 5 лет: 8419,98%. Объем заемных средств компании на конец 2024 года: 940402 тыс. руб.
A57: 7727465322 | B57: 141 | C57: Общество с ограниченной ответственностью Профессиональная коллекторская организация «Вива Коллект» | D57: 7727465322 | E57: 1217700225148 | F57: ООО ПКО «Вива Коллект» | G57: 44328 | H57: 3 | I57: Нет | J57: Мирончик Роман Борисович, Власов Дмитрий Викторович, Москаленко Андрей Сергеевич, Мурзин Алексей Валерьевич, Пацко Олеся Александровна | K57: Хазиев Азат Рамилевич | L57: 117218, Москва г, ул Кржижановского, 29, 2, Этаж 2 Помещ VIII | M57: 15000 | R57: 0 | S57: 4730 | T57: 84474 | U57: 147285 | V57: 615879 | W57: 0 | X57: 1141 | Y57: 14358 | Z57: 82652 | AA57: 302637 | AB57: 0 | AC57: 2871 | AD57: 53227 | AE57: 10172 | AF57: 111254 | AG57: 0 | AH57: 159363 | AI57: 131388 | AJ57: 360521 | AK57: 865281 | AL57: 0 | AM57: 102 | AN57: 109 | AO57: 79836 | AP57: 97869 | AQ57: 787650 | AR57: 130.21 | AS57: Высокий | AT57: vivacollect.ru | AU57: image374 | AV57: 5.43 | AW57: ООО ПКО «Вива Коллект» зарегистрировано по адресу: 117218, Москва г, ул Кржижановского, 29, 2, Этаж 2 Помещ VIII. Генеральным директором является Хазиев Азат Рамилевич. Рост доходов компании за 5 лет: 13020,7%. Рост финансовых активов компании за 5 лет: 542,96%. Объем заемных средств компании на конец 2024 года: 787650 тыс. руб. ФССП присвоил Высокий уровень риска для данного ПКО.
A58: 9709079818 | B58: 144 | C58: Общество с ограниченной ответственностью «Профессиональная коллекторская организация «Центурион» | D58: 9709079818 | E58: 1227700215467 | F58: ООО ПКО «Центурион» | G58: 44664 | H58: 3 | I58: Нет | J58: Котов Андрей Владимирович | K58: Цыпруш Олег Евгеньевич | L58: 109004, Г.Москва, вн.тер. г. Муниципальный Округ Таганский, ул Николоямская, дом 40/22, строение 4, этаж 1, офис 115 | M58: 10000 | R58: 0 | S58: 0 | T58: 24313 | U58: 110183 | V58: 606029 | W58: 0 | X58: 0 | Y58: 12968 | Z58: 23819 | AA58: 61213 | AB58: 0 | AC58: 0 | AD58: -37816 | AE58: 5755 | AF58: 472389 | AG58: 0 | AH58: 0 | AI58: 0 | AJ58: 0 | AK58: 0 | AL58: 0 | AM58: 0 | AN58: 80550 | AO58: 123241 | AP58: 823925 | AQ58: 234068 | AR58: 24.93 | AS58: Низкий | AT58: centuryon.ru | AU58: image414 | AW58: ООО ПКО «Центурион» зарегистрировано по адресу: 109004, Г.Москва, вн.тер. г. Муниципальный Округ Таганский, ул Николоямская, дом 40/22, строение 4, этаж 1, офис 115. Генеральным директором является Цыпруш Олег Евгеньевич. Рост доходов компании за 5 лет: 2492,6%. Объем заемных средств компании на конец 2024 года: 234068 тыс. руб. ФССП присвоил Низкий уровень риска для данного ПКО.
A59: 7705680245 | B59: 26 | C59: Общество с ограниченной ответственностью Профессиональная коллекторская организация «Столичная Сервисная Компания» | D59: 7705680245 | E59: 1057747813837 | F59: ООО ПКО «ССК» | G59: 38579 | H59: 19 | I59: Да | J59: Общество С Ограниченной Ответственностью Профессиональная Коллекторская Организация, "РЕГИОНАЛЬНАЯ СЛУЖБА ВЗЫСКАНИЯ", Компания С Ограниченной Ответственностью Свеа Экономи Сайпрус Лимитед | K59: Мохначев Дмитрий Вячеславович | L59: 121609, Москва г, б-р Осенний, 23, Помещ. 1 Ком. 20 | M59: 140942.64 | R59: 382354 | S59: 488458 | T59: 736047 | U59: 752672 | V59: 570424 | W59: 102589 | X59: 141204 | Y59: 248067 | Z59: 398836 | AA59: -231515 | AB59: 102589 | AC59: 241141 | AD59: 338174 | AE59: 244594 | AF59: 297977 | AG59: 209741 | AH59: 1039652 | AI59: 1203798 | AJ59: 1255498 | AK59: 1186700 | AL59: 66040 | AM59: 50814 | AN59: 61197 | AO59: 81722 | AP59: 59874 | AQ59: 801048 | AR59: 1.49 | AS59: Низкий | AT59: csc.msk.ru | AU59: image012 | AV59: 5.66 | AW59: ООО ПКО «ССК» зарегистрировано по адресу: 121609, Москва г, б-р Осенний, 23, Помещ. 1 Ком. 20. Генеральным директором является Мохначев Дмитрий Вячеславович. Рост доходов компании за 5 лет: 149,2%. Рост финансовых активов компании за 5 лет: 565,79%. Объем заемных средств компании на конец 2024 года: 801048 тыс. руб. ФССП присвоил Низкий уровень риска для данного ПКО.
A60: 7717528291 | B60: 15 | C60: Общество с ограниченной ответственностью Профессиональная коллекторская организация «Столичное агентство по возврату долгов» | D60: 7717528291 | E60: 1057746413922 | F60: ООО ПКО «Столичное АВД» | G60: 38422 | H60: 20 | I60: Да | J60: Курило Дарья Игоревна, Плохов Артем Валерьевич, Цацуа Давид Владимирович | K60: Цацуа Давид Владимирович | L60: 107564, Москва г, ул Краснобогатырская, 2, 2, 5 | M60: 269039.56 | R60: 977198 | S60: 736019 | T60: 1355386 | U60: 2090358 | V60: 544338 | W60: 680230 | X60: 331274 | Y60: 961053 | Z60: 1747501 | AA60: 163046 | AB60: 680230 | AC60: 12462 | AD60: 115893 | AE60: 21181 | AF60: 21353 | AG60: 28039 | AH60: 121783 | AI60: 345974 | AJ60: 141439 | AK60: 144030 | AL60: 773191 | AM60: 574963 | AN60: 367617 | AO60: 496505 | AP60: 133820 | AQ60: 1607 | AR60: 0.56 | AS60: Низкий | AT60: stcollector.ru | AU60: image083 | AV60: 5.14 | AW60: ООО ПКО «Столичное АВД» зарегистрировано по адресу: 107564, Москва г, ул Краснобогатырская, 2, 2, 5. Генеральным директором является Цацуа Давид Владимирович. Рост доходов компании за 5 лет: 55,7%. Рост финансовых активов компании за 5 лет: 513,68%. Объем заемных средств компании на конец 2024 года: 1607 тыс. руб. ФССП присвоил Низкий уровень риска для данного ПКО.
A61: 7702814010 | B61: 33 | C61: Общество с ограниченной ответственностью Профессиональная коллекторская организация «Агентство Финансового Контроля" | D61: 7702814010 | E61: 1137746368847 | F61: ООО ПКО «АФК» | G61: 41387 | H61: 12 | I61: Нет | J61: Абдуллин Ринат Шамильевич, Нефедов Михаил Геннадьевич | K61: Шарпов Сергей Викторович | L61: 603087, Нижегородская область, г. Нижний Новгород, ш. Казанское, дом 10, корпус 3, помещение 2 | M61: 10000 | R61: 635395 | S61: 629795 | T61: 559685 | U61: 562623 | V61: 540031 | W61: 154566 | X61: 89404 | Y61: 92973 | Z61: 112966 | AA61: 121793 | AB61: 154566 | AC61: 436893 | AD61: 384062 | AE61: 367432 | AF61: 351854 | AG61: 239263 | AH61: 275000 | AI61: 221762 | AJ61: 180502 | AK61: 9747 | AL61: 758 | AM61: 1515 | AN61: 45 | AO61: 1022 | AP61: 3844 | AQ61: 0 | AR61: 0.85 | AS61: Низкий | AT61: oooafk.ru | AU61: image011 | AV61: 0.04 | AW61: ООО ПКО «АФК» зарегистрировано по адресу: 603087, Нижегородская область, г. Нижний Новгород, ш. Казанское, дом 10, корпус 3, помещение 2. Генеральным директором является Шарпов Сергей Викторович. Рост доходов компании за 5 лет: 85%. Рост финансовых активов компании за 5 лет: 4,07%. ФССП присвоил Низкий уровень риска для данного ПКО.
A62: 5260410400 | B62: 40 | C62: Общество с ограниченной ответственностью Профессиональная коллекторская организация «Специализированное Агентство Аналитики и Безопасноти» | D62: 5260410400 | E62: 1155260007209 | F62: ООО ПКО «СААБ» | G62: 42150 | H62: 9 | I62: Нет | J62: Нефедов Михаил Геннадьевич, Абдуллин Ринат Шамильевич | K62: Шарпов Сергей Викторович | L62: 603087, Нижегородская область, г. Нижний Новгород, ш. Казанское, дом 10, корпус 3, помещение 2 | M62: 10000 | R62: 365053 | S62: 427720 | T62: 383873 | U62: 401434 | V62: 501099 | W62: 117104 | X62: 125508 | Y62: 65026 | Z62: 119225 | AA62: 188415 | AB62: 117104 | AC62: 243562 | AD62: 266071 | AE62: 225881 | AF62: 254445 | AG62: 113821 | AH62: 225000 | AI62: 166310 | AJ62: 193164 | AK62: 73510 | AL62: 11837 | AM62: 11785 | AN62: 10954 | AO62: 11422 | AP62: 17746 | AQ62: 0 | AR62: 1.37 | AS62: Низкий | AT62: ooosaab.ru | AU62: image016 | AV62: 0.65 | AW62: ООО ПКО «СААБ» зарегистрировано по адресу: 603087, Нижегородская область, г. Нижний Новгород, ш. Казанское, дом 10, корпус 3, помещение 2. Генеральным директором является Шарпов Сергей Викторович. Рост доходов компании за 5 лет: 137,3%. Рост финансовых активов компании за 5 лет: 64,58%. ФССП присвоил Низкий уровень риска для данного ПКО.
A63: 6230085345 | B63: 35 | C63: Общество с ограниченной ответственностью профессиональная коллекторская организация «СпецСнаб71» | D63: 6230085345 | E63: 1146230003127 | F63: ООО ПКО «СпецСнаб71» | G63: 41838 | H63: 10 | I63: Нет | J63: Сазонов Сергей Владимирович | K63: Сазонов Сергей Владимирович | L63: 390000, Рязанская область, г.о. город Рязань, г Рязань, ул Урицкого, д. 46, д.помещ. Н 48 | M63: 30020 | R63: 308809 | S63: 392415 | T63: 502955 | U63: 550947 | V63: 489090 | W63: 230799 | X63: 277288 | Y63: 292047 | Z63: 211587 | AA63: 157694 | AB63: 230799 | AC63: 5839 | AD63: 44057 | AE63: 147361 | AF63: 112229 | AG63: 791892 | AH63: 167239 | AI63: 246793 | AJ63: 286869 | AK63: 277540 | AL63: 104429 | AM63: 199034 | AN63: 144331 | AO63: 218540 | AP63: 110614 | AQ63: 220728 | AR63: 1.58 | AS63: Значительный | AT63: specsnab71.ru | AU63: image136 | AV63: 0.35 | AW63: ООО ПКО «СпецСнаб71» зарегистрировано по адресу: 390000, Рязанская область, г.о. город Рязань, г Рязань, ул Урицкого, д. 46, д.помещ. Н 48. Генеральным директором является Сазонов Сергей Владимирович. Рост доходов компании за 5 лет: 158,4%. Рост финансовых активов компании за 5 лет: 35,05%. Объем заемных средств компании на конец 2024 года: 220728 тыс. руб. ФССП присвоил Значительный уровень риска для данного ПКО.
A64: 9702030161 | B64: 23 | C64: Общество с ограниченной ответственностью Профессиональная коллекторская организация "Агентство кредитных решений» | D64: 9702030161 | E64: 1217700089386 | F64: ООО ПКО «АКР» | G64: 44256 | H64: 4 | I64: Да | J64: Общество С Ограниченной Ответственностью, "РЕАЛЬНЫЕ ИНВЕСТИЦИИ" | K64: Маршинин Денис Владимирович | L64: 129090, Москва г, пер Ботанический, 5, Этаж 5 Помещ. XV/Ком. 17к | M64: 100 | R64: 0 | S64: 174839 | T64: 263772 | U64: 944874 | V64: 455341 | W64: 0 | X64: -91556 | Y64: -160715 | Z64: -876761 | AA64: 330891 | AB64: 0 | AC64: 53833 | AD64: 83716 | AE64: 1230 | AF64: 69259 | AG64: 0 | AH64: 105955 | AI64: 53341 | AJ64: 96423 | AK64: 76411 | AL64: 0 | AM64: 1281 | AN64: 6172 | AO64: 37432 | AP64: 6247 | AQ64: 53183 | AR64: 2.6 | AS64: Низкий | AT64: csa.com.ru | AU64: image007 | AV64: 0.72 | AW64: ООО ПКО «АКР» зарегистрировано по адресу: 129090, Москва г, пер Ботанический, 5, Этаж 5 Помещ. XV/Ком. 17к. Генеральным директором является Маршинин Денис Владимирович. Рост доходов компании за 5 лет: 260,4%. Рост финансовых активов компании за 5 лет: 72,12%. Объем заемных средств компании на конец 2024 года: 53183 тыс. руб. ФССП присвоил Низкий уровень риска для данного ПКО.
A65: 7716932938 | B65: 52 | C65: Общество с ограниченной ответственностью «Профессиональная коллекторская организация «Первая Гильдия Ростовщиков» | D65: 7716932938 | E65: 1197746143473 | F65: ООО «ПКО «Первая Гильдия Ростовщиков» | G65: 43521 | H65: 6 | I65: Нет | J65: Глухова Эльвира Салаватовна | K65: Глухова Эльвира Салаватовна | L65: 115172, Москва г, Котельническая наб, дом 25, строение 1, офис 15 | M65: 500000 | R65: 8345 | S65: 20791 | T65: 176950 | U65: 291729 | V65: 454097 | W65: 7689 | X65: 19066 | Y65: 171297 | Z65: 240477 | AA65: 408769 | AB65: 7689 | AC65: 1380 | AD65: 4522 | AE65: 12344 | AF65: 27149 | AG65: 0 | AH65: 0 | AI65: 0 | AJ65: 183816 | AK65: 1006527 | AL65: 0 | AM65: 1110 | AN65: 52174 | AO65: 14166 | AP65: 12214 | AQ65: 342765 | AR65: 54.42 | AS65: Низкий | AT65: dolgi0pgr.ru | AU65: image453 | AV65: 5.48 | AW65: ООО «ПКО «Первая Гильдия Ростовщиков» зарегистрировано по адресу: 115172, Москва г, Котельническая наб, дом 25, строение 1, офис 15. Генеральным директором является Глухова Эльвира Салаватовна. Рост доходов компании за 5 лет: 5441,5%. Рост финансовых активов компании за 5 лет: 547,57%. Объем заемных средств компании на конец 2024 года: 342765 тыс. руб. ФССП присвоил Низкий уровень риска для данного ПКО.
A66: 1831191109 | B66: 85 | C66: Общество с ограниченной ответственностью Профессиональная коллекторская организация «СВД» | D66: 1831191109 | E66: 1181832017058 | F66: ООО ПКО «СВД» | G66: 43307 | H66: 6 | I66: Нет | J66: Колпаков Владислав Юрьевич, Общество С Ограниченной Ответственностью, "АГЕНТСТВО+" | K66: Мякишев Иван Владимирович | L66: 426008, Удмуртская Респ, г Ижевск, ул Пушкинская, 266, 302 | M66: 10500 | R66: 270534 | S66: 658417 | T66: 201057 | U66: 175550 | V66: 443384 | W66: 209888 | X66: 405611 | Y66: 69008 | Z66: 352717 | AA66: 440631 | AB66: 209888 | AC66: 284437 | AD66: 152533 | AE66: -206080 | AF66: -29898 | AG66: 398653 | AH66: 656911 | AI66: 491625 | AJ66: 251282 | AK66: 124421 | AL66: 21567 | AM66: 65968 | AN66: 109735 | AO66: 114211 | AP66: 164107 | AQ66: 122258 | AR66: 1.64 | AS66: 0 | AT66: svd18.ru | AU66: image249 | AV66: 0.31 | AW66: ООО ПКО «СВД» зарегистрировано по адресу: 426008, Удмуртская Респ, г Ижевск, ул Пушкинская, 266, 302. Генеральным директором является Мякишев Иван Владимирович. Рост доходов компании за 5 лет: 163,9%. Рост финансовых активов компании за 5 лет: 31,21%. Объем заемных средств компании на конец 2024 года: 122258 тыс. руб.
A67: 2465304196 | B67: 45 | C67: Общество с ограниченной ответственностью профессиональная коллекторская организация«Долг-контроль» | D67: 2465304196 | E67: 1132468067621 | F67: ООО ПКО «Долг-контроль» | G67: 41620 | H67: 11 | I67: Нет | J67: Черкасов Александр Николаевич, Карпова Елена Степановна | K67: Черкасов Александр Николаевич | L67: 660022, Красноярский край, Красноярск г, Партизана Железняка ул, дом № 18, офис 521 | M67: 2620 | R67: 110741 | S67: 251213 | T67: 269950 | U67: 350182 | V67: 424801 | W67: 2551 | X67: 20815 | Y67: 30527 | Z67: 19705 | AA67: 91330 | AB67: 2551 | AC67: 91250 | AD67: 89833 | AE67: 131236 | AF67: 135382 | AG67: 126711 | AH67: 189140 | AI67: 169385 | AJ67: 235618 | AK67: 206249 | AL67: 12116 | AM67: 13161 | AN67: 11 | AO67: 2124 | AP67: 64337 | AQ67: 0 | AR67: 3.84 | AS67: Низкий | AT67: dolgkontol.ru | AU67: image010 | AV67: 1.63 | AW67: ООО ПКО «Долг-контроль» зарегистрировано по адресу: 660022, Красноярский край, Красноярск г, Партизана Железняка ул, дом № 18, офис 521. Генеральным директором является Черкасов Александр Николаевич. Рост доходов компании за 5 лет: 383,6%. Рост финансовых активов компании за 5 лет: 162,77%. ФССП присвоил Низкий уровень риска для данного ПКО.
A68: 7704724468 | B68: 38 | C68: Общество с ограниченной ответственностью «Агентство Региональная организация по сбору долгов» | D68: 7704724468 | E68: 1097746191410 | F68: ООО «Агентство Р.О.С.долгЪ» | G68: 39906 | H68: 16 | I68: Нет | J68: Общество С Ограниченной Ответственностью, "МЭС-РАЗВИТИЕ" | K68: Железнов Андрей Вячеславович | L68: 121069, Город Москва, ул. Поварская, дом 31/29, помещение VI, комната 3 | M68: 1001 | R68: 230817 | S68: 229515 | T68: 278140 | U68: 428400 | V68: 419680 | W68: 6832 | X68: 3415 | Y68: 10740 | Z68: 278257 | AA68: 136327 | AB68: 6832 | AC68: 69011 | AD68: 64555 | AE68: 109788 | AF68: 129021 | AG68: 78860 | AH68: 70959 | AI68: 68232 | AJ68: 0 | AK68: 30000 | AL68: 73455 | AM68: 55962 | AN68: 74618 | AO68: 106955 | AP68: 111320 | AQ68: 10350 | AR68: 1.82 | AS68: Низкий | AT68: rosdolg.com | AU68: image145 | AV68: 0.38 | AW68: ООО «Агентство Р.О.С.долгЪ» зарегистрировано по адресу: 121069, Город Москва, ул. Поварская, дом 31/29, помещение VI, комната 3. Генеральным директором является Железнов Андрей Вячеславович. Рост доходов компании за 5 лет: 181,8%. Рост финансовых активов компании за 5 лет: 38,04%. Объем заемных средств компании на конец 2024 года: 10350 тыс. руб. ФССП присвоил Низкий уровень риска для данного ПКО.
A69: 4345197098 | B69: 61 | C69: Общество с ограниченной ответственностью «Профессиональная коллекторская организация «НБК» | D69: 4345197098 | E69: 1074345040857 | F69: ООО «ПКО «НБК» | G69: 39293 | H69: 17 | I69: Да | J69: Калыгин Сергей Олегович, Новиков Сергей Анатольевич | K69: Калыгин Сергей Олегович | L69: 610001, Кировская обл, Киров г, Красина ул, дом № 5, корпус 4 | M69: 10 | R69: 158398 | S69: 209408 | T69: 225360 | U69: 245769 | V69: 411741 | W69: 126722 | X69: 199897 | Y69: 184612 | Z69: 224751 | AA69: 332500 | AB69: 126722 | AC69: 7557 | AD69: 38627 | AE69: 18396 | AF69: 30842 | AG69: 1000 | AH69: 1004 | AI69: 1004 | AJ69: 1004 | AK69: 1004 | AL69: 68938 | AM69: 83970 | AN69: 67095 | AO69: 280021 | AP69: 282519 | AQ69: 244347 | AR69: 2.6 | AS69: Низкий | AT69: zakon43.ru | AU69: image149 | AV69: 1 | AW69: ООО «ПКО «НБК» зарегистрировано по адресу: 610001, Кировская обл, Киров г, Красина ул, дом № 5, корпус 4. Генеральным директором является Калыгин Сергей Олегович. Рост доходов компании за 5 лет: 259,9%. Рост финансовых активов компании за 5 лет: 100,4%. Объем заемных средств компании на конец 2024 года: 244347 тыс. руб. ФССП присвоил Низкий уровень риска для данного ПКО.
A70: 7735145855 | B70: 21 | C70: Общество с ограниченной ответственностью Профессиональная коллекторская организация «АВРОРА Консалт» | D70: 7735145855 | E70: 1157746706776 | F70: ООО ПКО «АВРОРА Консалт» | G70: 42216 | H70: 9 | I70: Нет | J70: Курышева Виктория Николаевна | K70: Кожевников Антон Алексеевич | L70: 124482, Москва г, Зеленоград г, Савёлкинский проезд, дом 4, помещение XXI, комната 4, офис 4е | M70: 10 | R70: 142343 | S70: 98300 | T70: 862798 | U70: 1148409 | V70: 410172 | W70: 142793 | X70: 96877 | Y70: 852545 | Z70: 1144994 | AA70: 398387 | AB70: 142793 | AC70: 677 | AD70: 6541 | AE70: 2468 | AF70: 2097 | AG70: 0 | AH70: 35840 | AI70: 42659 | AJ70: 45929 | AK70: 61692 | AL70: 31948 | AM70: 0 | AN70: 7949 | AO70: 4201 | AP70: 6646 | AQ70: 4310 | AR70: 2.88 | AS70: Низкий | AT70: avrora0consult.ru | AU70: image107 | AV70: 1.72 | AW70: ООО ПКО «АВРОРА Консалт» зарегистрировано по адресу: 124482, Москва г, Зеленоград г, Савёлкинский проезд, дом 4, помещение XXI, комната 4, офис 4е. Генеральным директором является Кожевников Антон Алексеевич. Рост доходов компании за 5 лет: 288,2%. Рост финансовых активов компании за 5 лет: 172,13%. Объем заемных средств компании на конец 2024 года: 4310 тыс. руб. ФССП присвоил Низкий уровень риска для данного ПКО.
A71: 9705138572 | B71: 48 | C71: Общество с ограниченной ответственностью Профессиональная коллекторская организация «РимБорсо» | D71: 9705138572 | E71: 1197746655468 | F71: ООО ПКО «РБР» | G71: 43780 | H71: 5 | I71: Нет | J71: Трани Винченцо | K71: Базюкин Дмитрий Валериевич | L71: 107023, Москва г, вн.тер.г. муниципальный округ Преображенское, ул Электрозаводская, д. 24, стр. 1, этаж 4, ком. 401 | M71: 10 | R71: 50342 | S71: 132252 | T71: 195257 | U71: 308943 | V71: 406543 | W71: 1206 | X71: 11549 | Y71: 3684 | Z71: 8012 | AA71: 9359 | AB71: 1206 | AC71: 8085 | AD71: 9174 | AE71: 33356 | AF71: 31050 | AG71: 49 | AH71: 49 | AI71: 32356 | AJ71: 83720 | AK71: 88503 | AL71: 10534 | AM71: 17999 | AN71: 22726 | AO71: 31205 | AP71: 52387 | AQ71: 64185 | AR71: 8.08 | AS71: Низкий | AT71: rim0borso.ru | AU71: image216 | AV71: 1806.18 | AW71: ООО ПКО «РБР» зарегистрировано по адресу: 107023, Москва г, вн.тер.г. муниципальный округ Преображенское, ул Электрозаводская, д. 24, стр. 1, этаж 4, ком. 401. Генеральным директором является Базюкин Дмитрий Валериевич. Рост доходов компании за 5 лет: 807,6%. Рост финансовых активов компании за 5 лет: 180618,37%. Объем заемных средств компании на конец 2024 года: 64185 тыс. руб. ФССП присвоил Низкий уровень риска для данного ПКО.
A72: 3123478956 | B72: 139 | C72: Общество с ограниченной ответственностью «Финансовые системы» | D72: 3123478956 | E72: 1213100005359 | F72: ООО «Финансовые системы» | G72: 44298 | H72: 4 | I72: Нет | J72: Общество С Ограниченной Ответственностью Профессиональная Коллекторская Организация, "АЙДИ КОЛЛЕКТ" | K72: Венедиктов Олег Вениаминович | L72: г. Белгород, Народный б-р, д. 79, ОФИС 526А, 308009 | M72: 10000 | R72: 0 | S72: 0 | T72: 0 | U72: 87829 | V72: 358886 | W72: 0 | X72: 181 | Y72: 106 | Z72: 21457 | AA72: 237166 | AB72: 0 | AC72: -99 | AD72: 165 | AE72: 49191 | AF72: 11127 | AG72: 0 | AH72: 9000 | AI72: 0 | AJ72: 131911 | AK72: 126688 | AL72: 0 | AM72: 130 | AN72: 40 | AO72: 2455 | AP72: 17561 | AQ72: 44475 | AR72: 4.09 | AS72: Низкий | AT72: finsistem.ru | AU72: image405 | AV72: 14.08 | AW72: ООО «Финансовые системы» зарегистрировано по адресу: г. Белгород, Народный б-р, д. 79, ОФИС 526А, 308009. Генеральным директором является Венедиктов Олег Вениаминович. Рост доходов компании за 5 лет: 408,6%. Рост финансовых активов компании за 5 лет: 1407,64%. Объем заемных средств компании на конец 2024 года: 44475 тыс. руб. ФССП присвоил Низкий уровень риска для данного ПКО.
A73: 7734387354 | B73: 57 | C73: Общество с ограниченной ответственностью Профессиональная коллекторская организация «Нэйва» | D73: 7734387354 | E73: 1167746657033 | F73: ООО ПКО «Нэйва» | G73: 42564 | H73: 8 | I73: Нет | J73: Киушкина Наталья Вадимовна, Иваночкин Илья Борисович, Максакова Анна Игоревна, Мягкова Ольга Викторовна, Манернова Светлана Олеговна, Князев Александр Юрьевич, Миронова Татьяна Алексеевна, Костина Алла Владимировна, Цветков Алексей Владимирович | K73: Иваночкин Илья Борисович | L73: 117218, Москва г, ул Кржижановского, 15, 5, 402 | M73: 5500 | R73: 196876 | S73: 229833 | T73: 192329 | U73: 254123 | V73: 343700 | W73: 103625 | X73: 135319 | Y73: 121756 | Z73: 169299 | AA73: 197818 | AB73: 103625 | AC73: 67444 | AD73: 59558 | AE73: 75878 | AF73: 136419 | AG73: 355977 | AH73: 220977 | AI73: 157003 | AJ73: 111811 | AK73: 254106 | AL73: 152404 | AM73: 408287 | AN73: 466886 | AO73: 610282 | AP73: 579876 | AQ73: 15917 | AR73: 1.75 | AS73: Низкий | AT73: нэйва.рф | AU73: image108 | AV73: 0.71 | AW73: ООО ПКО «Нэйва» зарегистрировано по адресу: 117218, Москва г, ул Кржижановского, 15, 5, 402. Генеральным директором является Иваночкин Илья Борисович. Рост доходов компании за 5 лет: 174,6%. Рост финансовых активов компании за 5 лет: 71,38%. Объем заемных средств компании на конец 2024 года: 15917 тыс. руб. ФССП присвоил Низкий уровень риска для данного ПКО.
A74: 7716764909 | B74: 42 | C74: Общество с ограниченной ответственностью Профессиональная коллекторская организация «ЭВЕРЕСТ» | D74: 7716764909 | E74: 1147746052475 | F74: ООО ПКО «ЭВЕРЕСТ» | G74: 41667 | H74: 11 | I74: Да | J74: Архипов Павел Сергеевич, Арсентьев Евгений Валерьевич, Чернышов Дмитрий Сергеевич | K74: Чернышов Дмитрий Сергеевич | L74: 109147, Москва г, ул Марксистская, 34, 8 | M74: 10723.46 | R74: 195184 | S74: 229247 | T74: 297123 | U74: 371405 | V74: 340587 | W74: 124366 | X74: 140440 | Y74: 185181 | Z74: 247265 | AA74: 215366 | AB74: 124366 | AC74: 1732 | AD74: 14963 | AE74: 18846 | AF74: 11007 | AG74: 155 | AH74: 0 | AI74: 0 | AJ74: 0 | AK74: 0 | AL74: 22573 | AM74: 24700 | AN74: 41268 | AO74: 57975 | AP74: 21934 | AQ74: 0 | AR74: 1.75 | AS74: 0 | AT74: everestcollect.ru | AU74: image217 | AV74: 0 | AW74: ООО ПКО «ЭВЕРЕСТ» зарегистрировано по адресу: 109147, Москва г, ул Марксистская, 34, 8. Генеральным директором является Чернышов Дмитрий Сергеевич. Рост доходов компании за 5 лет: 174,5%.
A75: 6685168732 | B75: 50 | C75: Общество с ограниченной ответственностью «Профессиональная коллекторская организация «Синара партнер» | D75: 6685168732 | E75: 1196658076196 | F75: ООО «ПКО «Синара партнер» | G75: 43777 | H75: 5 | I75: Нет | J75: Акционерное Общество Банк Синара | K75: Кисляков Алексей Владимирович | L75: 620026, Свердловская обл, г Екатеринбург, ул Куйбышева, стр. 58, офис 203 | M75: 319000 | R75: 43 | S75: 290321 | T75: 362230 | U75: 425762 | V75: 337579 | W75: 529 | X75: 1173 | Y75: 5353 | Z75: 40904 | AA75: 78624 | AB75: 529 | AC75: -20412 | AD75: 32400 | AE75: 100818 | AF75: 32985 | AG75: 0 | AH75: 2636 | AI75: 7626 | AJ75: 7808 | AK75: 36840 | AL75: 862 | AM75: 3966 | AN75: 280 | AO75: 41063 | AP75: 74132 | AQ75: 0 | AR75: 7850.67 | AS75: Низкий | AT75: lcc0partner.ru | AU75: image336 | AV75: 13.98 | AW75: ООО «ПКО «Синара партнер» зарегистрировано по адресу: 620026, Свердловская обл, г Екатеринбург, ул Куйбышева, стр. 58, офис 203. Генеральным директором является Кисляков Алексей Владимирович. Рост доходов компании за 5 лет: 785067,4%. Рост финансовых активов компании за 5 лет: 1397,57%. ФССП присвоил Низкий уровень риска для данного ПКО.
A76: 7716859501 | B76: 66 | C76: Общество с ограниченной ответственностью Профессиональная коллекторская организация «АЛЬФА» | D76: 7716859501 | E76: 1177746530158 | F76: ООО ПКО «АЛЬФА» | G76: 42885 | H76: 7 | I76: Да | J76: Тилежинский Константин Вячеславович, Зудин Сергей Андреевич, Шведкова Ольга Владимировна | K76: Зудин Сергей Андреевич | L76: 129346, Город Москва, вн.тер. г. Муниципальный Округ Лосиноостровский, ул Изумрудная, дом 18, этаж 5, ПОМЕЩ.XIII, комната 20, ОФИС 5Р | M76: 10.1 | R76: 247721 | S76: 88564 | T76: 135160 | U76: 217653 | V76: 320403 | W76: 233679 | X76: 81034 | Y76: 118912 | Z76: 154218 | AA76: 254769 | AB76: 233679 | AC76: 6303 | AD76: 10792 | AE76: 50617 | AF76: 42668 | AG76: 14918 | AH76: 0 | AI76: 0 | AJ76: 0 | AK76: 22 | AL76: 42298 | AM76: 56384 | AN76: 58324 | AO76: 56497 | AP76: 108682 | AQ76: 37534 | AR76: 1.29 | AS76: Низкий | AT76: alfacollection.ru | AU76: image167 | AV76: 0 | AW76: ООО ПКО «АЛЬФА» зарегистрировано по адресу: 129346, Город Москва, вн.тер. г. Муниципальный Округ Лосиноостровский, ул Изумрудная, дом 18, этаж 5, ПОМЕЩ.XIII, комната 20, ОФИС 5Р. Генеральным директором является Зудин Сергей Андреевич. Рост доходов компании за 5 лет: 129,3%. Рост финансовых активов компании за 5 лет: 0,15%. Объем заемных средств компании на конец 2024 года: 37534 тыс. руб. ФССП присвоил Низкий уровень риска для данного ПКО.
A77: 6311196251 | B77: 473 | C77: Общество с ограниченной ответственностью профессиональная коллекторская организация «Контур» | D77: 6311196251 | E77: 1236300017546 | F77: ООО ПКО «Контур» | G77: 45104 | H77: 1 | I77: Нет | J77: Бэр Ирина Павловна | K77: Бэр Ирина Павловна | L77: 443093, Самарская область, г.о. Самара, вн.р-н Железнодорожный, г Самара, ул Мориса Тореза, дом 1А, офис 511 | M77: 10 | R77: 0 | S77: 0 | T77: 0 | U77: 1 | V77: 317450 | W77: 0 | X77: 0 | Y77: 0 | Z77: 106 | AA77: 2081 | AB77: 0 | AC77: 0 | AD77: 0 | AE77: -486 | AF77: 244960 | AG77: 0 | AH77: 0 | AI77: 0 | AJ77: 4134 | AK77: 279427 | AL77: 0 | AM77: 0 | AN77: 0 | AO77: 131 | AP77: 48643 | AQ77: 35220 | AR77: 317450 | AS77: Низкий | AT77: kontur7.ru | AU77: image474 | AV77: 67.59 | AW77: ООО ПКО «Контур» зарегистрировано по адресу: 443093, Самарская область, г.о. Самара, вн.р-н Железнодорожный, г Самара, ул Мориса Тореза, дом 1А, офис 511. Генеральным директором является Бэр Ирина Павловна. Рост доходов компании за 5 лет: 31745000%. Рост финансовых активов компании за 5 лет: 6759,24%. Объем заемных средств компании на конец 2024 года: 35220 тыс. руб. ФССП присвоил Низкий уровень риска для данного ПКО.
A78: 1831167427 | B78: 68 | C78: Общество с ограниченной ответственностью Профессиональная коллекторская организация «Экспресс Коллекшн» | D78: 1831167427 | E78: 1141831003192 | F78: ООО ПКО «Экспресс Коллекшн» | G78: 41837 | H78: 10 | I78: Да | J78: Чирков Константин Николаевич, Зайцев Сергей Владимирович | K78: Чирков Константин Николаевич | L78: 426006, Удмуртская Респ, г Ижевск, проезд им Дерябина, 3, 314 | M78: 10000 | R78: 74072 | S78: 88679 | T78: 134747 | U78: 210100 | V78: 306735 | W78: 15382 | X78: 11204 | Y78: 6779 | Z78: 129804 | AA78: 146635 | AB78: 15382 | AC78: 31092 | AD78: 84818 | AE78: 71814 | AF78: 140768 | AG78: 103086 | AH78: 111076 | AI78: 167495 | AJ78: 245024 | AK78: 323603 | AL78: 3901 | AM78: 8625 | AN78: 5224 | AO78: 10959 | AP78: 11962 | AQ78: 0 | AR78: 4.14 | AS78: Низкий | AT78: collect118.ru | AU78: image1001 | AV78: 3.14 | AW78: ООО ПКО «Экспресс Коллекшн» зарегистрировано по адресу: 426006, Удмуртская Респ, г Ижевск, проезд им Дерябина, 3, 314. Генеральным директором является Чирков Константин Николаевич. Рост доходов компании за 5 лет: 414,1%. Рост финансовых активов компании за 5 лет: 313,92%. ФССП присвоил Низкий уровень риска для данного ПКО.
A79: 6316284222 | B79: 523 | C79: Общество с ограниченной ответственностью профессиональная коллекторская организация «Куратор» | D79: 6316284222 | E79: 1236300017557 | F79: ООО ПКО «Куратор» | G79: 45104 | H79: 1 | I79: Нет | J79: Каменская Анна Вячеславовна | K79: Каменская Анна Вячеславовна | L79: 443086, Самарская область, г.о. Самара, вн.р-н Октябрьский, г Самара, ул Ерошевского, дом 3, офис 10 | M79: 10 | R79: 0 | S79: 0 | T79: 0 | U79: 0 | V79: 302833 | W79: 0 | X79: 0 | Y79: 0 | Z79: 100 | AA79: 214182 | AB79: 0 | AC79: 0 | AD79: 0 | AE79: -913 | AF79: 21029 | AG79: 0 | AH79: 0 | AI79: 0 | AJ79: 0 | AK79: 2342 | AL79: 0 | AM79: 0 | AN79: 0 | AO79: 96 | AP79: 38866 | AQ79: 0 | AS79: Низкий | AT79: qurator.ru | AU79: image466 | AW79: ООО ПКО «Куратор» зарегистрировано по адресу: 443086, Самарская область, г.о. Самара, вн.р-н Октябрьский, г Самара, ул Ерошевского, дом 3, офис 10. Генеральным директором является Каменская Анна Вячеславовна. ФССП присвоил Низкий уровень риска для данного ПКО.
A80: 7806547391 | B80: 46 | C80: Общество с ограниченной ответственностью профессиональная коллекторская организация «Долговой Консультант» | D80: 7806547391 | E80: 1187847227270 | F80: ООО ПКО «ДОК» | G80: 43326 | H80: 6 | I80: Нет | J80: Аксёнов Денис Александрович, Общество С Ограниченной Ответственностью, "ФИНАНСОВЫЕ РЕШЕНИЯ" | K80: Аксёнов Денис Александрович | L80: 192019, г.Санкт-Петербург, ул.Профессора Качалова, д.7, корп.лите А, 16-Н/711 | M80: 1000 | R80: 340794 | S80: 428036 | T80: 283911 | U80: 328407 | V80: 301867 | W80: 213982 | X80: 236847 | Y80: 193185 | Z80: 160545 | AA80: 206655 | AB80: 213982 | AC80: 117265 | AD80: 31262 | AE80: 103022 | AF80: 25170 | AG80: 227351 | AH80: 335700 | AI80: 342226 | AJ80: 291534 | AK80: 376978 | AL80: 69666 | AM80: 67676 | AN80: 87620 | AO80: 113477 | AP80: 263718 | AQ80: 277000 | AR80: 0.89 | AS80: Низкий | AT80: dolgcons.ru | AU80: image079 | AV80: 1.66 | AW80: ООО ПКО «ДОК» зарегистрировано по адресу: 192019, г.Санкт-Петербург, ул.Профессора Качалова, д.7, корп.лите А, 16-Н/711. Генеральным директором является Аксёнов Денис Александрович. Рост доходов компании за 5 лет: 88,6%. Рост финансовых активов компании за 5 лет: 165,81%. Объем заемных средств компании на конец 2024 года: 277000 тыс. руб. ФССП присвоил Низкий уровень риска для данного ПКО.
A81: 6658506936 | B81: 70 | C81: Общество с ограниченной ответственностью «Профессиональная коллекторская организация «Голиаф» | D81: 6658506936 | E81: 1176658096306 | F81: ООО ПКО «Голиаф» | G81: 43013 | H81: 7 | I81: Нет | J81: Котельников Георгий Викторович, Чепелев Леонид Юрьевич | K81: Котельников Георгий Викторович | L81: 620000, Свердловская область, г.о. город Екатеринбург, г Екатеринбург, ул Мамина-Сибиряка, стр. 101, помещ. 5.17 | M81: 200 | R81: 35506 | S81: 59003 | T81: 99116 | U81: 204583 | V81: 296567 | W81: 155 | X81: 38359 | Y81: 60548 | Z81: 113666 | AA81: 196032 | AB81: 155 | AC81: 16906 | AD81: 28796 | AE81: 77058 | AF81: 44894 | AG81: 13862 | AH81: 472 | AI81: 297 | AJ81: 146448 | AK81: 179786 | AL81: 3675 | AM81: 66476 | AN81: 92386 | AO81: 11384 | AP81: 22138 | AQ81: 45115 | AR81: 8.35 | AS81: 0 | AT81: ka0goliaf.ru | AU81: image124 | AV81: 12.97 | AW81: ООО ПКО «Голиаф» зарегистрировано по адресу: 620000, Свердловская область, г.о. город Екатеринбург, г Екатеринбург, ул Мамина-Сибиряка, стр. 101, помещ. 5.17. Генеральным директором является Котельников Георгий Викторович. Рост доходов компании за 5 лет: 835,3%. Рост финансовых активов компании за 5 лет: 1296,97%. Объем заемных средств компании на конец 2024 года: 45115 тыс. руб.
A82: 2635227255 | B82: 89 | C82: Общество с ограниченной ответственностью профессиональная коллекторская организация «Межрегиональный консалтинговый центр» | D82: 2635227255 | E82: 1172651008078 | F82: ООО ПКО «МКЦ» | G82: 42839 | H82: 8 | I82: Нет | J82: Колесникова Марина Сергеевна | K82: Колесникова Марина Сергеевна | L82: 355003, Ставропольский край, г Ставрополь, ул Дзержинского, 160, 177 | M82: 10150 | R82: 13729 | S82: 22306 | T82: 32065 | U82: 167581 | V82: 289940 | W82: 6456 | X82: 21725 | Y82: 0 | Z82: 0 | AA82: 0 | AB82: 6456 | AC82: 173 | AD82: 972 | AE82: 108376 | AF82: 111233 | AG82: 10010 | AH82: 16049 | AI82: 44810 | AJ82: 238025 | AK82: 302649 | AL82: 53 | AM82: 279 | AN82: 353 | AO82: 0 | AP82: 0 | AQ82: 98506 | AR82: 21.12 | AS82: Низкий | AT82: mkc0collection.ru | AU82: image225 | AV82: 30.23 | AW82: ООО ПКО «МКЦ» зарегистрировано по адресу: 355003, Ставропольский край, г Ставрополь, ул Дзержинского, 160, 177. Генеральным директором является Колесникова Марина Сергеевна. Рост доходов компании за 5 лет: 2111,9%. Рост финансовых активов компании за 5 лет: 3023,47%. Объем заемных средств компании на конец 2024 года: 98506 тыс. руб. ФССП присвоил Низкий уровень риска для данного ПКО.
A83: 9726053295 | B83: 281 | C83: Общество с ограниченной ответственностью Профессиональная коллекторская организация «Ваш долг» | D83: 9726053295 | E83: 1237700607352 | F83: ООО ПКО «Ваш долг» | G83: 45182 | H83: 1 | I83: Нет | J83: Калёнова Екатерина Владимировна | K83: Калёнова Екатерина Владимировна | L83: 117545, Москва г, ул Дорожная, 8, 1 | M83: 10000 | R83: 0 | S83: 0 | T83: 0 | U83: 17666 | V83: 272213 | W83: 0 | X83: 0 | Y83: 0 | Z83: 17349 | AA83: 263085 | AB83: 0 | AC83: 0 | AD83: 0 | AE83: 316 | AF83: 5159 | AG83: 0 | AH83: 0 | AI83: 0 | AJ83: 0 | AK83: 12 | AL83: 0 | AM83: 0 | AN83: 0 | AO83: 17803 | AP83: 28712 | AQ83: 0 | AR83: 15.41 | AS83: Низкий | AT83: vash0dolg.ru | AU83: image464 | AW83: ООО ПКО «Ваш долг» зарегистрировано по адресу: 117545, Москва г, ул Дорожная, 8, 1. Генеральным директором является Калёнова Екатерина Владимировна. Рост доходов компании за 5 лет: 1540,9%. ФССП присвоил Низкий уровень риска для данного ПКО.
A84: 3801108273 | B84: 44 | C84: Общество с ограниченной ответственностью «Профессиональная коллекторская организация Компания Траст» | D84: 3801108273 | E84: 1103801001963 | F84: ООО « ПКО Компания Траст» | G84: 40309 | H84: 14 | I84: Нет | J84: Калёнова Екатерина Владимировна | K84: Калёнова Екатерина Владимировна | L84: 665801, Иркутская обл, г.о. Ангарское, г Ангарск, кв-л 252, стр. 19, офис 208 | M84: 20 | R84: 316611 | S84: 332291 | T84: 370139 | U84: 352502 | V84: 271822 | W84: 42474 | X84: 61422 | Y84: 88045 | Z84: 86860 | AA84: 52271 | AB84: 42474 | AC84: 127497 | AD84: 139694 | AE84: 135338 | AF84: 97903 | AG84: 265933 | AH84: 244812 | AI84: 217055 | AJ84: 209760 | AK84: 261720 | AL84: 8705 | AM84: 13065 | AN84: 11608 | AO84: 9114 | AP84: 10645 | AQ84: 0 | AR84: 0.86 | AS84: Низкий | AT84: trust0k.ru | AU84: image301 | AV84: 0.98 | AW84: ООО « ПКО Компания Траст» зарегистрировано по адресу: 665801, Иркутская обл, г.о. Ангарское, г Ангарск, кв-л 252, стр. 19, офис 208. Генеральным директором является Калёнова Екатерина Владимировна. Рост доходов компании за 5 лет: 85,9%. Рост финансовых активов компании за 5 лет: 98,42%. ФССП присвоил Низкий уровень риска для данного ПКО.
A85: 5032094681 | B85: 49 | C85: Общество с ограниченной ответственностью «Профессиональная коллекторская организация «Кредит Инкасо Рус» | D85: 5032094681 | E85: 1035006495171 | F85: ООО «ПКО «Кредит Инкасо Рус» | G85: 37890 | H85: 21 | I85: Да | J85: Долюк Андрей Николаевич, Самбудагва Ксения Павловна | K85: Долюк Андрей Николаевич | L85: 127273, Москва г, Березовая аллея, дом № 5А, строение 7, помещение 4 | M85: 99376.385 | R85: 493422 | S85: 464565 | T85: 399894 | U85: 307702 | V85: 271096 | W85: 239109 | X85: 184782 | Y85: 147071 | Z85: 123111 | AA85: 109982 | AB85: 239109 | AC85: 211390 | AD85: 191851 | AE85: 139104 | AF85: 149172 | AG85: 480337 | AH85: 561975 | AI85: 567071 | AJ85: 649733 | AK85: 786643 | AL85: 29987 | AM85: 10271 | AN85: 5807 | AO85: 23957 | AP85: 31473 | AQ85: 0 | AR85: 0.55 | AS85: Высокий | AT85: kredytinkaso.ru | AU85: image055 | AV85: 1.64 | AW85: ООО «ПКО «Кредит Инкасо Рус» зарегистрировано по адресу: 127273, Москва г, Березовая аллея, дом № 5А, строение 7, помещение 4. Генеральным директором является Долюк Андрей Николаевич. Рост доходов компании за 5 лет: 54,9%. Рост финансовых активов компании за 5 лет: 163,77%. ФССП присвоил Высокий уровень риска для данного ПКО.
A86: 3801128449 | B86: 41 | C86: Общество с ограниченной ответственностью «Профессиональная коллекторская организация Траст-Западная Сибирь» | D86: 3801128449 | E86: 1143801000463 | F86: ООО «ПКО Траст-Западная Сибирь» | G86: 41682 | H86: 11 | I86: Нет | J86: Долюк Андрей Николаевич, Самбудагва Ксения Павловна | K86: Долюк Андрей Николаевич | L86: 665801, Иркутская обл, г.о. Ангарское, г Ангарск, кв-л 252, стр. 19, офис 203 | M86: 20 | R86: 333310 | S86: 379404 | T86: 425733 | U86: 379503 | V86: 269406 | W86: 62468 | X86: 67449 | Y86: 91259 | Z86: 74416 | AA86: 44951 | AB86: 62468 | AC86: 163958 | AD86: 189898 | AE86: 186207 | AF86: 118284 | AG86: 87497 | AH86: 67870 | AI86: 79302 | AJ86: 150796 | AK86: 167414 | AL86: 2393 | AM86: 4753 | AN86: 7825 | AO86: 6009 | AP86: 11363 | AQ86: 0 | AR86: 0.81 | AS86: 0 | AT86: trust0zs.ru | AU86: image299 | AV86: 1.91 | AW86: ООО «ПКО Траст-Западная Сибирь» зарегистрировано по адресу: 665801, Иркутская обл, г.о. Ангарское, г Ангарск, кв-л 252, стр. 19, офис 203. Генеральным директором является Долюк Андрей Николаевич. Рост доходов компании за 5 лет: 80,8%. Рост финансовых активов компании за 5 лет: 191,34%.
A87: 7327093648 | B87: 59 | C87: Общество с ограниченной ответственностью «Профессиональная коллекторская организация «Бюро взыскания «Правёж» | D87: 7327093648 | E87: 1207300000148 | F87: ООО «ПКО «БВ «Правёж» | G87: 43840 | H87: 5 | I87: Нет | J87: Бринзевич Наталья Константиновна, Закатий Сергей Владимирович | K87: Бринзевич Наталья Константиновна | L87: 432045, Ульяновская обл, г Ульяновск, ш Московское, 40а, Строение 4 | M87: 11000 | R87: 20309 | S87: 80845 | T87: 156494 | U87: 249725 | V87: 267042 | W87: 15058 | X87: 57585 | Y87: 105785 | Z87: 209405 | AA87: 193583 | AB87: 15058 | AC87: 18453 | AD87: 49328 | AE87: 23245 | AF87: 56553 | AG87: 0 | AH87: 0 | AI87: 0 | AJ87: 0 | AK87: 0 | AL87: 30467 | AM87: 123018 | AN87: 255505 | AO87: 305574 | AP87: 327241 | AQ87: 163556 | AR87: 13.15 | AS87: Низкий | AT87: bv0pravezh.ru | AU87: image006 | AW87: ООО «ПКО «БВ «Правёж» зарегистрировано по адресу: 432045, Ульяновская обл, г Ульяновск, ш Московское, 40а, Строение 4. Генеральным директором является Бринзевич Наталья Константиновна. Рост доходов компании за 5 лет: 1314,9%. Объем заемных средств компании на конец 2024 года: 163556 тыс. руб. ФССП присвоил Низкий уровень риска для данного ПКО.
A88: 5406805083 | B88: 67 | C88: Общество с ограниченной ответственностью Профессиональная Коллекторская Организация «Бустер.Ру» | D88: 5406805083 | E88: 1205400014467 | F88: ООО ПКО «Бустер.Ру» | G88: 43903 | H88: 5 | I88: Нет | J88: Пащенко Максим Григорьевич | K88: Селиверстова Екатерина Владимировна | L88: 630099, Новосибирская область, г Новосибирск, ул Советская, д. 23 | M88: 10000 | R88: 8077 | S88: 33122 | T88: 222282 | U88: 215248 | V88: 258846 | W88: 170 | X88: 17544 | Y88: 217558 | Z88: 212292 | AA88: 140531 | AB88: 170 | AC88: 15335 | AD88: 2679 | AE88: 1051 | AF88: 78685 | AG88: 4942 | AH88: 4838 | AI88: 5838 | AJ88: 37826 | AK88: 304962 | AL88: 7163 | AM88: 24239 | AN88: 30943 | AO88: 41730 | AP88: 163 | AQ88: 200040 | AR88: 32.05 | AS88: Низкий | AT88: ca0mir.ru | AU88: image1001 | AV88: 61.71 | AW88: ООО ПКО «Бустер.Ру» зарегистрировано по адресу: 630099, Новосибирская область, г Новосибирск, ул Советская, д. 23. Генеральным директором является Селиверстова Екатерина Владимировна. Рост доходов компании за 5 лет: 3204,7%. Рост финансовых активов компании за 5 лет: 6170,82%. Объем заемных средств компании на конец 2024 года: 200040 тыс. руб. ФССП присвоил Низкий уровень риска для данного ПКО.
A89: 7714365867 | B89: 104 | C89: Общество с ограниченной ответственностью Профессиональная коллекторская организация «РМК-Коллектинг» | D89: 7714365867 | E89: 5157746145123 | F89: ООО ПКО «РМК-Коллектинг» | G89: 42345 | H89: 9 | I89: Да | J89: Морозов Александр Александрович, Курош Павел Янович | K89: Морозов Александр Александрович | L89: 123007, Город Москва, вн.тер. г. Муниципальный Округ Хорошевский, ш Хорошёвское, дом 35, корпус 1, помещение 7 | M89: 10 | R89: 120602 | S89: 49925 | T89: 57022 | U89: 146383 | V89: 253459 | W89: 53581 | X89: 34432 | Y89: 45225 | Z89: 71329 | AA89: 283226 | AB89: 53581 | AC89: 14160 | AD89: 10990 | AE89: 73477 | AF89: -35915 | AG89: 0 | AH89: 0 | AI89: 0 | AJ89: 0 | AK89: 0 | AL89: 90087 | AM89: 91152 | AN89: 108636 | AO89: 178774 | AP89: 389531 | AQ89: 0 | AR89: 2.1 | AS89: Низкий | AT89: rmc0collecting.ru | AU89: image128 | AW89: ООО ПКО «РМК-Коллектинг» зарегистрировано по адресу: 123007, Город Москва, вн.тер. г. Муниципальный Округ Хорошевский, ш Хорошёвское, дом 35, корпус 1, помещение 7. Генеральным директором является Морозов Александр Александрович. Рост доходов компании за 5 лет: 210,2%. ФССП присвоил Низкий уровень риска для данного ПКО.
A90: 5406973190 | B90: 545 | C90: Общество с ограниченной ответственностью Профессиональная коллекторская организация «Агентство финансовых решений» | D90: 5406973190 | E90: 1175476034150 | F90: ООО ПКО «Агентство финансовых решений» | G90: 42824 | H90: 8 | I90: Нет | J90: Парунов Алексей Викторович | K90: Рузина Дарья Андреевна | L90: г. Новосибирск, ул. Шевченко, д. 15/1, этаж 4, помещение 20, 630102 | M90: 11020 | R90: 13387 | S90: 2858 | T90: 126325 | U90: 30023 | V90: 249725 | W90: 13318 | X90: 223 | Y90: 123737 | Z90: 33659 | AA90: 159953 | AB90: 13318 | AC90: 2115 | AD90: 2035 | AE90: -4015 | AF90: 71781 | AG90: 0 | AH90: 0 | AI90: 0 | AJ90: 0 | AK90: 0 | AL90: 114 | AM90: 24027 | AN90: 19162 | AO90: 15944 | AP90: 129402 | AQ90: 0 | AR90: 18.65 | AT90: info@ka-afr.ru | AW90: ООО ПКО «Агентство финансовых решений» зарегистрировано по адресу: г. Новосибирск, ул. Шевченко, д. 15/1, этаж 4, помещение 20, 630102. Генеральным директором является Рузина Дарья Андреевна. Рост доходов компании за 5 лет: 1865,4%.
A91: 7717795970 | B91: 78 | C91: Общество с ограниченной ответственностью Профессиональная коллекторская организация «ДоброЗайм» | D91: 7717795970 | E91: 5147746190851 | F91: ООО ПКО «ДоброЗайм» | G91: 41918 | H91: 10 | I91: Да | J91: Моисеев Антон Викторович | K91: Васильева Амира Анатольевна | L91: 119180, Москва г, пер Старомонетный, 14, 2, 6-2 | M91: 4000 | R91: 1886 | S91: 130718 | T91: 106053 | U91: 196476 | V91: 248095 | W91: 520 | X91: 87671 | Y91: 96227 | Z91: -139104 | AA91: 338984 | AB91: 520 | AC91: 36340 | AD91: 149352 | AE91: 51227 | AF91: -94696 | AG91: 57565 | AH91: 173855 | AI91: 261801 | AJ91: 309835 | AK91: 145779 | AL91: 6151 | AM91: 14752 | AN91: 29811 | AO91: 58812 | AP91: 124506 | AQ91: 54329 | AR91: 131.55 | AS91: Низкий | AT91: pko0dbrz.ru | AU91: image054 | AV91: 2.53 | AW91: ООО ПКО «ДоброЗайм» зарегистрировано по адресу: 119180, Москва г, пер Старомонетный, 14, 2, 6-2. Генеральным директором является Васильева Амира Анатольевна. Рост доходов компании за 5 лет: 13154,6%. Рост финансовых активов компании за 5 лет: 253,24%. Объем заемных средств компании на конец 2024 года: 54329 тыс. руб. ФССП присвоил Низкий уровень риска для данного ПКО.
A92: 4632195224 | B92: 81 | C92: Общество с ограниченной ответственностью «Профессиональная коллекторская организация Центр Альтернативного Финансирования» | D92: 4632195224 | E92: 1144632011380 | F92: ООО «ПКО Центр Альтернативного Финансирования» | G92: 41918 | H92: 10 | I92: Нет | J92: Синяков Владимир Иванович | K92: Синяков Владимир Иванович | L92: 305000, Курская область, г.о. Город Курск, г Курск, ул Марата, дом 21, этаж 2, помещение I | M92: 20 | R92: 44121 | S92: 82029 | T92: 122222 | U92: 185710 | V92: 241823 | W92: 23068 | X92: 62790 | Y92: 69607 | Z92: 54544 | AA92: 105781 | AB92: 23068 | AC92: 15202 | AD92: 46656 | AE92: 121843 | AF92: 100423 | AG92: 0 | AH92: 0 | AI92: 0 | AJ92: 0 | AK92: 0 | AL92: 56366 | AM92: 51978 | AN92: 83824 | AO92: 179234 | AP92: 402552 | AQ92: 191309 | AR92: 5.48 | AS92: Низкий | AT92: alternativacentr.ru | AU92: image056 | AW92: ООО «ПКО Центр Альтернативного Финансирования» зарегистрировано по адресу: 305000, Курская область, г.о. Город Курск, г Курск, ул Марата, дом 21, этаж 2, помещение I. Генеральным директором является Синяков Владимир Иванович. Рост доходов компании за 5 лет: 548,1%. Объем заемных средств компании на конец 2024 года: 191309 тыс. руб. ФССП присвоил Низкий уровень риска для данного ПКО.
A93: 9725016460 | B93: 168 | C93: Общество с ограниченной ответственностью «ЮК Омега групп» | D93: 9725016460 | E93: 1197746458139 | F93: ООО «ЮК Омега групп» | G93: 43665 | H93: 5 | I93: Нет | J93: Алимов Ильдар Халитович, Шарков Тимофей Владимирович | K93: Алимов Ильдар Халитович | L93: 105523, Москва г, Щёлковское ш, дом 92, корпус 6, квартира 5 | M93: 10 | R93: 940 | S93: 7401 | T93: 44028 | U93: 56579 | V93: 241565 | W93: 367 | X93: 1835 | Y93: 17942 | Z93: 28400 | AA93: 134074 | AB93: 367 | AC93: 5197 | AD93: 24590 | AE93: 26452 | AF93: 94039 | AG93: 0 | AH93: 0 | AI93: 0 | AJ93: 0 | AK93: 0 | AL93: 36 | AM93: 756 | AN93: 7552 | AO93: 9707 | AP93: 2382 | AQ93: 0 | AR93: 256.98 | AS93: Низкий | AT93: dolgi0omega.ru | AU93: image422 | AW93: ООО «ЮК Омега групп» зарегистрировано по адресу: 105523, Москва г, Щёлковское ш, дом 92, корпус 6, квартира 5. Генеральным директором является Алимов Ильдар Халитович. Рост доходов компании за 5 лет: 25698,4%. ФССП присвоил Низкий уровень риска для данного ПКО.
A94: 6164244208 | B94: 62 | C94: Общество с ограниченной ответственностью «Профессиональная Коллекторская Организация «Сила Права» | D94: 6164244208 | E94: 1066164002354 | F94: ООО «ПКО «СП» | G94: 38744 | H94: 19 | I94: Нет | J94: Бревдо Михаил Григорьевич, Савинов Александр Васильевич | K94: Бревдо Михаил Григорьевич | L94: 344013, Ростовская обл, г Ростов-на-Дону, ул Мечникова, 39в | M94: 25 | R94: 111629 | S94: 153322 | T94: 206223 | U94: 236156 | V94: 239543 | W94: 73261 | X94: 108114 | Y94: 107277 | Z94: 74562 | AA94: 97268 | AB94: 73261 | AC94: 45208 | AD94: 98415 | AE94: 161048 | AF94: 141729 | AG94: 0 | AH94: 0 | AI94: 0 | AJ94: 0 | AK94: 0 | AL94: 36964 | AM94: 67401 | AN94: 88468 | AO94: 26883 | AP94: 75396 | AQ94: 8454 | AR94: 2.15 | AS94: Низкий | AT94: dolgrostov.ru | AU94: image081 | AW94: ООО «ПКО «СП» зарегистрировано по адресу: 344013, Ростовская обл, г Ростов-на-Дону, ул Мечникова, 39в. Генеральным директором является Бревдо Михаил Григорьевич. Рост доходов компании за 5 лет: 214,6%. Объем заемных средств компании на конец 2024 года: 8454 тыс. руб. ФССП присвоил Низкий уровень риска для данного ПКО.
A95: 7730611414 | B95: 106 | C95: Общество с ограниченной ответственностью Профессиональная коллекторская организация «Долговые Инвестиции» | D95: 7730611414 | E95: 1097746346500 | F95: ООО ПКО «Долговые Инвестиции» | G95: 39975 | H95: 15 | I95: Нет | J95: Смирнов Алексей Васильевич | K95: Феклистов Павел Анатольевич | L95: 117420, Москва г, 15 | M95: 10 | R95: 129331 | S95: 96203 | T95: 74749 | U95: 142406 | V95: 236924 | W95: 40118 | X95: 144387 | Y95: 86541 | Z95: 82651 | AA95: 159419 | AB95: 40118 | AC95: -50368 | AD95: -12247 | AE95: 55003 | AF95: 67521 | AG95: 70 | AH95: 20000 | AI95: 29703 | AJ95: 69376 | AK95: 129544 | AL95: 113986 | AM95: 55496 | AN95: 39530 | AO95: 51019 | AP95: 62557 | AQ95: 0 | AR95: 1.83 | AS95: 0 | AT95: debt0invest.ru | AU95: image276 | AV95: 1850.63 | AW95: ООО ПКО «Долговые Инвестиции» зарегистрировано по адресу: 117420, Москва г, 15. Генеральным директором является Феклистов Павел Анатольевич. Рост доходов компании за 5 лет: 183,2%. Рост финансовых активов компании за 5 лет: 185062,86%.
A96: 5406972623 | B96: 119 | C96: Общество с ограниченной ответственностью профессиональная коллекторская организация «Центр профессионального взыскания» | D96: 5406972623 | E96: 1175476029739 | F96: ООО ПКО «Центр профессионального взыскания» | G96: 42814 | H96: 8 | I96: Нет | J96: Яковлева Елена Александровна | K96: Яковлева Елена Александровна | L96: 630007, Новосибирская обл, г Новосибирск, ул Коммунистическая, 35, 1 | M96: 10000 | R96: 8479 | S96: 51420 | T96: 59851 | U96: 109568 | V96: 235777 | W96: 4750 | X96: 44958 | Y96: 50200 | Z96: 74730 | AA96: 192014 | AB96: 4750 | AC96: 5155 | AD96: 7721 | AE96: 26401 | AF96: 31128 | AG96: 0 | AH96: 0 | AI96: 0 | AJ96: 0 | AK96: 0 | AL96: 15553 | AM96: 48089 | AN96: 40291 | AO96: 46079 | AP96: 34318 | AQ96: 294 | AR96: 27.81 | AS96: Низкий | AT96: zentrv.ru | AU96: image152 | AW96: ООО ПКО «Центр профессионального взыскания» зарегистрировано по адресу: 630007, Новосибирская обл, г Новосибирск, ул Коммунистическая, 35, 1. Генеральным директором является Яковлева Елена Александровна. Рост доходов компании за 5 лет: 2780,7%. Объем заемных средств компании на конец 2024 года: 294 тыс. руб. ФССП присвоил Низкий уровень риска для данного ПКО.
A97: 2310197022 | B97: 105 | C97: Общество с ограниченной ответственностью Профессиональная коллекторская организация «Служба защиты активов» | D97: 2310197022 | E97: 1162375059758 | F97: ООО ПКО «СЗА» | G97: 42720 | H97: 8 | I97: Да | J97: Соловьёв Павел Алексеевич | K97: Панфилов Константин Юрьевич | L97: 350000, Краснодарский край, г Краснодар, ул Коммунаров, Дом 76, офис 365/2 | M97: 10538.039 | R97: 60376 | S97: 5163 | T97: 7081 | U97: 143971 | V97: 217387 | W97: 1383 | X97: 164631 | Y97: 2522 | Z97: 40264 | AA97: 42517 | AB97: 1383 | AC97: -159645 | AD97: 4288 | AE97: 105200 | AF97: 110833 | AG97: 0 | AH97: 0 | AI97: 0 | AJ97: 97541 | AK97: 245812 | AL97: 181085 | AM97: 19366 | AN97: 58683 | AO97: 18668 | AP97: 60072 | AQ97: 155641 | AR97: 3.6 | AS97: 0 | AT97: szacollect.ru | AU97: image118 | AV97: 2.52 | AW97: ООО ПКО «СЗА» зарегистрировано по адресу: 350000, Краснодарский край, г Краснодар, ул Коммунаров, Дом 76, офис 365/2. Генеральным директором является Панфилов Константин Юрьевич. Рост доходов компании за 5 лет: 360,1%. Рост финансовых активов компании за 5 лет: 252,01%. Объем заемных средств компании на конец 2024 года: 155641 тыс. руб.
A98: 5446015412 | B98: 87 | C98: Общество с ограниченной ответственностью Профессиональная коллекторская организация «Региональное Бюро Взысканий» | D98: 5446015412 | E98: 1135483002214 | F98: ООО ПКО «РБВ» | G98: 41430 | H98: 11 | I98: Да | J98: Газецкий Владислав Валериевич, Решетин Андрей Валентинович | K98: Решетин Андрей Валентинович | L98: 633209, Новосибирская обл, г Искитим, ул Пушкина, 24 | M98: 10 | R98: 11889 | S98: 12971 | T98: 78398 | U98: 170126 | V98: 217377 | W98: 9008 | X98: 8396 | Y98: 69862 | Z98: 148476 | AA98: 179181 | AB98: 9008 | AC98: 3934 | AD98: 6441 | AE98: 16657 | AF98: 31204 | AG98: 0 | AH98: 0 | AI98: 0 | AJ98: 0 | AK98: 0 | AL98: 51552 | AM98: 69862 | AN98: 52222 | AO98: 38982 | AP98: 50415 | AQ98: 0 | AR98: 18.28 | AS98: Низкий | AT98: рбв54.рф | AU98: image191 | AW98: ООО ПКО «РБВ» зарегистрировано по адресу: 633209, Новосибирская обл, г Искитим, ул Пушкина, 24. Генеральным директором является Решетин Андрей Валентинович. Рост доходов компании за 5 лет: 1828,4%. ФССП присвоил Низкий уровень риска для данного ПКО.
A99: 6161090133 | B99: 71 | C99: Общество с ограниченной ответственностью профессиональная коллекторская организация «Премьер» | D99: 6161090133 | E99: 1196196052865 | F99: ООО ПКО «Премьер» | G99: 43822 | H99: 5 | I99: Нет | J99: Аминов Равиль Эдуардович | K99: Ткаченко Максим Сергеевич | L99: 344092, Ростовская обл, г. Ростов-На-Дону, пр-кт Королева, д. 7/19, офис 601 | M99: 10 | R99: 20 | S99: 10317 | T99: 56134 | U99: 203394 | V99: 215497 | W99: 6 | X99: 127 | Y99: 37 | Z99: 2199 | AA99: 218777 | AB99: 6 | AC99: 5059 | AD99: 44716 | AE99: 158892 | AF99: -70614 | AG99: 0 | AH99: 38713 | AI99: 54950 | AJ99: 212158 | AK99: 133546 | AL99: 12 | AM99: 405 | AN99: 370 | AO99: 967 | AP99: 2201 | AQ99: 1084 | AR99: 10774.85 | AS99: Низкий | AT99: prcll.ru | AU99: image346 | AV99: 3.45 | AW99: ООО ПКО «Премьер» зарегистрировано по адресу: 344092, Ростовская обл, г. Ростов-На-Дону, пр-кт Королева, д. 7/19, офис 601. Генеральным директором является Ткаченко Максим Сергеевич. Рост доходов компании за 5 лет: 1077485%. Рост финансовых активов компании за 5 лет: 344,96%. Объем заемных средств компании на конец 2024 года: 1084 тыс. руб. ФССП присвоил Низкий уровень риска для данного ПКО.
A100: 8602183821 | B100: 60 | C100: Общество с ограниченной ответственностью Профессиональная коллекторская организация «Экспресс-Кредит» | D100: 8602183821 | E100: 1118602006786 | F100: ООО ПКО «Экспресс-Кредит» | G100: 40764 | H100: 13 | I100: Нет | J100: Обухова Гульнара Зайнулловна, Верцинский Михаил Сергеевич | K100: Обухова Гульнара Зайнулловна | L100: 628404, Ханты-Мансийский автономный округ - Югра, г Сургут, ул Григория Кукуевицкого, д. 15, кв. 305 | M100: 250 | R100: 132032 | S100: 215673 | T100: 176240 | U100: 246614 | V100: 209764 | W100: 71904 | X100: 98504 | Y100: 45369 | Z100: 61376 | AA100: 99115 | AB100: 71904 | AC100: 108010 | AD100: 113373 | AE100: 162979 | AF100: 95444 | AG100: 250 | AH100: 154 | AI100: 58 | AJ100: 30 | AK100: 57 | AL100: 66616 | AM100: 39005 | AN100: 34191 | AO100: 60238 | AP100: 60238 | AQ100: 0 | AR100: 1.59 | AS100: Низкий | AT100: expresskd.ru | AU100: image097 | AV100: 0.23 | AW100: ООО ПКО «Экспресс-Кредит» зарегистрировано по адресу: 628404, Ханты-Мансийский автономный округ - Югра, г Сургут, ул Григория Кукуевицкого, д. 15, кв. 305. Генеральным директором является Обухова Гульнара Зайнулловна. Рост доходов компании за 5 лет: 158,9%. Рост финансовых активов компании за 5 лет: 22,8%. ФССП присвоил Низкий уровень риска для данного ПКО.
...

Sheet old_Расчет
A1: id | B1: name | C1: inn | D1: ogrn | E1: name_light | F1: date_register | G1: working_years | H1: napka | I1: founder | J1: director | K1: adress | L1: capital | M1: agent | N1: raiting_get_a | O1: cess | P1: raiting_get_c | Q1: income2020 | R1: income2021 | S1: income2022 | T1: income2023 | U1: income2024 | V1: cost2020 | W1: cost2021 | X1: cost2022 | Y1: cost2023 | Z1: cost2024 | AA1: profit2020 | AB1: profit2021 | AC1: profit2022 | AD1: profit2023 | AE1: profit2024 | AF1: invest2020 | AG1: invest2021 | AH1: invest2022 | AI1: invest2023 | AJ1: invest2024 | AK1: receivable2020 | AL1: receivable2021 | AM1: receivable2022 | AN1: receivable2023 | AO1: receivable2024 | AP1: loan | AQ1: grow_income_2019_2023 | AR1: risk_fssp | AS1: site | AT1: logo | AU1: temp_grow_2019_2023 | AV1: description | AY1: 45769
A2: 0 | B2: Непубличное акционерное общество Профессиональная коллекторская организация «Первое клиентское бюро» | C2: 2723115222 | D2: 1092723000446 | E2: НАО ПКО «ПКБ» | F2: 39847 | G2: =ROUNDDOWN(($AY$1-F2)/365,0) -> 16 | H2: Да | I2: =IF(VLOOKUP(C2,гендир!$A$3:$C$3000,3,0)=0,"",VLOOKUP(C2,гендир!$A$3:$C$3000,3,0)) | J2: =IF(VLOOKUP(C2,гендир!$A$3:$C$3000,2,0)=0,"",VLOOKUP(C2,гендир!$A$3:$C$3000,2,0)) -> Клековкин Николай Игоревич | K2: Москва г, км Киевское шоссе 22-й (п Московский), 6, 1 | L2: 194.3 | P2: 1 | Q2: 9519863 | R2: 7778417 | S2: 9298765 | T2: 12765053 | U2: 17486370 | V2: 4961407 | W2: 1886740 | X2: 2913013 | Y2: 3028498 | Z2: 7354522 | AA2: 4961407 | AB2: 3327903 | AC2: 3667985 | AD2: 6746377 | AE2: 7017168 | AF2: 7094613 | AG2: 11961665 | AH2: 13692288 | AI2: 23483962 | AJ2: 21143934 | AK2: 410024 | AL2: 679296 | AM2: 874521 | AN2: 589736 | AO2: 522393 | AP2: 12919181 | AQ2: 1.83683 | AR2: Низкий | AS2: pkbonline.ru | AT2: =IF(VLOOKUP(C2,old!$D$3:$AU$549,44,0)=0,"",VLOOKUP(C2,old!$D$3:$AU$549,44,0)) -> image060 | AU2: 2.9802801 | AV2: =E2&" зарегистрировано по адресу: "&K2&IF(J2=0,"",IF(J2="","",". Генеральным директором является "&J2&IF(AQ2=0,".",IF(AQ2="",".",". Рост доходов компании за 5 лет: "&ROUND(AQ2*100,2)&"%."))&IF(AU2=0,"",IF(AU2="",""," Рост финансовых активов компании за 5 лет: "&IFERROR(ROUND(AU2*100,2),"")&"%."))&IF(AP2=0,"",IF(AP2="",""," Объем заемных средств компании на конец 2024 года: "&AP2&" тыс. руб."))&IF(AR2=0,"",IF(AR2="",""," ФССП присвоил "&AR2&" уровень риска для данного ПКО.")))) -> НАО ПКО «ПКБ» зарегистрировано по адресу: Москва г, км Киевское шоссе 22-й (п Московский), 6, 1. Генеральным директором является Клековкин Николай Игоревич. Рост доходов компании за 5 лет: 183,68%. Рост финансовых активов компании за 5 лет: 298,03%. Объем заемных средств компании на конец 2024 года: 12919181 тыс. руб. ФССП присвоил Низкий уровень риска для данного ПКО.
A3: 1 | B3: Общество с ограниченной ответственностью Профессиональная коллекторская организация «Феникс» | C3: 7713793524 | D3: 1147746920144 | E3: ООО ПКО «Феникс» | F3: 41863 | G3: =ROUNDDOWN(($AY$1-F3)/365,0) -> 10 | H3: Нет | I3: =IF(VLOOKUP(C3,гендир!$A$3:$C$3000,3,0)=0,"",VLOOKUP(C3,гендир!$A$3:$C$3000,3,0)) -> Акционерное Общество, "ТБАНК", Международная Компания Публичное Акционерное Общество, "Т-ТЕХНОЛОГИИ" | J3: =IF(VLOOKUP(C3,гендир!$A$3:$C$3000,2,0)=0,"",VLOOKUP(C3,гендир!$A$3:$C$3000,2,0)) -> Феклисов Иван Владимирович | K3: 127287, Москва г, Хуторская 2-Я ул, дом 38А, строение 26 | L3: 33250 | P3: 2 | Q3: 7746710 | R3: 9815218 | S3: 10699598 | T3: 12291051 | U3: 12835953 | V3: 2407105 | W3: 3230796 | X3: 3606574 | Y3: 2415999 | Z3: 1895600 | AA3: 2407105 | AB3: 5237831 | AC3: 5366147 | AD3: 7366870 | AE3: 8229971 | AF3: 9528726 | AG3: 8257159 | AH3: 11084910 | AI3: 11562703 | AJ3: 21154197 | AK3: 249470 | AL3: 63808 | AM3: 68805 | AN3: 61492 | AO3: 276242 | AP3: 2378544 | AQ3: =IFERROR(ROUND(IFERROR(U3/Q3,IFERROR(U3/R3,IFERROR(U3/S3,IFERROR(U3/T3,"")))),3),"") -> 1.657 | AR3: Высокий | AS3: phoenix0ca.ru | AT3: =IF(VLOOKUP(C3,old!$D$3:$AU$549,44,0)=0,"",VLOOKUP(C3,old!$D$3:$AU$549,44,0)) -> image002 | AU3: 2.2200446 | AV3: =E3&" зарегистрировано по адресу: "&K3&IF(J3=0,"",IF(J3="","",". Генеральным директором является "&J3&IF(AQ3=0,".",IF(AQ3="",".",". Рост доходов компании за 5 лет: "&ROUND(AQ3*100,2)&"%."))&IF(AU3=0,"",IF(AU3="",""," Рост финансовых активов компании за 5 лет: "&IFERROR(ROUND(AU3*100,2),"")&"%."))&IF(AP3=0,"",IF(AP3="",""," Объем заемных средств компании на конец 2024 года: "&AP3&" тыс. руб."))&IF(AR3=0,"",IF(AR3="",""," ФССП присвоил "&AR3&" уровень риска для данного ПКО.")))) -> ООО ПКО «Феникс» зарегистрировано по адресу: 127287, Москва г, Хуторская 2-Я ул, дом 38А, строение 26. Генеральным директором является Феклисов Иван Владимирович. Рост доходов компании за 5 лет: 165,7%. Рост финансовых активов компании за 5 лет: 222%. Объем заемных средств компании на конец 2024 года: 2378544 тыс. руб. ФССП присвоил Высокий уровень риска для данного ПКО.
A4: 4 | B4: Общество с ограниченной ответственностью профессиональная коллекторская организация «АйДи Коллект» | C4: 7730233723 | D4: 1177746355225 | E4: ООО ПКО «АйДи Коллект» | F4: 42832 | G4: =ROUNDDOWN(($AY$1-F4)/365,0) -> 8 | H4: Да | I4: =IF(VLOOKUP(C4,гендир!$A$3:$C$3000,3,0)=0,"",VLOOKUP(C4,гендир!$A$3:$C$3000,3,0)) -> Васильев Александр Александрович, Общество С Ограниченной Ответственностью, "ОНЛАЙН МИКРОФИНАНС", Общество С Ограниченной Ответственностью, "ФИНТЕХ ГРУПП" | J4: =IF(VLOOKUP(C4,гендир!$A$3:$C$3000,2,0)=0,"",VLOOKUP(C4,гендир!$A$3:$C$3000,2,0)) -> Васильев Александр Александрович | K4: 121096, Москва г, ул. Василисы Кожиной, дом 1, офис Д13 | L4: 101265.82 | P4: 3 | Q4: 694023 | R4: 2342953 | S4: 4647772 | T4: 8331391 | U4: 12362455 | V4: 247799 | W4: 530090 | X4: 1630652 | Y4: 2436827 | Z4: 4073731 | AA4: 247799 | AB4: 1119448 | AC4: 1329942 | AD4: 2975359 | AE4: 3863869 | AF4: 970210 | AG4: 4311265 | AH4: 7794949 | AI4: 13782767 | AJ4: 16179682 | AK4: 20331 | AL4: 31369 | AM4: 466385 | AN4: 289827 | AO4: 114237 | AP4: 13646924 | AQ4: =IFERROR(ROUND(IFERROR(U4/Q4,IFERROR(U4/R4,IFERROR(U4/S4,IFERROR(U4/T4,"")))),3),"") -> 17.813 | AR4: Низкий | AS4: idcollect.ru | AT4: =IF(VLOOKUP(C4,old!$D$3:$AU$549,44,0)=0,"",VLOOKUP(C4,old!$D$3:$AU$549,44,0)) -> image043 | AU4: 16.676474 | AV4: =E4&" зарегистрировано по адресу: "&K4&IF(J4=0,"",IF(J4="","",". Генеральным директором является "&J4&IF(AQ4=0,".",IF(AQ4="",".",". Рост доходов компании за 5 лет: "&ROUND(AQ4*100,2)&"%."))&IF(AU4=0,"",IF(AU4="",""," Рост финансовых активов компании за 5 лет: "&IFERROR(ROUND(AU4*100,2),"")&"%."))&IF(AP4=0,"",IF(AP4="",""," Объем заемных средств компании на конец 2024 года: "&AP4&" тыс. руб."))&IF(AR4=0,"",IF(AR4="",""," ФССП присвоил "&AR4&" уровень риска для данного ПКО.")))) -> ООО ПКО «АйДи Коллект» зарегистрировано по адресу: 121096, Москва г, ул. Василисы Кожиной, дом 1, офис Д13. Генеральным директором является Васильев Александр Александрович. Рост доходов компании за 5 лет: 1781,3%. Рост финансовых активов компании за 5 лет: 1667,65%. Объем заемных средств компании на конец 2024 года: 13646924 тыс. руб. ФССП присвоил Низкий уровень риска для данного ПКО.
A5: 2 | B5: Общество с ограниченной ответственностью Профессиональная коллекторская организация «ЭОС» | C5: 7714704125 | D5: 1077758117117 | E5: ООО ПКО «ЭОС» | F5: 39282 | G5: =ROUNDDOWN(($AY$1-F5)/365,0) -> 17 | H5: Да | I5: =IF(VLOOKUP(C5,гендир!$A$3:$C$3000,3,0)=0,"",VLOOKUP(C5,гендир!$A$3:$C$3000,3,0)) -> Завьялова Елена Михайловна, Компания С Ограниченной Ответственностью Эос Холдинг Гмбх, Компания С Ограниченной Ответственностью Эос Интернациональ Бетайлигунгс-фервальтунгсгезелльшафт Мбх | J5: =IF(VLOOKUP(C5,гендир!$A$3:$C$3000,2,0)=0,"",VLOOKUP(C5,гендир!$A$3:$C$3000,2,0)) -> Дмитраков Антон Александрович | K5: 117105, Москва г, вн.тер. г. муниципальный округ Нагорный, ш Варшавское, д. 26, этаж 2, ч. нежил. помещ. 8 | L5: 6450 | P5: 4 | Q5: 6360674 | R5: 9143168 | S5: 10606574 | T5: 11043025 | U5: 9784245 | V5: 1778110 | W5: 2163516 | X5: 4978419 | Y5: 3027672 | Z5: 3020218 | AA5: 1778110 | AB5: 4582547 | AC5: 2928525 | AD5: 5120363 | AE5: 4762878 | AF5: 5308242 | AG5: 9409339 | AH5: 11291057 | AI5: 12229815 | AJ5: 11134188 | AK5: 76857 | AL5: 143059 | AM5: 80269 | AN5: 335476 | AO5: 169474 | AP5: 5081951 | AQ5: =IFERROR(ROUND(IFERROR(U5/Q5,IFERROR(U5/R5,IFERROR(U5/S5,IFERROR(U5/T5,"")))),3),"") -> 1.538 | AR5: Низкий | AS5: oooeos.ru | AT5: =IF(VLOOKUP(C5,old!$D$3:$AU$549,44,0)=0,"",VLOOKUP(C5,old!$D$3:$AU$549,44,0)) -> image017 | AU5: 2.0975283 | AV5: =E5&" зарегистрировано по адресу: "&K5&IF(J5=0,"",IF(J5="","",". Генеральным директором является "&J5&IF(AQ5=0,".",IF(AQ5="",".",". Рост доходов компании за 5 лет: "&ROUND(AQ5*100,2)&"%."))&IF(AU5=0,"",IF(AU5="",""," Рост финансовых активов компании за 5 лет: "&IFERROR(ROUND(AU5*100,2),"")&"%."))&IF(AP5=0,"",IF(AP5="",""," Объем заемных средств компании на конец 2024 года: "&AP5&" тыс. руб."))&IF(AR5=0,"",IF(AR5="",""," ФССП присвоил "&AR5&" уровень риска для данного ПКО.")))) -> ООО ПКО «ЭОС» зарегистрировано по адресу: 117105, Москва г, вн.тер. г. муниципальный округ Нагорный, ш Варшавское, д. 26, этаж 2, ч. нежил. помещ. 8. Генеральным директором является Дмитраков Антон Александрович. Рост доходов компании за 5 лет: 153,8%. Рост финансовых активов компании за 5 лет: 209,75%. Объем заемных средств компании на конец 2024 года: 5081951 тыс. руб. ФССП присвоил Низкий уровень риска для данного ПКО.
A6: 3 | B6: Общество с ограниченной ответственностью «Профессиональная коллекторская организация «Национальная Фабрика Ипотеки» | C6: 7706450420 | D6: 1177746942020 | E6: ООО «ПКО «Национальная Фабрика Ипотеки» | F6: 42984 | G6: =ROUNDDOWN(($AY$1-F6)/365,0) -> 7 | H6: Нет | I6: =IF(VLOOKUP(C6,гендир!$A$3:$C$3000,3,0)=0,"",VLOOKUP(C6,гендир!$A$3:$C$3000,3,0)) -> "МОСКОВСКИЙ КРЕДИТНЫЙ БАНК", (публичное Акционерное Общество) | J6: =IF(VLOOKUP(C6,гендир!$A$3:$C$3000,2,0)=0,"",VLOOKUP(C6,гендир!$A$3:$C$3000,2,0)) -> Исеев Руслан Маратович | K6: 107140, Москва г, ул Красносельская Верхн., 11А, 1, 2/2/45 | L6: 315000 | P6: 5 | Q6: 8878559 | R6: 12637330 | S6: 12562020 | T6: 8536698 | U6: 8753853 | V6: 7464337 | W6: 11095638 | X6: 10423574 | Y6: 6517008 | Z6: 6476527 | AA6: 7464337 | AB6: 230250 | AC6: 151795 | AD6: 137313 | AE6: -776176 | AF6: 6273480 | AG6: 8206211 | AH6: 10015293 | AI6: 12684814 | AJ6: 13806928 | AK6: 164797 | AL6: 187427 | AM6: 322258 | AN6: 439587 | AO6: 563914 | AP6: 14942793 | AQ6: =IFERROR(ROUND(IFERROR(U6/Q6,IFERROR(U6/R6,IFERROR(U6/S6,IFERROR(U6/T6,"")))),3),"") -> 0.986 | AR6: Низкий | AS6: ipoteka24.ru | AT6: =IF(VLOOKUP(C6,old!$D$3:$AU$549,44,0)=0,"",VLOOKUP(C6,old!$D$3:$AU$549,44,0)) -> image142 | AU6: 2.2008404 | AV6: =E6&" зарегистрировано по адресу: "&K6&IF(J6=0,"",IF(J6="","",". Генеральным директором является "&J6&IF(AQ6=0,".",IF(AQ6="",".",". Рост доходов компании за 5 лет: "&ROUND(AQ6*100,2)&"%."))&IF(AU6=0,"",IF(AU6="",""," Рост финансовых активов компании за 5 лет: "&IFERROR(ROUND(AU6*100,2),"")&"%."))&IF(AP6=0,"",IF(AP6="",""," Объем заемных средств компании на конец 2024 года: "&AP6&" тыс. руб."))&IF(AR6=0,"",IF(AR6="",""," ФССП присвоил "&AR6&" уровень риска для данного ПКО.")))) -> ООО «ПКО «Национальная Фабрика Ипотеки» зарегистрировано по адресу: 107140, Москва г, ул Красносельская Верхн., 11А, 1, 2/2/45. Генеральным директором является Исеев Руслан Маратович. Рост доходов компании за 5 лет: 98,6%. Рост финансовых активов компании за 5 лет: 220,08%. Объем заемных средств компании на конец 2024 года: 14942793 тыс. руб. ФССП присвоил Низкий уровень риска для данного ПКО.
A7: 8 | B7: Общество с ограниченной ответственностью Профессиональная коллекторская организация «Право онлайн» | C7: 5407973997 | D7: 1195476020343 | E7: ООО ПКО «Право онлайн» | F7: 43538 | G7: =ROUNDDOWN(($AY$1-F7)/365,0) -> 6 | H7: Нет | I7: =IF(VLOOKUP(C7,гендир!$A$3:$C$3000,3,0)=0,"",VLOOKUP(C7,гендир!$A$3:$C$3000,3,0)) -> Волков Павел Александрович, Кравцова Наталья Николаевна, Евстифеева Юлия Евгеньевна, Кобяков Владислав Юрьевич, Елисеев Алексей Андреевич, Трахачёв Сергей Валерьевич | J7: =IF(VLOOKUP(C7,гендир!$A$3:$C$3000,2,0)=0,"",VLOOKUP(C7,гендир!$A$3:$C$3000,2,0)) -> Телятникова Елена Васильевна | K7: 630005, Новосибирская область, Новосибирск, Фрунзе, д. 88, этаж 2, офис 21 | L7: 62.035 | P7: 6 | Q7: 215252 | R7: 1025945 | S7: 2361430 | T7: 4627147 | U7: 7129755 | V7: 49016 | W7: 637310 | X7: 1438435 | Y7: 2640709 | Z7: 4214695 | AA7: 49016 | AB7: 296990 | AC7: 684861 | AD7: 1273402 | AE7: 1879565 | AF7: 0 | AG7: 962059 | AH7: 2260288 | AI7: 3547923 | AJ7: 5850603 | AK7: 305122 | AL7: 116045 | AM7: 121243 | AN7: 273368 | AO7: 104605 | AP7: 4008607 | AQ7: =IFERROR(ROUND(IFERROR(U7/Q7,IFERROR(U7/R7,IFERROR(U7/S7,IFERROR(U7/T7,"")))),3),"") -> 33.123 | AR7: Низкий | AS7: pvonline.ru | AT7: =IF(VLOOKUP(C7,old!$D$3:$AU$549,44,0)=0,"",VLOOKUP(C7,old!$D$3:$AU$549,44,0)) -> image057 | AU7: 6.0813349 | AV7: =E7&" зарегистрировано по адресу: "&K7&IF(J7=0,"",IF(J7="","",". Генеральным директором является "&J7&IF(AQ7=0,".",IF(AQ7="",".",". Рост доходов компании за 5 лет: "&ROUND(AQ7*100,2)&"%."))&IF(AU7=0,"",IF(AU7="",""," Рост финансовых активов компании за 5 лет: "&IFERROR(ROUND(AU7*100,2),"")&"%."))&IF(AP7=0,"",IF(AP7="",""," Объем заемных средств компании на конец 2024 года: "&AP7&" тыс. руб."))&IF(AR7=0,"",IF(AR7="",""," ФССП присвоил "&AR7&" уровень риска для данного ПКО.")))) -> ООО ПКО «Право онлайн» зарегистрировано по адресу: 630005, Новосибирская область, Новосибирск, Фрунзе, д. 88, этаж 2, офис 21. Генеральным директором является Телятникова Елена Васильевна. Рост доходов компании за 5 лет: 3312,3%. Рост финансовых активов компании за 5 лет: 608,13%. Объем заемных средств компании на конец 2024 года: 4008607 тыс. руб. ФССП присвоил Низкий уровень риска для данного ПКО.
A8: 7 | B8: Общество с ограниченной ответственностью Профессиональная коллекторская организация «Филберт» | C8: 7841430420 | D8: 1107847250961 | E8: ООО ПКО «Филберт» | F8: 40394 | G8: =ROUNDDOWN(($AY$1-F8)/365,0) -> 14 | H8: Да | I8: =IF(VLOOKUP(C8,гендир!$A$3:$C$3000,3,0)=0,"",VLOOKUP(C8,гендир!$A$3:$C$3000,3,0)) | J8: =IF(VLOOKUP(C8,гендир!$A$3:$C$3000,2,0)=0,"",VLOOKUP(C8,гендир!$A$3:$C$3000,2,0)) -> Иванов Андрей Борисович | K8: 198095, Санкт-Петербург г, Маршала Говорова ул, дом № 35, корпус 5, лит. Ж | L8: 10 | P8: 7 | Q8: 1770329 | R8: 4335154 | S8: 3848709 | T8: 4799034 | U8: 6148318 | V8: 348390 | W8: 1949395 | X8: 621948 | Y8: 874797 | Z8: 1394961 | AA8: 348390 | AB8: 1315749 | AC8: 1802945 | AD8: 2218456 | AE8: 2568638 | AF8: 2620651 | AG8: 3839953 | AH8: 4999692 | AI8: 7168661 | AJ8: 9102226 | AK8: 50639 | AL8: 113684 | AM8: 55850 | AN8: 173771 | AO8: 69730 | AP8: 2536194 | AQ8: =IFERROR(ROUND(IFERROR(U8/Q8,IFERROR(U8/R8,IFERROR(U8/S8,IFERROR(U8/T8,"")))),3),"") -> 3.473 | AR8: Значительный | AS8: filbert.su; Filbert.pro | AT8: =IF(VLOOKUP(C8,old!$D$3:$AU$549,44,0)=0,"",VLOOKUP(C8,old!$D$3:$AU$549,44,0)) -> image004 | AU8: 3.473269 | AV8: =E8&" зарегистрировано по адресу: "&K8&IF(J8=0,"",IF(J8="","",". Генеральным директором является "&J8&IF(AQ8=0,".",IF(AQ8="",".",". Рост доходов компании за 5 лет: "&ROUND(AQ8*100,2)&"%."))&IF(AU8=0,"",IF(AU8="",""," Рост финансовых активов компании за 5 лет: "&IFERROR(ROUND(AU8*100,2),"")&"%."))&IF(AP8=0,"",IF(AP8="",""," Объем заемных средств компании на конец 2024 года: "&AP8&" тыс. руб."))&IF(AR8=0,"",IF(AR8="",""," ФССП присвоил "&AR8&" уровень риска для данного ПКО.")))) -> ООО ПКО «Филберт» зарегистрировано по адресу: 198095, Санкт-Петербург г, Маршала Говорова ул, дом № 35, корпус 5, лит. Ж. Генеральным директором является Иванов Андрей Борисович. Рост доходов компании за 5 лет: 347,3%. Рост финансовых активов компании за 5 лет: 347,33%. Объем заемных средств компании на конец 2024 года: 2536194 тыс. руб. ФССП присвоил Значительный уровень риска для данного ПКО.
A9: 6 | B9: Общество с ограниченной ответственностью Профессиональная коллекторская организация «Региональная Служба Взыскания» | C9: 7707782563 | D9: 1127746618768 | E9: ООО ПКО «РСВ» | F9: 41131 | G9: =ROUNDDOWN(($AY$1-F9)/365,0) -> 12 | H9: Да | I9: =IF(VLOOKUP(C9,гендир!$A$3:$C$3000,3,0)=0,"",VLOOKUP(C9,гендир!$A$3:$C$3000,3,0)) -> Общество С Ограниченной Ответственностью Профессиональная Коллекторская Организация, "СТОЛИЧНАЯ СЕРВИСНАЯ КОМПАНИЯ", Свеа Экономи Сайпрус Лимитед | J9: =IF(VLOOKUP(C9,гендир!$A$3:$C$3000,2,0)=0,"",VLOOKUP(C9,гендир!$A$3:$C$3000,2,0)) -> Медведева Ольга Владимировна | K9: 127055, Москва, Бутырский Вал, дом № 68/70, стр. 1, этаж 2, помещение I, комната №4 | L9: 10 | P9: 8 | Q9: 1034499 | R9: 3183461 | S9: 6096482 | T9: 5276121 | U9: 5864105 | V9: 450337 | W9: 674239 | X9: 2086771 | Y9: 1622048 | Z9: 2473779 | AA9: 450337 | AB9: 1489776 | AC9: 2273861 | AD9: 2145981 | AE9: 3204091 | AF9: 1192462 | AG9: 4460750 | AH9: 4571756 | AI9: 4530378 | AJ9: 4794166 | AK9: 42936 | AL9: 204656 | AM9: 303021 | AN9: 569379 | AO9: 770038 | AP9: 3181681 | AQ9: =IFERROR(ROUND(IFERROR(U9/Q9,IFERROR(U9/R9,IFERROR(U9/S9,IFERROR(U9/T9,"")))),3),"") -> 5.669 | AR9: Высокий | AS9: rsvcollection.ru | AT9: =IF(VLOOKUP(C9,old!$D$3:$AU$549,44,0)=0,"",VLOOKUP(C9,old!$D$3:$AU$549,44,0)) -> image020 | AU9: 4.0203931 | AV9: =E9&" зарегистрировано по адресу: "&K9&IF(J9=0,"",IF(J9="","",". Генеральным директором является "&J9&IF(AQ9=0,".",IF(AQ9="",".",". Рост доходов компании за 5 лет: "&ROUND(AQ9*100,2)&"%."))&IF(AU9=0,"",IF(AU9="",""," Рост финансовых активов компании за 5 лет: "&IFERROR(ROUND(AU9*100,2),"")&"%."))&IF(AP9=0,"",IF(AP9="",""," Объем заемных средств компании на конец 2024 года: "&AP9&" тыс. руб."))&IF(AR9=0,"",IF(AR9="",""," ФССП присвоил "&AR9&" уровень риска для данного ПКО.")))) -> ООО ПКО «РСВ» зарегистрировано по адресу: 127055, Москва, Бутырский Вал, дом № 68/70, стр. 1, этаж 2, помещение I, комната №4. Генеральным директором является Медведева Ольга Владимировна. Рост доходов компании за 5 лет: 566,9%. Рост финансовых активов компании за 5 лет: 402,04%. Объем заемных средств компании на конец 2024 года: 3181681 тыс. руб. ФССП присвоил Высокий уровень риска для данного ПКО.
A10: 9 | B10: Акционерное общество Профессиональная коллекторская организация «Центр Долгового Управления» | C10: 7730592401 | D10: 5087746390353 | E10: АО ПКО «ЦДУ» | F10: 39763 | G10: =ROUNDDOWN(($AY$1-F10)/365,0) -> 16 | H10: Нет | I10: =IF(VLOOKUP(C10,гендир!$A$3:$C$3000,3,0)=0,"",VLOOKUP(C10,гендир!$A$3:$C$3000,3,0)) | J10: =IF(VLOOKUP(C10,гендир!$A$3:$C$3000,2,0)=0,"",VLOOKUP(C10,гендир!$A$3:$C$3000,2,0)) -> Ямпольская Елена Александровна | K10: 117420, Москва г, ул Намёткина, 15, Эт 1 Пом I Ком 01-06 | L10: 3000 | P10: 9 | Q10: 662863 | R10: 1518917 | S10: 2355062 | T10: 3768972 | U10: 4706406 | V10: 187289 | W10: 590555 | X10: 1392888 | Y10: 1955803 | Z10: 3014575 | AA10: 187289 | AB10: 774816 | AC10: 770441 | AD10: 1453064 | AE10: 1384779 | AF10: 260194 | AG10: 728282 | AH10: 1362348 | AI10: 2486555 | AJ10: 3311833 | AK10: 18583 | AL10: 66897 | AM10: 33544 | AN10: 65828 | AO10: 60950 | AP10: 0 | AQ10: =IFERROR(ROUND(IFERROR(U10/Q10,IFERROR(U10/R10,IFERROR(U10/S10,IFERROR(U10/T10,"")))),3),"") -> 7.1 | AR10: Низкий | AS10: gkcdu.ru | AT10: =IF(VLOOKUP(C10,old!$D$3:$AU$549,44,0)=0,"",VLOOKUP(C10,old!$D$3:$AU$549,44,0)) -> image031 | AU10: 12.728322 | AV10: =E10&" зарегистрировано по адресу: "&K10&IF(J10=0,"",IF(J10="","",". Генеральным директором является "&J10&IF(AQ10=0,".",IF(AQ10="",".",". Рост доходов компании за 5 лет: "&ROUND(AQ10*100,2)&"%."))&IF(AU10=0,"",IF(AU10="",""," Рост финансовых активов компании за 5 лет: "&IFERROR(ROUND(AU10*100,2),"")&"%."))&IF(AP10=0,"",IF(AP10="",""," Объем заемных средств компании на конец 2024 года: "&AP10&" тыс. руб."))&IF(AR10=0,"",IF(AR10="",""," ФССП присвоил "&AR10&" уровень риска для данного ПКО.")))) -> АО ПКО «ЦДУ» зарегистрировано по адресу: 117420, Москва г, ул Намёткина, 15, Эт 1 Пом I Ком 01-06. Генеральным директором является Ямпольская Елена Александровна. Рост доходов компании за 5 лет: 710%. Рост финансовых активов компании за 5 лет: 1272,83%. ФССП присвоил Низкий уровень риска для данного ПКО.
A11: 10 | B11: Общество с ограниченной ответственностью Профессиональная коллекторская организация Траст» | C11: 3801084488 | D11: 1063801051203 | E11: ООО «ПКО Траст» | F11: 38945 | G11: =ROUNDDOWN(($AY$1-F11)/365,0) -> 18 | H11: Да | I11: =IF(VLOOKUP(C11,гендир!$A$3:$C$3000,3,0)=0,"",VLOOKUP(C11,гендир!$A$3:$C$3000,3,0)) -> Долюк Андрей Николаевич, Самбудагва Ксения Павловна | J11: =IF(VLOOKUP(C11,гендир!$A$3:$C$3000,2,0)=0,"",VLOOKUP(C11,гендир!$A$3:$C$3000,2,0)) -> Долюк Андрей Николаевич | K11: 665801, Иркутская обл, г.о. Ангарское, г Ангарск, кв-л 252, стр. 19, д.офис 202 | L11: 20 | P11: 10 | Q11: 1314917 | R11: 2158767 | S11: 2677762 | T11: 3241552 | U11: 3666014 | V11: 200114 | W11: 397768 | X11: 650661 | Y11: 1199595 | Z11: 1582938 | AA11: 200114 | AB11: 1060974 | AC11: 1244435 | AD11: 1194514 | AE11: 1296597 | AF11: 1544620 | AG11: 2163179 | AH11: 2962323 | AI11: 4648416 | AJ11: 5416881 | AK11: 58178 | AL11: 60606 | AM11: 80407 | AN11: 252788 | AO11: 177879 | AP11: 463656 | AQ11: =IFERROR(ROUND(IFERROR(U11/Q11,IFERROR(U11/R11,IFERROR(U11/S11,IFERROR(U11/T11,"")))),3),"") -> 2.788 | AR11: Низкий | AS11: catrust.ru | AT11: =IF(VLOOKUP(C11,old!$D$3:$AU$549,44,0)=0,"",VLOOKUP(C11,old!$D$3:$AU$549,44,0)) -> image019 | AU11: 3.5069344 | AV11: =E11&" зарегистрировано по адресу: "&K11&IF(J11=0,"",IF(J11="","",". Генеральным директором является "&J11&IF(AQ11=0,".",IF(AQ11="",".",". Рост доходов компании за 5 лет: "&ROUND(AQ11*100,2)&"%."))&IF(AU11=0,"",IF(AU11="",""," Рост финансовых активов компании за 5 лет: "&IFERROR(ROUND(AU11*100,2),"")&"%."))&IF(AP11=0,"",IF(AP11="",""," Объем заемных средств компании на конец 2024 года: "&AP11&" тыс. руб."))&IF(AR11=0,"",IF(AR11="",""," ФССП присвоил "&AR11&" уровень риска для данного ПКО.")))) -> ООО «ПКО Траст» зарегистрировано по адресу: 665801, Иркутская обл, г.о. Ангарское, г Ангарск, кв-л 252, стр. 19, д.офис 202. Генеральным директором является Долюк Андрей Николаевич. Рост доходов компании за 5 лет: 278,8%. Рост финансовых активов компании за 5 лет: 350,69%. Объем заемных средств компании на конец 2024 года: 463656 тыс. руб. ФССП присвоил Низкий уровень риска для данного ПКО.
A12: 14 | B12: Общество с ограниченной ответственностью профессиональная коллекторская организация «ДОЛГОВОЕ АГЕНТСТВО «ФЕМИДА» | C12: 7805646537 | D12: 1147847101577 | E12: ООО ПКО «ДА «ФЕМИДА» | F12: 41719 | G12: =ROUNDDOWN(($AY$1-F12)/365,0) -> 11 | H12: Нет | I12: =IF(VLOOKUP(C12,гендир!$A$3:$C$3000,3,0)=0,"",VLOOKUP(C12,гендир!$A$3:$C$3000,3,0)) -> Общество С Ограниченной Ответственностью, "ДЗП-РАЗВИТИЕ" | J12: =IF(VLOOKUP(C12,гендир!$A$3:$C$3000,2,0)=0,"",VLOOKUP(C12,гендир!$A$3:$C$3000,2,0)) -> Карташова Ольга Владимировна | K12: 197374, Город Санкт-Петербург, ул. Мебельная, дом 12, корпус 1, литер А, помещение 55-Н, офис 420 | L12: 10 | P12: 11 | Q12: 133082 | R12: 154344 | S12: 474695 | T12: 2104307 | U12: 3049049 | V12: 175483 | W12: 57865 | X12: 92399 | Y12: 840418 | Z12: 1267589 | AA12: 175483 | AB12: 3147 | AC12: 35182 | AD12: 520556 | AE12: 835826 | AF12: 206760 | AG12: 426247 | AH12: 910217 | AI12: 1578595 | AJ12: 1713500 | AK12: 37055 | AL12: 33373 | AM12: 7705 | AN12: 56903 | AO12: 85223 | AP12: 137577 | AQ12: =IFERROR(ROUND(IFERROR(U12/Q12,IFERROR(U12/R12,IFERROR(U12/S12,IFERROR(U12/T12,"")))),3),"") -> 22.911 | AR12: Низкий | AS12: dafemida.ru | AT12: =IF(VLOOKUP(C12,old!$D$3:$AU$549,44,0)=0,"",VLOOKUP(C12,old!$D$3:$AU$549,44,0)) -> image175 | AU12: 8.2873863 | AV12: =E12&" зарегистрировано по адресу: "&K12&IF(J12=0,"",IF(J12="","",". Генеральным директором является "&J12&IF(AQ12=0,".",IF(AQ12="",".",". Рост доходов компании за 5 лет: "&ROUND(AQ12*100,2)&"%."))&IF(AU12=0,"",IF(AU12="",""," Рост финансовых активов компании за 5 лет: "&IFERROR(ROUND(AU12*100,2),"")&"%."))&IF(AP12=0,"",IF(AP12="",""," Объем заемных средств компании на конец 2024 года: "&AP12&" тыс. руб."))&IF(AR12=0,"",IF(AR12="",""," ФССП присвоил "&AR12&" уровень риска для данного ПКО.")))) -> ООО ПКО «ДА «ФЕМИДА» зарегистрировано по адресу: 197374, Город Санкт-Петербург, ул. Мебельная, дом 12, корпус 1, литер А, помещение 55-Н, офис 420. Генеральным директором является Карташова Ольга Владимировна. Рост доходов компании за 5 лет: 2291,1%. Рост финансовых активов компании за 5 лет: 828,74%. Объем заемных средств компании на конец 2024 года: 137577 тыс. руб. ФССП присвоил Низкий уровень риска для данного ПКО.
A13: 13 | B13: Общество с ограниченной ответственностью «Профессиональная коллекторская организация «М.Б.А. Финансы» | C13: 7726626680 | D13: 1097746177693 | E13: ООО «ПКО «М.Б.А. Финансы» | F13: 39903 | G13: =ROUNDDOWN(($AY$1-F13)/365,0) -> 16 | H13: Да | I13: =IF(VLOOKUP(C13,гендир!$A$3:$C$3000,3,0)=0,"",VLOOKUP(C13,гендир!$A$3:$C$3000,3,0)) -> Товарищество С Ограниченной Ответственностью, "КОЛЛЕКТОРСКОЕ АГЕНТСТВО ", М.б.а. Финансы" | J13: =IF(VLOOKUP(C13,гендир!$A$3:$C$3000,2,0)=0,"",VLOOKUP(C13,гендир!$A$3:$C$3000,2,0)) -> Вахата Федор | K13: 115280, Москва г, ул Мастеркова, 4, Эт 15 Пом I Ком 35 | L13: 200000 | P13: 12 | Q13: 1179086 | R13: 1453942 | S13: 2075137 | T13: 2301202 | U13: 2977193 | V13: -799983 | W13: -832060 | X13: -1266296 | Y13: -1053945 | Z13: 1292887 | AA13: -799983 | AB13: 197045 | AC13: 263131 | AD13: 484044 | AE13: 749259 | AF13: 1151591 | AG13: 1391909 | AH13: 1557802 | AI13: 1814461 | AJ13: 2496513 | AK13: 175659 | AL13: 111498 | AM13: 150323 | AN13: 176690 | AO13: 212366 | AP13: 365873 | AQ13: =IFERROR(ROUND(IFERROR(U13/Q13,IFERROR(U13/R13,IFERROR(U13/S13,IFERROR(U13/T13,"")))),3),"") -> 2.525 | AR13: Значительный | AS13: mbafin.ru | AT13: =IF(VLOOKUP(C13,old!$D$3:$AU$549,44,0)=0,"",VLOOKUP(C13,old!$D$3:$AU$549,44,0)) -> image044 | AU13: 2.1678817 | AV13: =E13&" зарегистрировано по адресу: "&K13&IF(J13=0,"",IF(J13="","",". Генеральным директором является "&J13&IF(AQ13=0,".",IF(AQ13="",".",". Рост доходов компании за 5 лет: "&ROUND(AQ13*100,2)&"%."))&IF(AU13=0,"",IF(AU13="",""," Рост финансовых активов компании за 5 лет: "&IFERROR(ROUND(AU13*100,2),"")&"%."))&IF(AP13=0,"",IF(AP13="",""," Объем заемных средств компании на конец 2024 года: "&AP13&" тыс. руб."))&IF(AR13=0,"",IF(AR13="",""," ФССП присвоил "&AR13&" уровень риска для данного ПКО.")))) -> ООО «ПКО «М.Б.А. Финансы» зарегистрировано по адресу: 115280, Москва г, ул Мастеркова, 4, Эт 15 Пом I Ком 35. Генеральным директором является Вахата Федор. Рост доходов компании за 5 лет: 252,5%. Рост финансовых активов компании за 5 лет: 216,79%. Объем заемных средств компании на конец 2024 года: 365873 тыс. руб. ФССП присвоил Значительный уровень риска для данного ПКО.
A14: 18 | B14: Общество с ограниченной ответственностью «Профессиональная коллекторская организация «Агентство Судебного Взыскания» | C14: 7841019595 | D14: 1157847071073 | E14: ООО «ПКО «АСВ» | F14: 42067 | G14: =ROUNDDOWN(($AY$1-F14)/365,0) -> 10 | H14: Да | I14: =IF(VLOOKUP(C14,гендир!$A$3:$C$3000,3,0)=0,"",VLOOKUP(C14,гендир!$A$3:$C$3000,3,0)) -> Общество С Ограниченной Ответственностью, "АСВ.УПРАВЛЕНИЕ" | J14: =IF(VLOOKUP(C14,гендир!$A$3:$C$3000,2,0)=0,"",VLOOKUP(C14,гендир!$A$3:$C$3000,2,0)) -> Богомолов Максим Владимирович | K14: 194044, город Санкт-Петербург, вн.тер. г. Муниципальный Округ Сампсониевское, пр-кт Большой Сампсониевский, дом 28, корпус 2, литера Д, офис 642 | L14: 115.656 | P14: 13 | Q14: 483240 | R14: 784084 | S14: 1221840 | T14: 1469015 | U14: 2330001 | V14: 189104 | W14: 234597 | X14: 514545 | Y14: 527752 | Z14: 833951 | AA14: 189104 | AB14: 39262 | AC14: 52476 | AD14: 65942 | AE14: 210834 | AF14: 178384 | AG14: 310830 | AH14: 535756 | AI14: 1475570 | AJ14: 1857986 | AK14: 71461 | AL14: 73708 | AM14: 61021 | AN14: 113400 | AO14: 231762 | AP14: 2217172 | AQ14: =IFERROR(ROUND(IFERROR(U14/Q14,IFERROR(U14/R14,IFERROR(U14/S14,IFERROR(U14/T14,"")))),3),"") -> 4.822 | AR14: Низкий | AS14: legalcollection.ru | AT14: =IF(VLOOKUP(C14,old!$D$3:$AU$549,44,0)=0,"",VLOOKUP(C14,old!$D$3:$AU$549,44,0)) -> image204 | AU14: 10.415654 | AV14: =E14&" зарегистрировано по адресу: "&K14&IF(J14=0,"",IF(J14="","",". Генеральным директором является "&J14&IF(AQ14=0,".",IF(AQ14="",".",". Рост доходов компании за 5 лет: "&ROUND(AQ14*100,2)&"%."))&IF(AU14=0,"",IF(AU14="",""," Рост финансовых активов компании за 5 лет: "&IFERROR(ROUND(AU14*100,2),"")&"%."))&IF(AP14=0,"",IF(AP14="",""," Объем заемных средств компании на конец 2024 года: "&AP14&" тыс. руб."))&IF(AR14=0,"",IF(AR14="",""," ФССП присвоил "&AR14&" уровень риска для данного ПКО.")))) -> ООО «ПКО «АСВ» зарегистрировано по адресу: 194044, город Санкт-Петербург, вн.тер. г. Муниципальный Округ Сампсониевское, пр-кт Большой Сампсониевский, дом 28, корпус 2, литера Д, офис 642. Генеральным директором является Богомолов Максим Владимирович. Рост доходов компании за 5 лет: 482,2%. Рост финансовых активов компании за 5 лет: 1041,57%. Объем заемных средств компании на конец 2024 года: 2217172 тыс. руб. ФССП присвоил Низкий уровень риска для данного ПКО.
... A17: 19 | B17: Общество с ограниченной ответственностью Профессиональная коллекторская организация «Фабула» | C17: 1657199916 | D17: 1151690071741 | E17: ООО ПКО «Фабула» | F17: 42256 | G17: =ROUNDDOWN(($AY$1-F17)/365,0) -> 9 | H17: Нет | I17: =IF(VLOOKUP(C17,гендир!$A$3:$C$3000,3,0)=0,"",VLOOKUP(C17,гендир!$A$3:$C$3000,3,0)) -> Общество С Ограниченной Ответственностью, "ЛЕГАЛАЙТ" | J17: =IF(VLOOKUP(C17,гендир!$A$3:$C$3000,2,0)=0,"",VLOOKUP(C17,гендир!$A$3:$C$3000,2,0)) -> Диянов Радик Рашидович | K17: 420044, Татарстан Респ, Казань г, Ямашева пр-кт, дом № 36Д, офис 15 | L17: 15000 | P17: 16 | Q17: 432196 | R17: 688012 | S17: 902262 | T17: 1373573 | U17: 1584330 | V17: 96637 | W17: 165381 | X17: 295097 | Y17: 562133 | Z17: 676507 | AA17: 96637 | AB17: 316576 | AC17: 378643 | AD17: 498600 | AE17: 577188 | AF17: 184152 | AG17: 497285 | AH17: 678648 | AI17: 1031369 | AJ17: 1319603 | AK17: 137587 | AL17: 119788 | AM17: 179893 | AN17: 207466 | AO17: 345144 | AP17: 0 | AQ17: =IFERROR(ROUND(IFERROR(U17/Q17,IFERROR(U17/R17,IFERROR(U17/S17,IFERROR(U17/T17,"")))),3),"") -> 3.666 | AR17: Низкий | AS17: kafabula.ru | AT17: =IF(VLOOKUP(C17,old!$D$3:$AU$549,44,0)=0,"",VLOOKUP(C17,old!$D$3:$AU$549,44,0)) -> image036 | AU17: 7.1658358 | AV17: =E17&" зарегистрировано по адресу: "&K17&IF(J17=0,"",IF(J17="","",". Генеральным директором является "&J17&IF(AQ17=0,".",IF(AQ17="",".",". Рост доходов компании за 5 лет: "&ROUND(AQ17*100,2)&"%."))&IF(AU17=0,"",IF(AU17="",""," Рост финансовых активов компании за 5 лет: "&IFERROR(ROUND(AU17*100,2),"")&"%."))&IF(AP17=0,"",IF(AP17="",""," Объем заемных средств компании на конец 2024 года: "&AP17&" тыс. руб."))&IF(AR17=0,"",IF(AR17="",""," ФССП присвоил "&AR17&" уровень риска для данного ПКО.")))) -> ООО ПКО «Фабула» зарегистрировано по адресу: 420044, Татарстан Респ, Казань г, Ямашева пр-кт, дом № 36Д, офис 15. Генеральным директором является Диянов Радик Рашидович. Рост доходов компании за 5 лет: 366,6%. Рост финансовых активов компании за 5 лет: 716,58%. ФССП присвоил Низкий уровень риска для данного ПКО.
A18: 22 | B18: Общество с ограниченной ответственности Профессиональная коллекторская организация «Вернём» | C18: 5611067262 | D18: 1135658002149 | E18: ООО ПКО «Вернём» | F18: 41302 | G18: =ROUNDDOWN(($AY$1-F18)/365,0) -> 12 | H18: Нет | I18: =IF(VLOOKUP(C18,гендир!$A$3:$C$3000,3,0)=0,"",VLOOKUP(C18,гендир!$A$3:$C$3000,3,0)) -> Луцык Андрей Григорьевич, Жалнина Дарья Александровна, Стержанов Алексей Евгеньевич | J18: =IF(VLOOKUP(C18,гендир!$A$3:$C$3000,2,0)=0,"",VLOOKUP(C18,гендир!$A$3:$C$3000,2,0)) -> Ивановский Павел Владимирович | K18: 650992, Кемеровская область - Кузбасс, г.о. Кемеровский, г Кемерово, ул 50 лет Октября, д. 11, ком. 818 | L18: 30 | P18: 17 | Q18: 259551 | R18: 325575 | S18: 711964 | T18: 1097668 | U18: 1336834 | V18: 46469 | W18: 91478 | X18: 276832 | Y18: 378927 | Z18: 494821 | AA18: 46469 | AB18: -29905 | AC18: 13 | AD18: 44568 | AE18: 75050 | AF18: 651687 | AG18: 1033420 | AH18: 1190136 | AI18: 1265840 | AJ18: 1324574 | AK18: 17428 | AL18: 35069 | AM18: 80875 | AN18: 320772 | AO18: 372691 | AP18: 1586580 | AQ18: =IFERROR(ROUND(IFERROR(U18/Q18,IFERROR(U18/R18,IFERROR(U18/S18,IFERROR(U18/T18,"")))),3),"") -> 5.151 | AR18: 0 | AS18: вернём.рф | AT18: =IF(VLOOKUP(C18,old!$D$3:$AU$549,44,0)=0,"",VLOOKUP(C18,old!$D$3:$AU$549,44,0)) -> image240 | AU18: 2.032531 | AV18: =E18&" зарегистрировано по адресу: "&K18&IF(J18=0,"",IF(J18="","",". Генеральным директором является "&J18&IF(AQ18=0,".",IF(AQ18="",".",". Рост доходов компании за 5 лет: "&ROUND(AQ18*100,2)&"%."))&IF(AU18=0,"",IF(AU18="",""," Рост финансовых активов компании за 5 лет: "&IFERROR(ROUND(AU18*100,2),"")&"%."))&IF(AP18=0,"",IF(AP18="",""," Объем заемных средств компании на конец 2024 года: "&AP18&" тыс. руб."))&IF(AR18=0,"",IF(AR18="",""," ФССП присвоил "&AR18&" уровень риска для данного ПКО.")))) -> ООО ПКО «Вернём» зарегистрировано по адресу: 650992, Кемеровская область - Кузбасс, г.о. Кемеровский, г Кемерово, ул 50 лет Октября, д. 11, ком. 818. Генеральным директором является Ивановский Павел Владимирович. Рост доходов компании за 5 лет: 515,1%. Рост финансовых активов компании за 5 лет: 203,25%. Объем заемных средств компании на конец 2024 года: 1586580 тыс. руб.
A19: 31 | B19: Общество с ограниченной ответственностью «Профессиональная коллекторская организация «Редут» | C19: 1659180290 | D19: 1171690027585 | E19: ООО «ПКО «Редут» | F19: 42817 | G19: =ROUNDDOWN(($AY$1-F19)/365,0) -> 8 | H19: Нет | I19: =IF(VLOOKUP(C19,гендир!$A$3:$C$3000,3,0)=0,"",VLOOKUP(C19,гендир!$A$3:$C$3000,3,0)) -> Садыкова Алина Азатовна | J19: =IF(VLOOKUP(C19,гендир!$A$3:$C$3000,2,0)=0,"",VLOOKUP(C19,гендир!$A$3:$C$3000,2,0)) -> Гаттаров Ринат Саматович | K19: 420021, Татарстан Респ, Казань г, Братьев Петряевых ул, дом № 5, помещение 407 | L19: 10501 | P19: 18 | Q19: 624986 | R19: 617489 | S19: 545602 | T19: 634272 | U19: 1261165 | V19: 407873 | W19: 569400 | X19: 435014 | Y19: 448767 | Z19: 914213 | AA19: 407873 | AB19: -96268 | AC19: 1932 | AD19: 21054 | AE19: 108629 | AF19: 40834 | AG19: 80144 | AH19: 15635 | AI19: 10935 | AJ19: 46799 | AK19: 18533 | AL19: 28478 | AM19: 39028 | AN19: 3801 | AO19: 16702 | AP19: 7456 | AQ19: =IFERROR(ROUND(IFERROR(U19/Q19,IFERROR(U19/R19,IFERROR(U19/S19,IFERROR(U19/T19,"")))),3),"") -> 2.018 | AR19: Низкий | AS19: redut16.ru | AT19: =IF(VLOOKUP(C19,old!$D$3:$AU$549,44,0)=0,"",VLOOKUP(C19,old!$D$3:$AU$549,44,0)) -> image233 | AU19: 1.1460792 | AV19: =E19&" зарегистрировано по адресу: "&K19&IF(J19=0,"",IF(J19="","",". Генеральным директором является "&J19&IF(AQ19=0,".",IF(AQ19="",".",". Рост доходов компании за 5 лет: "&ROUND(AQ19*100,2)&"%."))&IF(AU19=0,"",IF(AU19="",""," Рост финансовых активов компании за 5 лет: "&IFERROR(ROUND(AU19*100,2),"")&"%."))&IF(AP19=0,"",IF(AP19="",""," Объем заемных средств компании на конец 2024 года: "&AP19&" тыс. руб."))&IF(AR19=0,"",IF(AR19="",""," ФССП присвоил "&AR19&" уровень риска для данного ПКО.")))) -> ООО «ПКО «Редут» зарегистрировано по адресу: 420021, Татарстан Респ, Казань г, Братьев Петряевых ул, дом № 5, помещение 407. Генеральным директором является Гаттаров Ринат Саматович. Рост доходов компании за 5 лет: 201,8%. Рост финансовых активов компании за 5 лет: 114,61%. Объем заемных средств компании на конец 2024 года: 7456 тыс. руб. ФССП присвоил Низкий уровень риска для данного ПКО.
A20: 37 | B20: Общество с ограниченной ответственностью «Профессиональная коллекторская организация СОЛ» | C20: 6164139228 | D20: 1226100025029 | E20: ООО «ПКО СОЛ» | F20: 44825 | G20: =ROUNDDOWN(($AY$1-F20)/365,0) -> 2 | H20: Нет | I20: =IF(VLOOKUP(C20,гендир!$A$3:$C$3000,3,0)=0,"",VLOOKUP(C20,гендир!$A$3:$C$3000,3,0)) -> Ванян Лариса Кареновна | J20: =IF(VLOOKUP(C20,гендир!$A$3:$C$3000,2,0)=0,"",VLOOKUP(C20,гендир!$A$3:$C$3000,2,0)) -> Ванян Лариса Кареновна | K20: 344082, Ростовская обл, г Ростов-на-Дону, пер Халтуринский, 4, 25 | L20: 10000 | P20: 19 | Q20: 0 | R20: 0 | S20: 1870 | T20: 471460 | U20: 1258567 | V20: 0 | W20: 0 | X20: -158 | Y20: 353920 | Z20: 1162053 | AA20: 0 | AB20: 0 | AC20: 1611 | AD20: 11298 | AE20: -5590 | AF20: 0 | AG20: 0 | AH20: 0 | AI20: 127879 | AJ20: 387009 | AK20: 0 | AL20: 0 | AM20: 14 | AN20: 118905 | AO20: 280200 | AP20: 181610 | AQ20: =IFERROR(ROUND(IFERROR(U20/Q20,IFERROR(U20/R20,IFERROR(U20/S20,IFERROR(U20/T20,"")))),3),"") -> 673.03 | AR20: Низкий | AS20: ka0sol.ru | AT20: =IF(VLOOKUP(C20,old!$D$3:$AU$549,44,0)=0,"",VLOOKUP(C20,old!$D$3:$AU$549,44,0)) -> image432 | AU20: 3.0263687 | AV20: =E20&" зарегистрировано по адресу: "&K20&IF(J20=0,"",IF(J20="","",". Генеральным директором является "&J20&IF(AQ20=0,".",IF(AQ20="",".",". Рост доходов компании за 5 лет: "&ROUND(AQ20*100,2)&"%."))&IF(AU20=0,"",IF(AU20="",""," Рост финансовых активов компании за 5 лет: "&IFERROR(ROUND(AU20*100,2),"")&"%."))&IF(AP20=0,"",IF(AP20="",""," Объем заемных средств компании на конец 2024 года: "&AP20&" тыс. руб."))&IF(AR20=0,"",IF(AR20="",""," ФССП присвоил "&AR20&" уровень риска для данного ПКО.")))) -> ООО «ПКО СОЛ» зарегистрировано по адресу: 344082, Ростовская обл, г Ростов-на-Дону, пер Халтуринский, 4, 25. Генеральным директором является Ванян Лариса Кареновна. Рост доходов компании за 5 лет: 67303%. Рост финансовых активов компании за 5 лет: 302,64%. Объем заемных средств компании на конец 2024 года: 181610 тыс. руб. ФССП присвоил Низкий уровень риска для данного ПКО.
A21: 25 | B21: Общество с ограниченной ответственностью «Профессиональная коллекторская организация ВПК-Капитал» | C21: 3702239395 | D21: 1203700004375 | E21: ООО «ПКО ВПК-Капитал» | F21: 43892 | G21: =ROUNDDOWN(($AY$1-F21)/365,0) -> 5 | H21: Нет | I21: =IF(VLOOKUP(C21,гендир!$A$3:$C$3000,3,0)=0,"",VLOOKUP(C21,гендир!$A$3:$C$3000,3,0)) -> Вахатова Мария Михайловна, Юркив Евгения Анатольевна, Кадышев Роман Иванович | J21: =IF(VLOOKUP(C21,гендир!$A$3:$C$3000,2,0)=0,"",VLOOKUP(C21,гендир!$A$3:$C$3000,2,0)) -> Кадышев Роман Иванович | K21: 153012, Ивановская обл, г Иваново, ул Марии Рябининой, 5, 2 | L21: 10500 | P21: 20 | Q21: 32723 | R21: 172216 | S21: 404532 | T21: 781162 | U21: 1249961 | V21: 8277 | W21: 70749 | X21: 172971 | Y21: 287250 | Z21: 675418 | AA21: 8277 | AB21: 92331 | AC21: 185242 | AD21: 368694 | AE21: 407064 | AF21: 31049 | AG21: 141586 | AH21: 432771 | AI21: 707496 | AJ21: 854703 | AK21: 343 | AL21: 585 | AM21: 1142 | AN21: 2915 | AO21: 7173 | AP21: 205768 | AQ21: =IFERROR(ROUND(IFERROR(U21/Q21,IFERROR(U21/R21,IFERROR(U21/S21,IFERROR(U21/T21,"")))),3),"") -> 38.198 | AR21: Низкий | AS21: vpk0capital.ru | AT21: =IF(VLOOKUP(C21,old!$D$3:$AU$549,44,0)=0,"",VLOOKUP(C21,old!$D$3:$AU$549,44,0)) -> image311 | AU21: 27.527553 | AV21: =E21&" зарегистрировано по адресу: "&K21&IF(J21=0,"",IF(J21="","",". Генеральным директором является "&J21&IF(AQ21=0,".",IF(AQ21="",".",". Рост доходов компании за 5 лет: "&ROUND(AQ21*100,2)&"%."))&IF(AU21=0,"",IF(AU21="",""," Рост финансовых активов компании за 5 лет: "&IFERROR(ROUND(AU21*100,2),"")&"%."))&IF(AP21=0,"",IF(AP21="",""," Объем заемных средств компании на конец 2024 года: "&AP21&" тыс. руб."))&IF(AR21=0,"",IF(AR21="",""," ФССП присвоил "&AR21&" уровень риска для данного ПКО.")))) -> ООО «ПКО ВПК-Капитал» зарегистрировано по адресу: 153012, Ивановская обл, г Иваново, ул Марии Рябининой, 5, 2. Генеральным директором является Кадышев Роман Иванович. Рост доходов компании за 5 лет: 3819,8%. Рост финансовых активов компании за 5 лет: 2752,76%. Объем заемных средств компании на конец 2024 года: 205768 тыс. руб. ФССП присвоил Низкий уровень риска для данного ПКО.
A22: 54 | B22: Общество с ограниченной ответственностью «Профессиональная коллекторская организация «Камелот» | C22: 5902160058 | D22: 1075902008445 | E22: ООО «ПКО «Камелот» | F22: 39283 | G22: =ROUNDDOWN(($AY$1-F22)/365,0) -> 17 | H22: Нет | I22: =IF(VLOOKUP(C22,гендир!$A$3:$C$3000,3,0)=0,"",VLOOKUP(C22,гендир!$A$3:$C$3000,3,0)) -> Харисов Артем Фанусович, Лизунов Сергей Евгеньевич | J22: =IF(VLOOKUP(C22,гендир!$A$3:$C$3000,2,0)=0,"",VLOOKUP(C22,гендир!$A$3:$C$3000,2,0)) -> Лизунов Сергей Евгеньевич | K22: 614015, Пермский край, г. Пермь, ул. Монастырская, дом 14, квартира 200 | L22: 10 | P22: 21 | Q22: 235373 | R22: 297168 | S22: 581761 | T22: 283795 | U22: 1204007 | V22: 14701 | W22: 26943 | X22: 27548 | Y22: 49569 | Z22: 2397060 | AA22: 14701 | AB22: 269327 | AC22: 553265 | AD22: 232192 | AE22: -1197547 | AF22: 0 | AG22: 0 | AH22: 0 | AI22: 0 | AJ22: 0 | AK22: 258453 | AL22: 540280 | AM22: 1091383 | AN22: 1324970 | AO22: 125893 | AP22: 5659 | AQ22: =IFERROR(ROUND(IFERROR(U22/Q22,IFERROR(U22/R22,IFERROR(U22/S22,IFERROR(U22/T22,"")))),3),"") -> 5.115 | AR22: 0 | AS22: kamelotperm.ru | AT22: =IF(VLOOKUP(C22,old!$D$3:$AU$549,44,0)=0,"",VLOOKUP(C22,old!$D$3:$AU$549,44,0)) -> image005 | AV22: =E22&" зарегистрировано по адресу: "&K22&IF(J22=0,"",IF(J22="","",". Генеральным директором является "&J22&IF(AQ22=0,".",IF(AQ22="",".",". Рост доходов компании за 5 лет: "&ROUND(AQ22*100,2)&"%."))&IF(AU22=0,"",IF(AU22="",""," Рост финансовых активов компании за 5 лет: "&IFERROR(ROUND(AU22*100,2),"")&"%."))&IF(AP22=0,"",IF(AP22="",""," Объем заемных средств компании на конец 2024 года: "&AP22&" тыс. руб."))&IF(AR22=0,"",IF(AR22="",""," ФССП присвоил "&AR22&" уровень риска для данного ПКО.")))) -> ООО «ПКО «Камелот» зарегистрировано по адресу: 614015, Пермский край, г. Пермь, ул. Монастырская, дом 14, квартира 200. Генеральным директором является Лизунов Сергей Евгеньевич. Рост доходов компании за 5 лет: 511,5%. Объем заемных средств компании на конец 2024 года: 5659 тыс. руб.
A23: 20 | B23: Общество с ограниченной ответственностью «Профессиональная коллекторская организация Управляющая компания Траст» | C23: 3801109213 | D23: 1103801002909 | E23: ООО «ПКО Управляющая компания Траст» | F23: 40373 | G23: =ROUNDDOWN(($AY$1-F23)/365,0) -> 14 | H23: Нет | I23: =IF(VLOOKUP(C23,гендир!$A$3:$C$3000,3,0)=0,"",VLOOKUP(C23,гендир!$A$3:$C$3000,3,0)) -> Долюк Андрей Николаевич, Самбудагва Ксения Павловна | J23: =IF(VLOOKUP(C23,гендир!$A$3:$C$3000,2,0)=0,"",VLOOKUP(C23,гендир!$A$3:$C$3000,2,0)) -> Долюк Андрей Николаевич | K23: 665801, Иркутская обл, г.о. Ангарское, г Ангарск, кв-л 252, стр. 19, д.офис 207 | L23: 40 | P23: 22 | Q23: 620347 | R23: 813876 | S23: 1140510 | T23: 1252507 | U23: 1151012 | V23: 70820 | W23: 121894 | X23: 199679 | Y23: 289867 | Z23: 239551 | AA23: 70820 | AB23: 500980 | AC23: 678397 | AD23: 679210 | AE23: 649462 | AF23: 633564 | AG23: 783654 | AH23: 955607 | AI23: 1423161 | AJ23: 1918391 | AK23: 28851 | AL23: 41828 | AM23: 44679 | AN23: 34209 | AO23: 44170 | AP23: 37031 | AQ23: =IFERROR(ROUND(IFERROR(U23/Q23,IFERROR(U23/R23,IFERROR(U23/S23,IFERROR(U23/T23,"")))),3),"") -> 1.855 | AR23: Низкий | AS23: trust0uk.ru | AT23: =IF(VLOOKUP(C23,old!$D$3:$AU$549,44,0)=0,"",VLOOKUP(C23,old!$D$3:$AU$549,44,0)) -> image300 | AU23: 3.0279356 | AV23: =E23&" зарегистрировано по адресу: "&K23&IF(J23=0,"",IF(J23="","",". Генеральным директором является "&J23&IF(AQ23=0,".",IF(AQ23="",".",". Рост доходов компании за 5 лет: "&ROUND(AQ23*100,2)&"%."))&IF(AU23=0,"",IF(AU23="",""," Рост финансовых активов компании за 5 лет: "&IFERROR(ROUND(AU23*100,2),"")&"%."))&IF(AP23=0,"",IF(AP23="",""," Объем заемных средств компании на конец 2024 года: "&AP23&" тыс. руб."))&IF(AR23=0,"",IF(AR23="",""," ФССП присвоил "&AR23&" уровень риска для данного ПКО.")))) -> ООО «ПКО Управляющая компания Траст» зарегистрировано по адресу: 665801, Иркутская обл, г.о. Ангарское, г Ангарск, кв-л 252, стр. 19, д.офис 207. Генеральным директором является Долюк Андрей Николаевич. Рост доходов компании за 5 лет: 185,5%. Рост финансовых активов компании за 5 лет: 302,79%. Объем заемных средств компании на конец 2024 года: 37031 тыс. руб. ФССП присвоил Низкий уровень риска для данного ПКО.
A24: 39 | B24: Общество с ограниченной ответственностью Профессиональная коллекторская организация «Интел коллект» | C24: 5407977286 | D24: 1205400001399 | E24: ООО ПКО «Интел коллект» | F24: 43846 | G24: =ROUNDDOWN(($AY$1-F24)/365,0) -> 5 | H24: Нет | I24: =IF(VLOOKUP(C24,гендир!$A$3:$C$3000,3,0)=0,"",VLOOKUP(C24,гендир!$A$3:$C$3000,3,0)) -> Микрофинансовая Компания, "ЛАЙМ-ЗАЙМ", (общество С Ограниченной Ответственностью) | J24: =IF(VLOOKUP(C24,гендир!$A$3:$C$3000,2,0)=0,"",VLOOKUP(C24,гендир!$A$3:$C$3000,2,0)) -> Полетаев Тимофей Олегович | K24: 630102, Новосибирская обл, г Новосибирск, ул Восход, д. 20, офис 14 | L24: 11 | P24: 23 | Q24: 606 | R24: 17881 | S24: 252365 | T24: 404847 | U24: 1032325 | V24: 31 | W24: 14010 | X24: 109258 | Y24: 226642 | Z24: 413636 | AA24: 31 | AB24: 2559 | AC24: 121216 | AD24: 140116 | AE24: 247149 | AF24: 3846 | AG24: 0 | AH24: 0 | AI24: 0 | AJ24: 1156303 | AK24: 159 | AL24: 23449 | AM24: 164943 | AN24: 677140 | AO24: 15567 | AP24: 414784 | AQ24: =IFERROR(ROUND(IFERROR(U24/Q24,IFERROR(U24/R24,IFERROR(U24/S24,IFERROR(U24/T24,"")))),3),"") -> 1703.507 | AR24: Низкий | AS24: intelcollect.ru | AT24: =IF(VLOOKUP(C24,old!$D$3:$AU$549,44,0)=0,"",VLOOKUP(C24,old!$D$3:$AU$549,44,0)) -> image310 | AU24: 300.65081 | AV24: =E24&" зарегистрировано по адресу: "&K24&IF(J24=0,"",IF(J24="","",". Генеральным директором является "&J24&IF(AQ24=0,".",IF(AQ24="",".",". Рост доходов компании за 5 лет: "&ROUND(AQ24*100,2)&"%."))&IF(AU24=0,"",IF(AU24="",""," Рост финансовых активов компании за 5 лет: "&IFERROR(ROUND(AU24*100,2),"")&"%."))&IF(AP24=0,"",IF(AP24="",""," Объем заемных средств компании на конец 2024 года: "&AP24&" тыс. руб."))&IF(AR24=0,"",IF(AR24="",""," ФССП присвоил "&AR24&" уровень риска для данного ПКО.")))) -> ООО ПКО «Интел коллект» зарегистрировано по адресу: 630102, Новосибирская обл, г Новосибирск, ул Восход, д. 20, офис 14. Генеральным директором является Полетаев Тимофей Олегович. Рост доходов компании за 5 лет: 170350,7%. Рост финансовых активов компании за 5 лет: 30065,08%. Объем заемных средств компании на конец 2024 года: 414784 тыс. руб. ФССП присвоил Низкий уровень риска для данного ПКО.
A25: 122 | B25: Общество с ограниченной ответственностью «Профессиональная коллекторская организация «Киберколлект» | C25: 1655364579 | D25: 1161690117852 | E25: ООО «ПКО «Киберколлект» | F25: 42544 | G25: =ROUNDDOWN(($AY$1-F25)/365,0) -> 8 | H25: Нет | I25: =IF(VLOOKUP(C25,гендир!$A$3:$C$3000,3,0)=0,"",VLOOKUP(C25,гендир!$A$3:$C$3000,3,0)) -> Бабушкин Валерий Евгеньевич | J25: =IF(VLOOKUP(C25,гендир!$A$3:$C$3000,2,0)=0,"",VLOOKUP(C25,гендир!$A$3:$C$3000,2,0)) -> Казак Екатерина Николаевна | K25: 420043, Республика Татарстан (Татарстан), г Казань, ул Вишневского, д. 22, помещ. 9 | L25: 28232 | P25: 24 | Q25: 0 | R25: 110 | S25: 101498 | T25: 341533 | U25: 1032276 | V25: 246 | W25: 251 | X25: 13583 | Y25: 129032 | Z25: 270763 | AA25: 246 | AB25: -6917 | AC25: -19996 | AD25: 131724 | AE25: 9535 | AF25: 38 | AG25: 0 | AH25: 179866 | AI25: 840710 | AJ25: 1619251 | AK25: 73 | AL25: 159269 | AM25: 451912 | AN25: 461271 | AO25: 252095 | AP25: 1704387 | AQ25: =IFERROR(ROUND(IFERROR(U25/Q25,IFERROR(U25/R25,IFERROR(U25/S25,IFERROR(U25/T25,"")))),3),"") -> 9384.327 | AR25: Значительный | AS25: cybercollect.ru | AT25: =IF(VLOOKUP(C25,old!$D$3:$AU$549,44,0)=0,"",VLOOKUP(C25,old!$D$3:$AU$549,44,0)) -> image364 | AU25: 42611.868 | AV25: =E25&" зарегистрировано по адресу: "&K25&IF(J25=0,"",IF(J25="","",". Генеральным директором является "&J25&IF(AQ25=0,".",IF(AQ25="",".",". Рост доходов компании за 5 лет: "&ROUND(AQ25*100,2)&"%."))&IF(AU25=0,"",IF(AU25="",""," Рост финансовых активов компании за 5 лет: "&IFERROR(ROUND(AU25*100,2),"")&"%."))&IF(AP25=0,"",IF(AP25="",""," Объем заемных средств компании на конец 2024 года: "&AP25&" тыс. руб."))&IF(AR25=0,"",IF(AR25="",""," ФССП присвоил "&AR25&" уровень риска для данного ПКО.")))) -> ООО «ПКО «Киберколлект» зарегистрировано по адресу: 420043, Республика Татарстан (Татарстан), г Казань, ул Вишневского, д. 22, помещ. 9. Генеральным директором является Казак Екатерина Николаевна. Рост доходов компании за 5 лет: 938432,7%. Рост финансовых активов компании за 5 лет: 4261186,84%. Объем заемных средств компании на конец 2024 года: 1704387 тыс. руб. ФССП присвоил Значительный уровень риска для данного ПКО.
A26: 28 | B26: Общество с ограниченной ответственностью Профессиональная коллекторская организация «Кредитэкспресс Финанс» | C26: 7707790885 | D26: 1127747190152 | E26: ООО ПКО «КЭФ» | F26: 41241 | G26: =ROUNDDOWN(($AY$1-F26)/365,0) -> 12 | H26: Да | I26: =IF(VLOOKUP(C26,гендир!$A$3:$C$3000,3,0)=0,"",VLOOKUP(C26,гендир!$A$3:$C$3000,3,0)) -> Частное Общество С Ограниченной Ответственностью, "КРЕДИТ ЭКСПРЕСС ГРУПП Б.В.", Свеа Инкассо Актиболаг | J26: =IF(VLOOKUP(C26,гендир!$A$3:$C$3000,2,0)=0,"",VLOOKUP(C26,гендир!$A$3:$C$3000,2,0)) -> Семендуев Виктор Александрович | K26: 127055, Москва г, вн.тер.г. муниципальный округ Тверской, ул Бутырский Вал, д. 68/70, стр. 1, помещ. 1, комната 44 | L26: 10 | P26: 25 | Q26: 474215 | R26: 390849 | S26: 502071 | T26: 713679 | U26: 888275 | V26: 12768 | W26: 17664 | X26: 22897 | Y26: 20296 | Z26: 12655 | AA26: 12768 | AB26: 35508 | AC26: -149088 | AD26: 106226 | AE26: 173720 | AF26: 0 | AG26: 0 | AH26: 0 | AI26: 0 | AJ26: 0 | AK26: 71864 | AL26: 58175 | AM26: 87560 | AN26: 94184 | AO26: 121904 | AP26: 0 | AQ26: =IFERROR(ROUND(IFERROR(U26/Q26,IFERROR(U26/R26,IFERROR(U26/S26,IFERROR(U26/T26,"")))),3),"") -> 1.873 | AR26: 0 | AS26: creditexpress.ru | AT26: =IF(VLOOKUP(C26,old!$D$3:$AU$549,44,0)=0,"",VLOOKUP(C26,old!$D$3:$AU$549,44,0)) -> image289 | AV26: =E26&" зарегистрировано по адресу: "&K26&IF(J26=0,"",IF(J26="","",". Генеральным директором является "&J26&IF(AQ26=0,".",IF(AQ26="",".",". Рост доходов компании за 5 лет: "&ROUND(AQ26*100,2)&"%."))&IF(AU26=0,"",IF(AU26="",""," Рост финансовых активов компании за 5 лет: "&IFERROR(ROUND(AU26*100,2),"")&"%."))&IF(AP26=0,"",IF(AP26="",""," Объем заемных средств компании на конец 2024 года: "&AP26&" тыс. руб."))&IF(AR26=0,"",IF(AR26="",""," ФССП присвоил "&AR26&" уровень риска для данного ПКО.")))) -> ООО ПКО «КЭФ» зарегистрировано по адресу: 127055, Москва г, вн.тер.г. муниципальный округ Тверской, ул Бутырский Вал, д. 68/70, стр. 1, помещ. 1, комната 44. Генеральным директором является Семендуев Виктор Александрович. Рост доходов компании за 5 лет: 187,3%.
A27: 94 | B27: Общество с ограниченной ответственностью «Профессиональная коллекторская организация «Аскалон» | C27: 7203492939 | D27: 1197232028388 | E27: ООО «ПКО «Аскалон» | F27: 43784 | G27: =ROUNDDOWN(($AY$1-F27)/365,0) -> 5 | H27: Нет | I27: =IF(VLOOKUP(C27,гендир!$A$3:$C$3000,3,0)=0,"",VLOOKUP(C27,гендир!$A$3:$C$3000,3,0)) -> Аксенов Алексей Александрович | J27: =IF(VLOOKUP(C27,гендир!$A$3:$C$3000,2,0)=0,"",VLOOKUP(C27,гендир!$A$3:$C$3000,2,0)) -> Аксенов Алексей Александрович | K27: 628403, Ханты-Мансийский Автономный округ - Югра, г.о. Сургут, г Сургут, ул 30 лет Победы, зд. 44А, офис 8/1 | L27: 10.204 | P27: 26 | Q27: 11558 | R27: 248629 | S27: 246916 | T27: 163057 | U27: 871130 | V27: 1463 | W27: 237527 | X27: 231614 | Y27: 166991 | Z27: 772065 | AA27: 1463 | AB27: 8301 | AC27: 9832 | AD27: -14228 | AE27: 6799 | AF27: 1 | AG27: 313 | AH27: 301 | AI27: 300 | AJ27: 300 | AK27: 6745 | AL27: 1006 | AM27: 3370 | AN27: 280455 | AO27: 598217 | AP27: 576284 | AQ27: =IFERROR(ROUND(IFERROR(U27/Q27,IFERROR(U27/R27,IFERROR(U27/S27,IFERROR(U27/T27,"")))),3),"") -> 75.37 | AR27: Низкий | AS27: dolgi72.ru | AT27: =IF(VLOOKUP(C27,old!$D$3:$AU$549,44,0)=0,"",VLOOKUP(C27,old!$D$3:$AU$549,44,0)) -> image025 | AU27: 300 | AV27: =E27&" зарегистрировано по адресу: "&K27&IF(J27=0,"",IF(J27="","",". Генеральным директором является "&J27&IF(AQ27=0,".",IF(AQ27="",".",". Рост доходов компании за 5 лет: "&ROUND(AQ27*100,2)&"%."))&IF(AU27=0,"",IF(AU27="",""," Рост финансовых активов компании за 5 лет: "&IFERROR(ROUND(AU27*100,2),"")&"%."))&IF(AP27=0,"",IF(AP27="",""," Объем заемных средств компании на конец 2024 года: "&AP27&" тыс. руб."))&IF(AR27=0,"",IF(AR27="",""," ФССП присвоил "&AR27&" уровень риска для данного ПКО.")))) -> ООО «ПКО «Аскалон» зарегистрировано по адресу: 628403, Ханты-Мансийский Автономный округ - Югра, г.о. Сургут, г Сургут, ул 30 лет Победы, зд. 44А, офис 8/1. Генеральным директором является Аксенов Алексей Александрович. Рост доходов компании за 5 лет: 7537%. Рост финансовых активов компании за 5 лет: 30000%. Объем заемных средств компании на конец 2024 года: 576284 тыс. руб. ФССП присвоил Низкий уровень риска для данного ПКО.
A28: 27 | B28: Общество с ограниченной ответственностью Профессиональная коллекторская организация НСВ | C28: 7727551797 | D28: 1057748047675 | E28: ООО ПКО НСВ | F28: 38595 | G28: =ROUNDDOWN(($AY$1-F28)/365,0) -> 19 | H28: Да | I28: =IF(VLOOKUP(C28,гендир!$A$3:$C$3000,3,0)=0,"",VLOOKUP(C28,гендир!$A$3:$C$3000,3,0)) -> Общество С Ограниченной Ответственностью, "АВТОМАТИЗИРОВАННЫЕ ГОЛОСОВЫЕ СИСТЕМЫ", Непубличное Акционерное Общество Профессиональная Коллекторская Организация, "ПЕРВОЕ КЛИЕНТСКОЕ БЮРО" | J28: =IF(VLOOKUP(C28,гендир!$A$3:$C$3000,2,0)=0,"",VLOOKUP(C28,гендир!$A$3:$C$3000,2,0)) -> Виноградов Артур Алексеевич | K28: 108811, Москва г, км Киевское шоссе 22-й (п Московский), 6, 1 | L28: 67600 | P28: 27 | Q28: 763278 | R28: 794354 | S28: 791529 | T28: 752563 | U28: 751828 | V28: 509133 | W28: 582015 | X28: 521744 | Y28: 426648 | Z28: 465905 | AA28: 509133 | AB28: -32283 | AC28: 47374 | AD28: 33519 | AE28: 35693 | AF28: 316508 | AG28: 350772 | AH28: 537837 | AI28: 6380 | AJ28: 12115 | AK28: 124537 | AL28: 106926 | AM28: 103491 | AN28: 155738 | AO28: 88079 | AP28: 0 | AQ28: =IFERROR(ROUND(IFERROR(U28/Q28,IFERROR(U28/R28,IFERROR(U28/S28,IFERROR(U28/T28,"")))),3),"") -> 0.985 | AR28: Низкий | AS28: nrservice.ru | AT28: =IF(VLOOKUP(C28,old!$D$3:$AU$549,44,0)=0,"",VLOOKUP(C28,old!$D$3:$AU$549,44,0)) -> image200 | AU28: 0.038277074 | AV28: =E28&" зарегистрировано по адресу: "&K28&IF(J28=0,"",IF(J28="","",". Генеральным директором является "&J28&IF(AQ28=0,".",IF(AQ28="",".",". Рост доходов компании за 5 лет: "&ROUND(AQ28*100,2)&"%."))&IF(AU28=0,"",IF(AU28="",""," Рост финансовых активов компании за 5 лет: "&IFERROR(ROUND(AU28*100,2),"")&"%."))&IF(AP28=0,"",IF(AP28="",""," Объем заемных средств компании на конец 2024 года: "&AP28&" тыс. руб."))&IF(AR28=0,"",IF(AR28="",""," ФССП присвоил "&AR28&" уровень риска для данного ПКО.")))) -> ООО ПКО НСВ зарегистрировано по адресу: 108811, Москва г, км Киевское шоссе 22-й (п Московский), 6, 1. Генеральным директором является Виноградов Артур Алексеевич. Рост доходов компании за 5 лет: 98,5%. Рост финансовых активов компании за 5 лет: 3,83%. ФССП присвоил Низкий уровень риска для данного ПКО.
A29: 34 | B29: Общество с ограниченной ответственностью Профессиональная коллекторская организация «Бюро судебного взыскания» | C29: 2225130330 | D29: 1122225006056 | E29: ООО ПКО «БСВ» | F29: 45691 | G29: =ROUNDDOWN(($AY$1-F29)/365,0) -> 0 | H29: Да | I29: =IF(VLOOKUP(C29,гендир!$A$3:$C$3000,3,0)=0,"",VLOOKUP(C29,гендир!$A$3:$C$3000,3,0)) -> Корнилов Станислав Юрьевич | J29: =IF(VLOOKUP(C29,гендир!$A$3:$C$3000,2,0)=0,"",VLOOKUP(C29,гендир!$A$3:$C$3000,2,0)) -> Лукьянов Денис Владимирович | K29: г. Новосибирск, ул. Добролюбова, д. 10/2, 630009 | L29: 20 | P29: 28 | Q29: 144144 | R29: 230065 | S29: 320820 | T29: 558677 | U29: 642678 | V29: 21683 | W29: 41419 | X29: 98997 | Y29: 342571 | Z29: 385166 | AA29: 21683 | AB29: 132354 | AC29: 70958 | AD29: -68269 | AE29: -11710 | AF29: 53836 | AG29: 48312 | AH29: 145178 | AI29: 113541 | AJ29: 125535 | AK29: 24420 | AL29: 125403 | AM29: 141779 | AN29: 49726 | AO29: 74119 | AP29: 76417 | AQ29: =IFERROR(ROUND(IFERROR(U29/Q29,IFERROR(U29/R29,IFERROR(U29/S29,IFERROR(U29/T29,"")))),3),"") -> 4.459 | AR29: Низкий | AS29: bsv0nsk.ru | AT29: =IF(VLOOKUP(C29,old!$D$3:$AU$549,44,0)=0,"",VLOOKUP(C29,old!$D$3:$AU$549,44,0)) -> image153 | AU29: 2.331804 | AV29: =E29&" зарегистрировано по адресу: "&K29&IF(J29=0,"",IF(J29="","",". Генеральным директором является "&J29&IF(AQ29=0,".",IF(AQ29="",".",". Рост доходов компании за 5 лет: "&ROUND(AQ29*100,2)&"%."))&IF(AU29=0,"",IF(AU29="",""," Рост финансовых активов компании за 5 лет: "&IFERROR(ROUND(AU29*100,2),"")&"%."))&IF(AP29=0,"",IF(AP29="",""," Объем заемных средств компании на конец 2024 года: "&AP29&" тыс. руб."))&IF(AR29=0,"",IF(AR29="",""," ФССП присвоил "&AR29&" уровень риска для данного ПКО.")))) -> ООО ПКО «БСВ» зарегистрировано по адресу: г. Новосибирск, ул. Добролюбова, д. 10/2, 630009. Генеральным директором является Лукьянов Денис Владимирович. Рост доходов компании за 5 лет: 445,9%. Рост финансовых активов компании за 5 лет: 233,18%. Объем заемных средств компании на конец 2024 года: 76417 тыс. руб. ФССП присвоил Низкий уровень риска для данного ПКО.
A30: 29 | B30: Акционерное общество Профессиональная коллекторская организация «Финансовое Агентство по Сбору Платежей» | C30: 7704527702 | D30: 1047796582305 | E30: АО ПКО «ФАСП» | F30: 38208 | G30: =ROUNDDOWN(($AY$1-F30)/365,0) -> 20 | H30: Да | I30: =IF(VLOOKUP(C30,гендир!$A$3:$C$3000,3,0)=0,"",VLOOKUP(C30,гендир!$A$3:$C$3000,3,0)) | J30: =IF(VLOOKUP(C30,гендир!$A$3:$C$3000,2,0)=0,"",VLOOKUP(C30,гендир!$A$3:$C$3000,2,0)) -> Давымока Сергей Вячеславович | K30: 121151, Москва г, наб Тараса Шевченко, 23А, пом. 1Н/5 | L30: 773.6 | P30: 29 | Q30: 862236 | R30: 648052 | S30: 578020 | T30: 686798 | U30: 633524 | V30: 627678 | W30: 316547 | X30: 326949 | Y30: 526060 | Z30: 424217 | AA30: 627678 | AB30: 182119 | AC30: 110667 | AD30: 30277 | AE30: 139039 | AF30: 96823 | AG30: 100966 | AH30: 66399 | AI30: 539 | AJ30: 33682 | AK30: 78141 | AL30: 138344 | AM30: 79740 | AN30: 62352 | AO30: 121055 | AP30: 0 | AQ30: =IFERROR(ROUND(IFERROR(U30/Q30,IFERROR(U30/R30,IFERROR(U30/S30,IFERROR(U30/T30,"")))),3),"") -> 0.735 | AR30: Низкий | AS30: fasp.ru | AT30: =IF(VLOOKUP(C30,old!$D$3:$AU$549,44,0)=0,"",VLOOKUP(C30,old!$D$3:$AU$549,44,0)) -> image157 | AU30: 0.34787189 | AV30: =E30&" зарегистрировано по адресу: "&K30&IF(J30=0,"",IF(J30="","",". Генеральным директором является "&J30&IF(AQ30=0,".",IF(AQ30="",".",". Рост доходов компании за 5 лет: "&ROUND(AQ30*100,2)&"%."))&IF(AU30=0,"",IF(AU30="",""," Рост финансовых активов компании за 5 лет: "&IFERROR(ROUND(AU30*100,2),"")&"%."))&IF(AP30=0,"",IF(AP30="",""," Объем заемных средств компании на конец 2024 года: "&AP30&" тыс. руб."))&IF(AR30=0,"",IF(AR30="",""," ФССП присвоил "&AR30&" уровень риска для данного ПКО.")))) -> АО ПКО «ФАСП» зарегистрировано по адресу: 121151, Москва г, наб Тараса Шевченко, 23А, пом. 1Н/5. Генеральным директором является Давымока Сергей Вячеславович. Рост доходов компании за 5 лет: 73,5%. Рост финансовых активов компании за 5 лет: 34,79%. ФССП присвоил Низкий уровень риска для данного ПКО.
A31: 546 | B31: Общество с ограниченной ответственностью «Профессиональная коллекторская организация «ЮРИДИЧЕСКАЯ СЛУЖБА ВЗЫСКАНИЯ» | C31: 6168114626 | D31: 1216100018750 | E31: ООО ПКО «ЮСВ» | F31: 44382 | G31: =ROUNDDOWN(($AY$1-F31)/365,0) -> 3 | H31: Нет | I31: =IF(VLOOKUP(C31,гендир!$A$3:$C$3000,3,0)=0,"",VLOOKUP(C31,гендир!$A$3:$C$3000,3,0)) -> Общество С Ограниченной Ответственностью, "ФИНБРИДЖ" | J31: =IF(VLOOKUP(C31,гендир!$A$3:$C$3000,2,0)=0,"",VLOOKUP(C31,гендир!$A$3:$C$3000,2,0)) -> Спасенная Алена Олеговна | K31: 344091, Ростовская обл, г Ростов-на-Дону, ул Малиновского, 3, 25 | L31: 10000 | P31: 30 | Q31: 0 | R31: 17357 | S31: 84780 | T31: 141693 | U31: 625885 | V31: 0 | W31: 6230 | X31: 68610 | Y31: 89958 | Z31: 369240 | AA31: 0 | AB31: 10516 | AC31: 7660 | AD31: 19432 | AE31: 25136 | AF31: 0 | AG31: 16343 | AH31: 149363 | AI31: 515934 | AJ31: 1376077 | AK31: 0 | AL31: 230 | AM31: 796 | AN31: 18713 | AO31: 15739 | AP31: 940402 | AQ31: =IFERROR(ROUND(IFERROR(U31/Q31,IFERROR(U31/R31,IFERROR(U31/S31,IFERROR(U31/T31,"")))),3),"") -> 36.06 | AS31: inf@usv-ka.ru | AT31: =IF(VLOOKUP(C31,old!$D$3:$AU$549,44,0)=0,"",VLOOKUP(C31,old!$D$3:$AU$549,44,0)) | AU31: 84.19978 | AV31: =E31&" зарегистрировано по адресу: "&K31&IF(J31=0,"",IF(J31="","",". Генеральным директором является "&J31&IF(AQ31=0,".",IF(AQ31="",".",". Рост доходов компании за 5 лет: "&ROUND(AQ31*100,2)&"%."))&IF(AU31=0,"",IF(AU31="",""," Рост финансовых активов компании за 5 лет: "&IFERROR(ROUND(AU31*100,2),"")&"%."))&IF(AP31=0,"",IF(AP31="",""," Объем заемных средств компании на конец 2024 года: "&AP31&" тыс. руб."))&IF(AR31=0,"",IF(AR31="",""," ФССП присвоил "&AR31&" уровень риска для данного ПКО.")))) -> ООО ПКО «ЮСВ» зарегистрировано по адресу: 344091, Ростовская обл, г Ростов-на-Дону, ул Малиновского, 3, 25. Генеральным директором является Спасенная Алена Олеговна. Рост доходов компании за 5 лет: 3606%. Рост финансовых активов компании за 5 лет: 8419,98%. Объем заемных средств компании на конец 2024 года: 940402 тыс. руб.
A32: 141 | B32: Общество с ограниченной ответственностью Профессиональная коллекторская организация «Вива Коллект» | C32: 7727465322 | D32: 1217700225148 | E32: ООО ПКО «Вива Коллект» | F32: 44328 | G32: =ROUNDDOWN(($AY$1-F32)/365,0) -> 3 | H32: Нет | I32: =IF(VLOOKUP(C32,гендир!$A$3:$C$3000,3,0)=0,"",VLOOKUP(C32,гендир!$A$3:$C$3000,3,0)) -> Мирончик Роман Борисович, Власов Дмитрий Викторович, Москаленко Андрей Сергеевич, Мурзин Алексей Валерьевич, Пацко Олеся Александровна | J32: =IF(VLOOKUP(C32,гендир!$A$3:$C$3000,2,0)=0,"",VLOOKUP(C32,гендир!$A$3:$C$3000,2,0)) -> Хазиев Азат Рамилевич | K32: 117218, Москва г, ул Кржижановского, 29, 2, Этаж 2 Помещ VIII | L32: 15000 | P32: 31 | Q32: 0 | R32: 4730 | S32: 84474 | T32: 147285 | U32: 615879 | V32: 0 | W32: 1141 | X32: 14358 | Y32: 82652 | Z32: 302637 | AA32: 0 | AB32: 2871 | AC32: 53227 | AD32: 10172 | AE32: 111254 | AF32: 0 | AG32: 159363 | AH32: 131388 | AI32: 360521 | AJ32: 865281 | AK32: 0 | AL32: 102 | AM32: 109 | AN32: 79836 | AO32: 97869 | AP32: 787650 | AQ32: =IFERROR(ROUND(IFERROR(U32/Q32,IFERROR(U32/R32,IFERROR(U32/S32,IFERROR(U32/T32,"")))),3),"") -> 130.207 | AR32: Высокий | AS32: vivacollect.ru | AT32: =IF(VLOOKUP(C32,old!$D$3:$AU$549,44,0)=0,"",VLOOKUP(C32,old!$D$3:$AU$549,44,0)) -> image374 | AU32: 5.4296229 | AV32: =E32&" зарегистрировано по адресу: "&K32&IF(J32=0,"",IF(J32="","",". Генеральным директором является "&J32&IF(AQ32=0,".",IF(AQ32="",".",". Рост доходов компании за 5 лет: "&ROUND(AQ32*100,2)&"%."))&IF(AU32=0,"",IF(AU32="",""," Рост финансовых активов компании за 5 лет: "&IFERROR(ROUND(AU32*100,2),"")&"%."))&IF(AP32=0,"",IF(AP32="",""," Объем заемных средств компании на конец 2024 года: "&AP32&" тыс. руб."))&IF(AR32=0,"",IF(AR32="",""," ФССП присвоил "&AR32&" уровень риска для данного ПКО.")))) -> ООО ПКО «Вива Коллект» зарегистрировано по адресу: 117218, Москва г, ул Кржижановского, 29, 2, Этаж 2 Помещ VIII. Генеральным директором является Хазиев Азат Рамилевич. Рост доходов компании за 5 лет: 13020,7%. Рост финансовых активов компании за 5 лет: 542,96%. Объем заемных средств компании на конец 2024 года: 787650 тыс. руб. ФССП присвоил Высокий уровень риска для данного ПКО.
A33: 144 | B33: Общество с ограниченной ответственностью «Профессиональная коллекторская организация «Центурион» | C33: 9709079818 | D33: 1227700215467 | E33: ООО ПКО «Центурион» | F33: 44664 | G33: =ROUNDDOWN(($AY$1-F33)/365,0) -> 3 | H33: Нет | I33: =IF(VLOOKUP(C33,гендир!$A$3:$C$3000,3,0)=0,"",VLOOKUP(C33,гендир!$A$3:$C$3000,3,0)) -> Котов Андрей Владимирович | J33: =IF(VLOOKUP(C33,гендир!$A$3:$C$3000,2,0)=0,"",VLOOKUP(C33,гендир!$A$3:$C$3000,2,0)) -> Цыпруш Олег Евгеньевич | K33: 109004, Г.Москва, вн.тер. г. Муниципальный Округ Таганский, ул Николоямская, дом 40/22, строение 4, этаж 1, офис 115 | L33: 10000 | P33: 32 | Q33: 0 | R33: 0 | S33: 24313 | T33: 110183 | U33: 606029 | V33: 0 | W33: 0 | X33: 12968 | Y33: 23819 | Z33: 61213 | AA33: 0 | AB33: 0 | AC33: -37816 | AD33: 5755 | AE33: 472389 | AF33: 0 | AG33: 0 | AH33: 0 | AI33: 0 | AJ33: 0 | AK33: 0 | AL33: 0 | AM33: 80550 | AN33: 123241 | AO33: 823925 | AP33: 234068 | AQ33: =IFERROR(ROUND(IFERROR(U33/Q33,IFERROR(U33/R33,IFERROR(U33/S33,IFERROR(U33/T33,"")))),3),"") -> 24.926 | AR33: Низкий | AS33: centuryon.ru | AT33: =IF(VLOOKUP(C33,old!$D$3:$AU$549,44,0)=0,"",VLOOKUP(C33,old!$D$3:$AU$549,44,0)) -> image414 | AV33: =E33&" зарегистрировано по адресу: "&K33&IF(J33=0,"",IF(J33="","",". Генеральным директором является "&J33&IF(AQ33=0,".",IF(AQ33="",".",". Рост доходов компании за 5 лет: "&ROUND(AQ33*100,2)&"%."))&IF(AU33=0,"",IF(AU33="",""," Рост финансовых активов компании за 5 лет: "&IFERROR(ROUND(AU33*100,2),"")&"%."))&IF(AP33=0,"",IF(AP33="",""," Объем заемных средств компании на конец 2024 года: "&AP33&" тыс. руб."))&IF(AR33=0,"",IF(AR33="",""," ФССП присвоил "&AR33&" уровень риска для данного ПКО.")))) -> ООО ПКО «Центурион» зарегистрировано по адресу: 109004, Г.Москва, вн.тер. г. Муниципальный Округ Таганский, ул Николоямская, дом 40/22, строение 4, этаж 1, офис 115. Генеральным директором является Цыпруш Олег Евгеньевич. Рост доходов компании за 5 лет: 2492,6%. Объем заемных средств компании на конец 2024 года: 234068 тыс. руб. ФССП присвоил Низкий уровень риска для данного ПКО.
A34: 26 | B34: Общество с ограниченной ответственностью Профессиональная коллекторская организация «Столичная Сервисная Компания» | C34: 7705680245 | D34: 1057747813837 | E34: ООО ПКО «ССК» | F34: 38579 | G34: =ROUNDDOWN(($AY$1-F34)/365,0) -> 19 | H34: Да | I34: =IF(VLOOKUP(C34,гендир!$A$3:$C$3000,3,0)=0,"",VLOOKUP(C34,гендир!$A$3:$C$3000,3,0)) -> Общество С Ограниченной Ответственностью Профессиональная Коллекторская Организация, "РЕГИОНАЛЬНАЯ СЛУЖБА ВЗЫСКАНИЯ", Компания С Ограниченной Ответственностью Свеа Экономи Сайпрус Лимитед | J34: =IF(VLOOKUP(C34,гендир!$A$3:$C$3000,2,0)=0,"",VLOOKUP(C34,гендир!$A$3:$C$3000,2,0)) -> Мохначев Дмитрий Вячеславович | K34: 121609, Москва г, б-р Осенний, 23, Помещ. 1 Ком. 20 | L34: 140942.64 | P34: 33 | Q34: 382354 | R34: 488458 | S34: 736047 | T34: 752672 | U34: 570424 | V34: 102589 | W34: 141204 | X34: 248067 | Y34: 398836 | Z34: -231515 | AA34: 102589 | AB34: 241141 | AC34: 338174 | AD34: 244594 | AE34: 297977 | AF34: 209741 | AG34: 1039652 | AH34: 1203798 | AI34: 1255498 | AJ34: 1186700 | AK34: 66040 | AL34: 50814 | AM34: 61197 | AN34: 81722 | AO34: 59874 | AP34: 801048 | AQ34: =IFERROR(ROUND(IFERROR(U34/Q34,IFERROR(U34/R34,IFERROR(U34/S34,IFERROR(U34/T34,"")))),3),"") -> 1.492 | AR34: Низкий | AS34: csc.msk.ru | AT34: =IF(VLOOKUP(C34,old!$D$3:$AU$549,44,0)=0,"",VLOOKUP(C34,old!$D$3:$AU$549,44,0)) -> image012 | AU34: 5.6579305 | AV34: =E34&" зарегистрировано по адресу: "&K34&IF(J34=0,"",IF(J34="","",". Генеральным директором является "&J34&IF(AQ34=0,".",IF(AQ34="",".",". Рост доходов компании за 5 лет: "&ROUND(AQ34*100,2)&"%."))&IF(AU34=0,"",IF(AU34="",""," Рост финансовых активов компании за 5 лет: "&IFERROR(ROUND(AU34*100,2),"")&"%."))&IF(AP34=0,"",IF(AP34="",""," Объем заемных средств компании на конец 2024 года: "&AP34&" тыс. руб."))&IF(AR34=0,"",IF(AR34="",""," ФССП присвоил "&AR34&" уровень риска для данного ПКО.")))) -> ООО ПКО «ССК» зарегистрировано по адресу: 121609, Москва г, б-р Осенний, 23, Помещ. 1 Ком. 20. Генеральным директором является Мохначев Дмитрий Вячеславович. Рост доходов компании за 5 лет: 149,2%. Рост финансовых активов компании за 5 лет: 565,79%. Объем заемных средств компании на конец 2024 года: 801048 тыс. руб. ФССП присвоил Низкий уровень риска для данного ПКО.
A35: 15 | B35: Общество с ограниченной ответственностью Профессиональная коллекторская организация «Столичное агентство по возврату долгов» | C35: 7717528291 | D35: 1057746413922 | E35: ООО ПКО «Столичное АВД» | F35: 38422 | G35: =ROUNDDOWN(($AY$1-F35)/365,0) -> 20 | H35: Да | I35: =IF(VLOOKUP(C35,гендир!$A$3:$C$3000,3,0)=0,"",VLOOKUP(C35,гендир!$A$3:$C$3000,3,0)) -> Курило Дарья Игоревна, Плохов Артем Валерьевич, Цацуа Давид Владимирович | J35: =IF(VLOOKUP(C35,гендир!$A$3:$C$3000,2,0)=0,"",VLOOKUP(C35,гендир!$A$3:$C$3000,2,0)) -> Цацуа Давид Владимирович | K35: 107564, Москва г, ул Краснобогатырская, 2, 2, 5 | L35: 269039.56 | P35: 34 | Q35: 977198 | R35: 736019 | S35: 1355386 | T35: 2090358 | U35: 544338 | V35: 680230 | W35: 331274 | X35: 961053 | Y35: 1747501 | Z35: 163046 | AA35: 680230 | AB35: 12462 | AC35: 115893 | AD35: 21181 | AE35: 21353 | AF35: 28039 | AG35: 121783 | AH35: 345974 | AI35: 141439 | AJ35: 144030 | AK35: 773191 | AL35: 574963 | AM35: 367617 | AN35: 496505 | AO35: 133820 | AP35: 1607 | AQ35: =IFERROR(ROUND(IFERROR(U35/Q35,IFERROR(U35/R35,IFERROR(U35/S35,IFERROR(U35/T35,"")))),3),"") -> 0.557 | AR35: Низкий | AS35: stcollector.ru | AT35: =IF(VLOOKUP(C35,old!$D$3:$AU$549,44,0)=0,"",VLOOKUP(C35,old!$D$3:$AU$549,44,0)) -> image083 | AU35: 5.1367738 | AV35: =E35&" зарегистрировано по адресу: "&K35&IF(J35=0,"",IF(J35="","",". Генеральным директором является "&J35&IF(AQ35=0,".",IF(AQ35="",".",". Рост доходов компании за 5 лет: "&ROUND(AQ35*100,2)&"%."))&IF(AU35=0,"",IF(AU35="",""," Рост финансовых активов компании за 5 лет: "&IFERROR(ROUND(AU35*100,2),"")&"%."))&IF(AP35=0,"",IF(AP35="",""," Объем заемных средств компании на конец 2024 года: "&AP35&" тыс. руб."))&IF(AR35=0,"",IF(AR35="",""," ФССП присвоил "&AR35&" уровень риска для данного ПКО.")))) -> ООО ПКО «Столичное АВД» зарегистрировано по адресу: 107564, Москва г, ул Краснобогатырская, 2, 2, 5. Генеральным директором является Цацуа Давид Владимирович. Рост доходов компании за 5 лет: 55,7%. Рост финансовых активов компании за 5 лет: 513,68%. Объем заемных средств компании на конец 2024 года: 1607 тыс. руб. ФССП присвоил Низкий уровень риска для данного ПКО.
A36: 33 | B36: Общество с ограниченной ответственностью Профессиональная коллекторская организация «Агентство Финансового Контроля" | C36: 7702814010 | D36: 1137746368847 | E36: ООО ПКО «АФК» | F36: 41387 | G36: =ROUNDDOWN(($AY$1-F36)/365,0) -> 12 | H36: Нет | I36: =IF(VLOOKUP(C36,гендир!$A$3:$C$3000,3,0)=0,"",VLOOKUP(C36,гендир!$A$3:$C$3000,3,0)) -> Абдуллин Ринат Шамильевич, Нефедов Михаил Геннадьевич | J36: =IF(VLOOKUP(C36,гендир!$A$3:$C$3000,2,0)=0,"",VLOOKUP(C36,гендир!$A$3:$C$3000,2,0)) -> Шарпов Сергей Викторович | K36: 603087, Нижегородская область, г. Нижний Новгород, ш. Казанское, дом 10, корпус 3, помещение 2 | L36: 10000 | P36: 35 | Q36: 635395 | R36: 629795 | S36: 559685 | T36: 562623 | U36: 540031 | V36: 154566 | W36: 89404 | X36: 92973 | Y36: 112966 | Z36: 121793 | AA36: 154566 | AB36: 436893 | AC36: 384062 | AD36: 367432 | AE36: 351854 | AF36: 239263 | AG36: 275000 | AH36: 221762 | AI36: 180502 | AJ36: 9747 | AK36: 758 | AL36: 1515 | AM36: 45 | AN36: 1022 | AO36: 3844 | AP36: 0 | AQ36: =IFERROR(ROUND(IFERROR(U36/Q36,IFERROR(U36/R36,IFERROR(U36/S36,IFERROR(U36/T36,"")))),3),"") -> 0.85 | AR36: Низкий | AS36: oooafk.ru | AT36: =IF(VLOOKUP(C36,old!$D$3:$AU$549,44,0)=0,"",VLOOKUP(C36,old!$D$3:$AU$549,44,0)) -> image011 | AU36: 0.040737598 | AV36: =E36&" зарегистрировано по адресу: "&K36&IF(J36=0,"",IF(J36="","",". Генеральным директором является "&J36&IF(AQ36=0,".",IF(AQ36="",".",". Рост доходов компании за 5 лет: "&ROUND(AQ36*100,2)&"%."))&IF(AU36=0,"",IF(AU36="",""," Рост финансовых активов компании за 5 лет: "&IFERROR(ROUND(AU36*100,2),"")&"%."))&IF(AP36=0,"",IF(AP36="",""," Объем заемных средств компании на конец 2024 года: "&AP36&" тыс. руб."))&IF(AR36=0,"",IF(AR36="",""," ФССП присвоил "&AR36&" уровень риска для данного ПКО.")))) -> ООО ПКО «АФК» зарегистрировано по адресу: 603087, Нижегородская область, г. Нижний Новгород, ш. Казанское, дом 10, корпус 3, помещение 2. Генеральным директором является Шарпов Сергей Викторович. Рост доходов компании за 5 лет: 85%. Рост финансовых активов компании за 5 лет: 4,07%. ФССП присвоил Низкий уровень риска для данного ПКО.
A37: 40 | B37: Общество с ограниченной ответственностью Профессиональная коллекторская организация «Специализированное Агентство Аналитики и Безопасноти» | C37: 5260410400 | D37: 1155260007209 | E37: ООО ПКО «СААБ» | F37: 42150 | G37: =ROUNDDOWN(($AY$1-F37)/365,0) -> 9 | H37: Нет | I37: =IF(VLOOKUP(C37,гендир!$A$3:$C$3000,3,0)=0,"",VLOOKUP(C37,гендир!$A$3:$C$3000,3,0)) -> Нефедов Михаил Геннадьевич, Абдуллин Ринат Шамильевич | J37: =IF(VLOOKUP(C37,гендир!$A$3:$C$3000,2,0)=0,"",VLOOKUP(C37,гендир!$A$3:$C$3000,2,0)) -> Шарпов Сергей Викторович | K37: 603087, Нижегородская область, г. Нижний Новгород, ш. Казанское, дом 10, корпус 3, помещение 2 | L37: 10000 | P37: 36 | Q37: 365053 | R37: 427720 | S37: 383873 | T37: 401434 | U37: 501099 | V37: 117104 | W37: 125508 | X37: 65026 | Y37: 119225 | Z37: 188415 | AA37: 117104 | AB37: 243562 | AC37: 266071 | AD37: 225881 | AE37: 254445 | AF37: 113821 | AG37: 225000 | AH37: 166310 | AI37: 193164 | AJ37: 73510 | AK37: 11837 | AL37: 11785 | AM37: 10954 | AN37: 11422 | AO37: 17746 | AP37: 0 | AQ37: =IFERROR(ROUND(IFERROR(U37/Q37,IFERROR(U37/R37,IFERROR(U37/S37,IFERROR(U37/T37,"")))),3),"") -> 1.373 | AR37: Низкий | AS37: ooosaab.ru | AT37: =IF(VLOOKUP(C37,old!$D$3:$AU$549,44,0)=0,"",VLOOKUP(C37,old!$D$3:$AU$549,44,0)) -> image016 | AU37: 0.64583864 | AV37: =E37&" зарегистрировано по адресу: "&K37&IF(J37=0,"",IF(J37="","",". Генеральным директором является "&J37&IF(AQ37=0,".",IF(AQ37="",".",". Рост доходов компании за 5 лет: "&ROUND(AQ37*100,2)&"%."))&IF(AU37=0,"",IF(AU37="",""," Рост финансовых активов компании за 5 лет: "&IFERROR(ROUND(AU37*100,2),"")&"%."))&IF(AP37=0,"",IF(AP37="",""," Объем заемных средств компании на конец 2024 года: "&AP37&" тыс. руб."))&IF(AR37=0,"",IF(AR37="",""," ФССП присвоил "&AR37&" уровень риска для данного ПКО.")))) -> ООО ПКО «СААБ» зарегистрировано по адресу: 603087, Нижегородская область, г. Нижний Новгород, ш. Казанское, дом 10, корпус 3, помещение 2. Генеральным директором является Шарпов Сергей Викторович. Рост доходов компании за 5 лет: 137,3%. Рост финансовых активов компании за 5 лет: 64,58%. ФССП присвоил Низкий уровень риска для данного ПКО.
A38: 35 | B38: Общество с ограниченной ответственностью профессиональная коллекторская организация «СпецСнаб71» | C38: 6230085345 | D38: 1146230003127 | E38: ООО ПКО «СпецСнаб71» | F38: 41838 | G38: =ROUNDDOWN(($AY$1-F38)/365,0) -> 10 | H38: Нет | I38: =IF(VLOOKUP(C38,гендир!$A$3:$C$3000,3,0)=0,"",VLOOKUP(C38,гендир!$A$3:$C$3000,3,0)) -> Сазонов Сергей Владимирович | J38: =IF(VLOOKUP(C38,гендир!$A$3:$C$3000,2,0)=0,"",VLOOKUP(C38,гендир!$A$3:$C$3000,2,0)) -> Сазонов Сергей Владимирович | K38: 390000, Рязанская область, г.о. город Рязань, г Рязань, ул Урицкого, д. 46, д.помещ. Н 48 | L38: 30020 | P38: 37 | Q38: 308809 | R38: 392415 | S38: 502955 | T38: 550947 | U38: 489090 | V38: 230799 | W38: 277288 | X38: 292047 | Y38: 211587 | Z38: 157694 | AA38: 230799 | AB38: 5839 | AC38: 44057 | AD38: 147361 | AE38: 112229 | AF38: 791892 | AG38: 167239 | AH38: 246793 | AI38: 286869 | AJ38: 277540 | AK38: 104429 | AL38: 199034 | AM38: 144331 | AN38: 218540 | AO38: 110614 | AP38: 220728 | AQ38: =IFERROR(ROUND(IFERROR(U38/Q38,IFERROR(U38/R38,IFERROR(U38/S38,IFERROR(U38/T38,"")))),3),"") -> 1.584 | AR38: Значительный | AS38: specsnab71.ru | AT38: =IF(VLOOKUP(C38,old!$D$3:$AU$549,44,0)=0,"",VLOOKUP(C38,old!$D$3:$AU$549,44,0)) -> image136 | AU38: 0.35047709 | AV38: =E38&" зарегистрировано по адресу: "&K38&IF(J38=0,"",IF(J38="","",". Генеральным директором является "&J38&IF(AQ38=0,".",IF(AQ38="",".",". Рост доходов компании за 5 лет: "&ROUND(AQ38*100,2)&"%."))&IF(AU38=0,"",IF(AU38="",""," Рост финансовых активов компании за 5 лет: "&IFERROR(ROUND(AU38*100,2),"")&"%."))&IF(AP38=0,"",IF(AP38="",""," Объем заемных средств компании на конец 2024 года: "&AP38&" тыс. руб."))&IF(AR38=0,"",IF(AR38="",""," ФССП присвоил "&AR38&" уровень риска для данного ПКО.")))) -> ООО ПКО «СпецСнаб71» зарегистрировано по адресу: 390000, Рязанская область, г.о. город Рязань, г Рязань, ул Урицкого, д. 46, д.помещ. Н 48. Генеральным директором является Сазонов Сергей Владимирович. Рост доходов компании за 5 лет: 158,4%. Рост финансовых активов компании за 5 лет: 35,05%. Объем заемных средств компании на конец 2024 года: 220728 тыс. руб. ФССП присвоил Значительный уровень риска для данного ПКО.
A39: 23 | B39: Общество с ограниченной ответственностью Профессиональная коллекторская организация "Агентство кредитных решений» | C39: 9702030161 | D39: 1217700089386 | E39: ООО ПКО «АКР» | F39: 44256 | G39: =ROUNDDOWN(($AY$1-F39)/365,0) -> 4 | H39: Да | I39: =IF(VLOOKUP(C39,гендир!$A$3:$C$3000,3,0)=0,"",VLOOKUP(C39,гендир!$A$3:$C$3000,3,0)) -> Общество С Ограниченной Ответственностью, "РЕАЛЬНЫЕ ИНВЕСТИЦИИ" | J39: =IF(VLOOKUP(C39,гендир!$A$3:$C$3000,2,0)=0,"",VLOOKUP(C39,гендир!$A$3:$C$3000,2,0)) -> Маршинин Денис Владимирович | K39: 129090, Москва г, пер Ботанический, 5, Этаж 5 Помещ. XV/Ком. 17к | L39: 100 | P39: 38 | Q39: 0 | R39: 174839 | S39: 263772 | T39: 944874 | U39: 455341 | V39: 0 | W39: -91556 | X39: -160715 | Y39: -876761 | Z39: 330891 | AA39: 0 | AB39: 53833 | AC39: 83716 | AD39: 1230 | AE39: 69259 | AF39: 0 | AG39: 105955 | AH39: 53341 | AI39: 96423 | AJ39: 76411 | AK39: 0 | AL39: 1281 | AM39: 6172 | AN39: 37432 | AO39: 6247 | AP39: 53183 | AQ39: =IFERROR(ROUND(IFERROR(U39/Q39,IFERROR(U39/R39,IFERROR(U39/S39,IFERROR(U39/T39,"")))),3),"") -> 2.604 | AR39: Низкий | AS39: csa.com.ru | AT39: =IF(VLOOKUP(C39,old!$D$3:$AU$549,44,0)=0,"",VLOOKUP(C39,old!$D$3:$AU$549,44,0)) -> image007 | AU39: 0.72116465 | AV39: =E39&" зарегистрировано по адресу: "&K39&IF(J39=0,"",IF(J39="","",". Генеральным директором является "&J39&IF(AQ39=0,".",IF(AQ39="",".",". Рост доходов компании за 5 лет: "&ROUND(AQ39*100,2)&"%."))&IF(AU39=0,"",IF(AU39="",""," Рост финансовых активов компании за 5 лет: "&IFERROR(ROUND(AU39*100,2),"")&"%."))&IF(AP39=0,"",IF(AP39="",""," Объем заемных средств компании на конец 2024 года: "&AP39&" тыс. руб."))&IF(AR39=0,"",IF(AR39="",""," ФССП присвоил "&AR39&" уровень риска для данного ПКО.")))) -> ООО ПКО «АКР» зарегистрировано по адресу: 129090, Москва г, пер Ботанический, 5, Этаж 5 Помещ. XV/Ком. 17к. Генеральным директором является Маршинин Денис Владимирович. Рост доходов компании за 5 лет: 260,4%. Рост финансовых активов компании за 5 лет: 72,12%. Объем заемных средств компании на конец 2024 года: 53183 тыс. руб. ФССП присвоил Низкий уровень риска для данного ПКО.
A40: 85 | B40: Общество с ограниченной ответственностью Профессиональная коллекторская организация «СВД» | C40: 1831191109 | D40: 1181832017058 | E40: ООО ПКО «СВД» | F40: 43307 | G40: =ROUNDDOWN(($AY$1-F40)/365,0) -> 6 | H40: Нет | I40: =IF(VLOOKUP(C40,гендир!$A$3:$C$3000,3,0)=0,"",VLOOKUP(C40,гендир!$A$3:$C$3000,3,0)) -> Колпаков Владислав Юрьевич, Общество С Ограниченной Ответственностью, "АГЕНТСТВО+" | J40: =IF(VLOOKUP(C40,гендир!$A$3:$C$3000,2,0)=0,"",VLOOKUP(C40,гендир!$A$3:$C$3000,2,0)) -> Мякишев Иван Владимирович | K40: 426008, Удмуртская Респ, г Ижевск, ул Пушкинская, 266, 302 | L40: 10500 | P40: 39 | Q40: 270534 | R40: 658417 | S40: 201057 | T40: 175550 | U40: 443384 | V40: 209888 | W40: 405611 | X40: 69008 | Y40: 352717 | Z40: 440631 | AA40: 209888 | AB40: 284437 | AC40: 152533 | AD40: -206080 | AE40: -29898 | AF40: 398653 | AG40: 656911 | AH40: 491625 | AI40: 251282 | AJ40: 124421 | AK40: 21567 | AL40: 65968 | AM40: 109735 | AN40: 114211 | AO40: 164107 | AP40: 122258 | AQ40: =IFERROR(ROUND(IFERROR(U40/Q40,IFERROR(U40/R40,IFERROR(U40/S40,IFERROR(U40/T40,"")))),3),"") -> 1.639 | AR40: 0 | AS40: svd18.ru | AT40: =IF(VLOOKUP(C40,old!$D$3:$AU$549,44,0)=0,"",VLOOKUP(C40,old!$D$3:$AU$549,44,0)) -> image249 | AU40: 0.31210351 | AV40: =E40&" зарегистрировано по адресу: "&K40&IF(J40=0,"",IF(J40="","",". Генеральным директором является "&J40&IF(AQ40=0,".",IF(AQ40="",".",". Рост доходов компании за 5 лет: "&ROUND(AQ40*100,2)&"%."))&IF(AU40=0,"",IF(AU40="",""," Рост финансовых активов компании за 5 лет: "&IFERROR(ROUND(AU40*100,2),"")&"%."))&IF(AP40=0,"",IF(AP40="",""," Объем заемных средств компании на конец 2024 года: "&AP40&" тыс. руб."))&IF(AR40=0,"",IF(AR40="",""," ФССП присвоил "&AR40&" уровень риска для данного ПКО.")))) -> ООО ПКО «СВД» зарегистрировано по адресу: 426008, Удмуртская Респ, г Ижевск, ул Пушкинская, 266, 302. Генеральным директором является Мякишев Иван Владимирович. Рост доходов компании за 5 лет: 163,9%. Рост финансовых активов компании за 5 лет: 31,21%. Объем заемных средств компании на конец 2024 года: 122258 тыс. руб.
A41: 45 | B41: Общество с ограниченной ответственностью профессиональная коллекторская организация«Долг-контроль» | C41: 2465304196 | D41: 1132468067621 | E41: ООО ПКО «Долг-контроль» | F41: 41620 | G41: =ROUNDDOWN(($AY$1-F41)/365,0) -> 11 | H41: Нет | I41: =IF(VLOOKUP(C41,гендир!$A$3:$C$3000,3,0)=0,"",VLOOKUP(C41,гендир!$A$3:$C$3000,3,0)) -> Черкасов Александр Николаевич, Карпова Елена Степановна | J41: =IF(VLOOKUP(C41,гендир!$A$3:$C$3000,2,0)=0,"",VLOOKUP(C41,гендир!$A$3:$C$3000,2,0)) -> Черкасов Александр Николаевич | K41: 660022, Красноярский край, Красноярск г, Партизана Железняка ул, дом № 18, офис 521 | L41: 2620 | P41: 40 | Q41: 110741 | R41: 251213 | S41: 269950 | T41: 350182 | U41: 424801 | V41: 2551 | W41: 20815 | X41: 30527 | Y41: 19705 | Z41: 91330 | AA41: 2551 | AB41: 91250 | AC41: 89833 | AD41: 131236 | AE41: 135382 | AF41: 126711 | AG41: 189140 | AH41: 169385 | AI41: 235618 | AJ41: 206249 | AK41: 12116 | AL41: 13161 | AM41: 11 | AN41: 2124 | AO41: 64337 | AP41: 0 | AQ41: =IFERROR(ROUND(IFERROR(U41/Q41,IFERROR(U41/R41,IFERROR(U41/S41,IFERROR(U41/T41,"")))),3),"") -> 3.836 | AR41: Низкий | AS41: dolgkontol.ru | AT41: =IF(VLOOKUP(C41,old!$D$3:$AU$549,44,0)=0,"",VLOOKUP(C41,old!$D$3:$AU$549,44,0)) -> image010 | AU41: 1.6277119 | AV41: =E41&" зарегистрировано по адресу: "&K41&IF(J41=0,"",IF(J41="","",". Генеральным директором является "&J41&IF(AQ41=0,".",IF(AQ41="",".",". Рост доходов компании за 5 лет: "&ROUND(AQ41*100,2)&"%."))&IF(AU41=0,"",IF(AU41="",""," Рост финансовых активов компании за 5 лет: "&IFERROR(ROUND(AU41*100,2),"")&"%."))&IF(AP41=0,"",IF(AP41="",""," Объем заемных средств компании на конец 2024 года: "&AP41&" тыс. руб."))&IF(AR41=0,"",IF(AR41="",""," ФССП присвоил "&AR41&" уровень риска для данного ПКО.")))) -> ООО ПКО «Долг-контроль» зарегистрировано по адресу: 660022, Красноярский край, Красноярск г, Партизана Железняка ул, дом № 18, офис 521. Генеральным директором является Черкасов Александр Николаевич. Рост доходов компании за 5 лет: 383,6%. Рост финансовых активов компании за 5 лет: 162,77%. ФССП присвоил Низкий уровень риска для данного ПКО.
A42: 38 | B42: Общество с ограниченной ответственностью «Агентство Региональная организация по сбору долгов» | C42: 7704724468 | D42: 1097746191410 | E42: ООО «Агентство Р.О.С.долгЪ» | F42: 39906 | G42: =ROUNDDOWN(($AY$1-F42)/365,0) -> 16 | H42: Нет | I42: =IF(VLOOKUP(C42,гендир!$A$3:$C$3000,3,0)=0,"",VLOOKUP(C42,гендир!$A$3:$C$3000,3,0)) -> Общество С Ограниченной Ответственностью, "МЭС-РАЗВИТИЕ" | J42: =IF(VLOOKUP(C42,гендир!$A$3:$C$3000,2,0)=0,"",VLOOKUP(C42,гендир!$A$3:$C$3000,2,0)) -> Железнов Андрей Вячеславович | K42: 121069, Город Москва, ул. Поварская, дом 31/29, помещение VI, комната 3 | L42: 1001 | P42: 41 | Q42: 230817 | R42: 229515 | S42: 278140 | T42: 428400 | U42: 419680 | V42: 6832 | W42: 3415 | X42: 10740 | Y42: 278257 | Z42: 136327 | AA42: 6832 | AB42: 69011 | AC42: 64555 | AD42: 109788 | AE42: 129021 | AF42: 78860 | AG42: 70959 | AH42: 68232 | AI42: 0 | AJ42: 30000 | AK42: 73455 | AL42: 55962 | AM42: 74618 | AN42: 106955 | AO42: 111320 | AP42: 10350 | AQ42: =IFERROR(ROUND(IFERROR(U42/Q42,IFERROR(U42/R42,IFERROR(U42/S42,IFERROR(U42/T42,"")))),3),"") -> 1.818 | AR42: Низкий | AS42: rosdolg.com | AT42: =IF(VLOOKUP(C42,old!$D$3:$AU$549,44,0)=0,"",VLOOKUP(C42,old!$D$3:$AU$549,44,0)) -> image145 | AU42: 0.380421 | AV42: =E42&" зарегистрировано по адресу: "&K42&IF(J42=0,"",IF(J42="","",". Генеральным директором является "&J42&IF(AQ42=0,".",IF(AQ42="",".",". Рост доходов компании за 5 лет: "&ROUND(AQ42*100,2)&"%."))&IF(AU42=0,"",IF(AU42="",""," Рост финансовых активов компании за 5 лет: "&IFERROR(ROUND(AU42*100,2),"")&"%."))&IF(AP42=0,"",IF(AP42="",""," Объем заемных средств компании на конец 2024 года: "&AP42&" тыс. руб."))&IF(AR42=0,"",IF(AR42="",""," ФССП присвоил "&AR42&" уровень риска для данного ПКО.")))) -> ООО «Агентство Р.О.С.долгЪ» зарегистрировано по адресу: 121069, Город Москва, ул. Поварская, дом 31/29, помещение VI, комната 3. Генеральным директором является Железнов Андрей Вячеславович. Рост доходов компании за 5 лет: 181,8%. Рост финансовых активов компании за 5 лет: 38,04%. Объем заемных средств компании на конец 2024 года: 10350 тыс. руб. ФССП присвоил Низкий уровень риска для данного ПКО.
